Workbook

Sheet Website_README
A1: Interactive website package - data and methodology
A3: Package purpose | B3: Back-up data for the GitHub Pages website. The interactive chart links each overlap bubble to the exact overlap units and relevant programs.
A4: Matched portfolio snapshot | B4: AstraZeneca 10 Feb 2026 and BMS 5 Feb 2026 pipeline disclosures.
A5: Late-stage program definition | B5: Unique lead investigational asset in Phase II or Phase III/pivotal/registration development; approved-indication expansions and major lifecycle-management programs excluded from the core count.
A6: Overlap count definition | B6: Number of distinct shared indication territories, modality classes, target/mechanism themes, or development-stage bands - not all possible AZ-BMS asset-pair permutations.
A7: Launch window | B7: Illustrative analyst scenario calculated from trial primary-completion year plus a stage-specific lag. It is not company guidance, a probability-adjusted forecast, or a regulatory prediction.
A8: Historical sales | B8: Investigational assets have no historical sales. The Commercial_Benchmarks sheet provides company-reported brand revenue for scale context; figures are generally not indication-specific.
A9: Website deployment | B9: Upload the package contents to a GitHub repository and enable GitHub Pages from the main branch / root folder. No build step is required.
A11: Fit-vs-collision matrix | B11: Analyst-normalized indication-territory × modality-family map. AZ-only/BMS-only cells show complementarity; overlap cells show collision. The map does not capture earlier-stage, marketed or undisclosed programs.
A13: v4 update | B13: Program rows now show approved brands or marketed components where available. Sales trend cards separate reported history (solid) from analyst projections (dashed), with disclosed patent / exclusivity events reflected in the scenarios.

Sheet README
A1: AstraZeneca + BMS: Portfolio Fit—or Collision?
A3: Purpose
A4: Backup workbook for a LinkedIn post examining where AstraZeneca and Bristol Myers Squibb have overlapping versus complementary late-stage R&D portfolios.
A7: Headline findings
A8: 1. The shared areas contain 41 of 62 mapped programs (66%), concentrated in solid-tumor oncology, hematology, immunology/respiratory/fibrosis and cardiovascular disease.
A9: 2. Oncology is the clearest collision zone: 18 solid-tumor programs plus 8 hematology programs across the two companies.
A10: 3. Complementarity is strongest outside oncology: AstraZeneca adds rare disease, renal/metabolic and infectious-disease breadth; BMS adds a distinct neuroscience foothold.
A11: 4. Counts show portfolio breadth—not program quality, probability of success, revenue potential, target-level duplication or antitrust risk.
A14: Methodology
A15: Snapshot dates | B15: AstraZeneca: 10 Feb 2026; BMS: 5 Feb 2026. Matching annual-report snapshots were used to improve comparability.
A16: Included | B16: Lead investigational assets or disclosed lead programs in Phase II or Phase III/pivotal/registration.
A17: Excluded | B17: Approved indications, additional indications for marketed products, and AstraZeneca significant life-cycle-management tables.
A18: Deduplication | B18: The same lead asset is counted once at its highest disclosed phase; multiple indications and combinations are consolidated under the lead investigational asset.
A19: Normalization | B19: Company therapy areas were harmonized into eight cross-company categories. AstraZeneca oncology assets were classified as solid-tumor oncology or hematology based on disclosed areas under investigation.
A20: Interpretation | B20: A “shared” category means both companies have late-stage activity in the broad therapeutic area; it does not prove direct mechanism, indication or asset duplication.
A23: Important current-event caveat
A24: Reuters reported on Aug. 5, 2026 that a senior source said there were no ongoing discussions between the companies. The analysis is therefore framed as a portfolio thought experiment, not an announced transaction.
A27: Stacked-footprint + count-based lollipop update
A28: The chart restores the stacked late-stage program bars above each disease area. AstraZeneca and BMS use logo-inspired company colors; bubble size and number show distinct overlap count, while red tone shows analyst-coded directness. Portfolio balance remains excluded.
A29: Reproduction: the Plot_Data tab feeds the R and Python scripts; the Visual_Settings tab records the exact palette and visual encodings.

Sheet Asset_Data
A1: Company | B1: Source therapeutic area | C1: Normalized area | D1: Lead investigational asset / program | E1: Highest disclosed phase in snapshot | F1: Modality / mechanism | G1: Representative area(s) under investigation | H1: Source snapshot date | I1: Source URL | J1: Methodology notes | K1: Brand / marketed component | L1: Brand relationship | M1: Sales trend IDs
A2: AstraZeneca | B2: Oncology | C2: Solid-tumor oncology | D2: AZD9574 | E2: Phase II | F2: PARP1 inhibitor | G2: Advanced solid malignancies | H2: 2026-02-10 | I2: https://www.astrazeneca.com/content/dam/az/Investor_Relations/annual-report-2025/pdf/AstraZeneca_Development_Pipeline_2025.pdf
A3: AstraZeneca | B3: Oncology | C3: Solid-tumor oncology | D3: camizestrant | E3: Phase III / registration | F3: Next-generation oral SERD | G3: HR+/HER2- breast cancer, including advanced and adjuvant settings | H3: 2026-02-10 | I3: https://www.astrazeneca.com/content/dam/az/Investor_Relations/annual-report-2025/pdf/AstraZeneca_Development_Pipeline_2025.pdf | J3: Combination trials counted once under the lead investigational asset. | K3: Etcamah | L3: Approved brand for camizestrant (EU and Japan, 2026) | M3: ETCAMAH
A4: AstraZeneca | B4: Oncology | C4: Solid-tumor oncology | D4: FPI-2265 | E4: Phase II | F4: PSMA-targeted actinium radioconjugate | G4: Prostate cancer | H4: 2026-02-10 | I4: https://www.astrazeneca.com/content/dam/az/Investor_Relations/annual-report-2025/pdf/AstraZeneca_Development_Pipeline_2025.pdf
A5: AstraZeneca | B5: Oncology | C5: Solid-tumor oncology | D5: IPH5201 | E5: Phase II | F5: CD39 monoclonal antibody | G5: Neoadjuvant/adjuvant NSCLC; listed in combination with Imfinzi | H5: 2026-02-10 | I5: https://www.astrazeneca.com/content/dam/az/Investor_Relations/annual-report-2025/pdf/AstraZeneca_Development_Pipeline_2025.pdf | J5: Marketed combination backbone excluded from the asset count. | K5: Imfinzi | L5: Marketed combination backbone: Imfinzi (durvalumab) | M5: IMFINZI
A6: AstraZeneca | B6: Oncology | C6: Solid-tumor oncology | D6: puxitatug samrotecan | E6: Phase III | F6: B7-H4 TOP1i antibody-drug conjugate | G6: Solid tumors; Phase III endometrial cancer program | H6: 2026-02-10 | I6: https://www.astrazeneca.com/content/dam/az/Investor_Relations/annual-report-2025/pdf/AstraZeneca_Development_Pipeline_2025.pdf
A7: AstraZeneca | B7: Oncology | C7: Solid-tumor oncology | D7: rilvegostomig | E7: Phase III | F7: PD-1/TIGIT bispecific antibody | G7: NSCLC, HCC, gastric, biliary and other solid tumors | H7: 2026-02-10 | I7: https://www.astrazeneca.com/content/dam/az/Investor_Relations/annual-report-2025/pdf/AstraZeneca_Development_Pipeline_2025.pdf | J7: Multiple combinations and indications counted once under the lead asset.
A8: AstraZeneca | B8: Oncology | C8: Solid-tumor oncology | D8: saruparib | E8: Phase III | F8: PARP1 inhibitor | G8: Prostate and breast cancer programs | H8: 2026-02-10 | I8: https://www.astrazeneca.com/content/dam/az/Investor_Relations/annual-report-2025/pdf/AstraZeneca_Development_Pipeline_2025.pdf | J8: Multiple combinations and indications counted once under the lead asset.
A9: AstraZeneca | B9: Oncology | C9: Solid-tumor oncology | D9: sonesitatug vedotin | E9: Phase III | F9: CLDN18.2 MMAE antibody-drug conjugate | G9: Solid tumors; Phase III gastric cancer program | H9: 2026-02-10 | I9: https://www.astrazeneca.com/content/dam/az/Investor_Relations/annual-report-2025/pdf/AstraZeneca_Development_Pipeline_2025.pdf
A10: AstraZeneca | B10: Oncology | C10: Solid-tumor oncology | D10: tilatamig samrotecan | E10: Phase II | F10: EGFR/cMET TOP1i antibody-drug conjugate | G10: Solid tumors | H10: 2026-02-10 | I10: https://www.astrazeneca.com/content/dam/az/Investor_Relations/annual-report-2025/pdf/AstraZeneca_Development_Pipeline_2025.pdf
A11: AstraZeneca | B11: Oncology | C11: Solid-tumor oncology | D11: torvutatug samrotecan (AZD5335) | E11: Phase III | F11: FR-alpha TOP1i antibody-drug conjugate | G11: Ovarian cancer and other solid tumors | H11: 2026-02-10 | I11: https://www.astrazeneca.com/content/dam/az/Investor_Relations/annual-report-2025/pdf/AstraZeneca_Development_Pipeline_2025.pdf
A12: AstraZeneca | B12: Oncology | C12: Solid-tumor oncology | D12: volrustomig | E12: Phase III | F12: PD-1/CTLA-4 bispecific antibody | G12: NSCLC, cervical, head and neck, colorectal and mesothelioma | H12: 2026-02-10 | I12: https://www.astrazeneca.com/content/dam/az/Investor_Relations/annual-report-2025/pdf/AstraZeneca_Development_Pipeline_2025.pdf | J12: Multiple indications counted once under the lead asset.
A13: AstraZeneca | B13: Oncology | C13: Hematology | D13: AZD0120 | E13: Phase II | F13: CD19/BCMA CAR-T | G13: Multiple myeloma | H13: 2026-02-10 | I13: https://www.astrazeneca.com/content/dam/az/Investor_Relations/annual-report-2025/pdf/AstraZeneca_Development_Pipeline_2025.pdf
A14: AstraZeneca | B14: Oncology | C14: Hematology | D14: AZD0305 | E14: Phase II | F14: GPRC5D MMAE antibody-drug conjugate | G14: Relapsed/refractory multiple myeloma | H14: 2026-02-10 | I14: https://www.astrazeneca.com/content/dam/az/Investor_Relations/annual-report-2025/pdf/AstraZeneca_Development_Pipeline_2025.pdf
A15: AstraZeneca | B15: Oncology | C15: Hematology | D15: AZD3470 | E15: Phase II | F15: PRMT5 inhibitor | G15: Classical Hodgkin lymphoma; also early solid-tumor work | H15: 2026-02-10 | I15: https://www.astrazeneca.com/content/dam/az/Investor_Relations/annual-report-2025/pdf/AstraZeneca_Development_Pipeline_2025.pdf | J15: Classified to hematology based on the disclosed Phase II indication.
A16: AstraZeneca | B16: Oncology | C16: Hematology | D16: surovatamig | E16: Phase III | F16: CD19/CD3 T-cell engager | G16: B-cell malignancies including DLBCL, follicular lymphoma and B-ALL | H16: 2026-02-10 | I16: https://www.astrazeneca.com/content/dam/az/Investor_Relations/annual-report-2025/pdf/AstraZeneca_Development_Pipeline_2025.pdf | J16: Multiple indications counted once under the lead asset.
A17: AstraZeneca | B17: Respiratory & Immunology | C17: Immunology, respiratory & fibrosis | D17: atuliflapon | E17: Phase II | F17: FLAP inhibitor | G17: Asthma | H17: 2026-02-10 | I17: https://www.astrazeneca.com/content/dam/az/Investor_Relations/annual-report-2025/pdf/AstraZeneca_Development_Pipeline_2025.pdf
A18: AstraZeneca | B18: Respiratory & Immunology | C18: Immunology, respiratory & fibrosis | D18: AZD1163 | E18: Phase II | F18: PAD2/4 bispecific antibody | G18: Rheumatoid arthritis | H18: 2026-02-10 | I18: https://www.astrazeneca.com/content/dam/az/Investor_Relations/annual-report-2025/pdf/AstraZeneca_Development_Pipeline_2025.pdf
A19: AstraZeneca | B19: Respiratory & Immunology | C19: Immunology, respiratory & fibrosis | D19: AZD4604 | E19: Phase II | F19: Inhaled JAK1 inhibitor | G19: Asthma | H19: 2026-02-10 | I19: https://www.astrazeneca.com/content/dam/az/Investor_Relations/annual-report-2025/pdf/AstraZeneca_Development_Pipeline_2025.pdf
A20: AstraZeneca | B20: Respiratory & Immunology | C20: Immunology, respiratory & fibrosis | D20: AZD6793 | E20: Phase II | F20: IRAK4 inhibitor | G20: COPD | H20: 2026-02-10 | I20: https://www.astrazeneca.com/content/dam/az/Investor_Relations/annual-report-2025/pdf/AstraZeneca_Development_Pipeline_2025.pdf
A21: AstraZeneca | B21: Respiratory & Immunology | C21: Immunology, respiratory & fibrosis | D21: AZD7798 | E21: Phase II | F21: T-cell-subset-targeting monoclonal antibody | G21: Crohn's disease | H21: 2026-02-10 | I21: https://www.astrazeneca.com/content/dam/az/Investor_Relations/annual-report-2025/pdf/AstraZeneca_Development_Pipeline_2025.pdf
A22: AstraZeneca | B22: Respiratory & Immunology | C22: Immunology, respiratory & fibrosis | D22: AZD8630 | E22: Phase II | F22: Inhaled TSLP Fab | G22: Asthma | H22: 2026-02-10 | I22: https://www.astrazeneca.com/content/dam/az/Investor_Relations/annual-report-2025/pdf/AstraZeneca_Development_Pipeline_2025.pdf
A23: AstraZeneca | B23: Respiratory & Immunology | C23: Immunology, respiratory & fibrosis | D23: tozorakimab | E23: Phase III | F23: IL-33 monoclonal antibody | G23: COPD and severe viral lower respiratory tract disease | H23: 2026-02-10 | I23: https://www.astrazeneca.com/content/dam/az/Investor_Relations/annual-report-2025/pdf/AstraZeneca_Development_Pipeline_2025.pdf
A24: AstraZeneca | B24: CVRM | C24: Cardiovascular | D24: AZD5462 | E24: Phase II | F24: RXFP1 agonist | G24: Heart failure | H24: 2026-02-10 | I24: https://www.astrazeneca.com/content/dam/az/Investor_Relations/annual-report-2025/pdf/AstraZeneca_Development_Pipeline_2025.pdf
A25: AstraZeneca | B25: CVRM | C25: Cardiovascular | D25: baxdrostat | E25: Phase III / registration | F25: Aldosterone synthase inhibitor | G25: Hypertension and primary aldosteronism | H25: 2026-02-10 | I25: https://www.astrazeneca.com/content/dam/az/Investor_Relations/annual-report-2025/pdf/AstraZeneca_Development_Pipeline_2025.pdf | J25: Programs with dapagliflozin counted once under baxdrostat. | K25: Baxfendy | L25: Approved brand for baxdrostat (US, 2026) | M25: BAXFENDY
A26: AstraZeneca | B26: CVRM | C26: Cardiovascular | D26: laroprovstat | E26: Phase III | F26: PCSK9 inhibitor | G26: Dyslipidemia | H26: 2026-02-10 | I26: https://www.astrazeneca.com/content/dam/az/Investor_Relations/annual-report-2025/pdf/AstraZeneca_Development_Pipeline_2025.pdf
A27: AstraZeneca | B27: CVRM | C27: Renal & metabolic | D27: AZD2389 | E27: Phase II | F27: Anti-fibrotic mechanism | G27: Metabolic dysfunction-associated steatohepatitis | H27: 2026-02-10 | I27: https://www.astrazeneca.com/content/dam/az/Investor_Relations/annual-report-2025/pdf/AstraZeneca_Development_Pipeline_2025.pdf
A28: AstraZeneca | B28: CVRM | C28: Renal & metabolic | D28: AZD6234 | E28: Phase II | F28: Peptide therapy | G28: Chronic weight management | H28: 2026-02-10 | I28: https://www.astrazeneca.com/content/dam/az/Investor_Relations/annual-report-2025/pdf/AstraZeneca_Development_Pipeline_2025.pdf
A29: AstraZeneca | B29: CVRM | C29: Renal & metabolic | D29: AZD9550 + AZD6234 | E29: Phase II | F29: GLP-1/glucagon dual agonist plus amylin agonist | G29: Obesity | H29: 2026-02-10 | I29: https://www.astrazeneca.com/content/dam/az/Investor_Relations/annual-report-2025/pdf/AstraZeneca_Development_Pipeline_2025.pdf | J29: Two-investigational-asset combination counted as one disclosed program.
A30: AstraZeneca | B30: CVRM | C30: Renal & metabolic | D30: balcinrenone / dapagliflozin | E30: Phase III | F30: Mineralocorticoid receptor modulator plus SGLT2 inhibitor | G30: CKD and heart failure with CKD | H30: 2026-02-10 | I30: https://www.astrazeneca.com/content/dam/az/Investor_Relations/annual-report-2025/pdf/AstraZeneca_Development_Pipeline_2025.pdf | K30: Farxiga / Forxiga | L30: Marketed component: dapagliflozin | M30: FARXIGA
A31: AstraZeneca | B31: CVRM | C31: Renal & metabolic | D31: elecoglipron (AZD5004) | E31: Phase II | F31: Oral GLP-1 receptor agonist | G31: Type 2 diabetes and chronic weight management | H31: 2026-02-10 | I31: https://www.astrazeneca.com/content/dam/az/Investor_Relations/annual-report-2025/pdf/AstraZeneca_Development_Pipeline_2025.pdf
A32: AstraZeneca | B32: CVRM | C32: Renal & metabolic | D32: opemalirsen | E32: Phase II | F32: Podocyte-health therapeutic | G32: Nephropathy | H32: 2026-02-10 | I32: https://www.astrazeneca.com/content/dam/az/Investor_Relations/annual-report-2025/pdf/AstraZeneca_Development_Pipeline_2025.pdf
A33: AstraZeneca | B33: CVRM | C33: Renal & metabolic | D33: zibotentan / dapagliflozin | E33: Phase III | F33: Endothelin-A receptor antagonist plus SGLT2 inhibitor | G33: CKD with high proteinuria | H33: 2026-02-10 | I33: https://www.astrazeneca.com/content/dam/az/Investor_Relations/annual-report-2025/pdf/AstraZeneca_Development_Pipeline_2025.pdf | K33: Farxiga / Forxiga | L33: Marketed component: dapagliflozin | M33: FARXIGA
A34: AstraZeneca | B34: Rare Disease | C34: Rare disease | D34: ALXN1920 | E34: Phase II | F34: Kidney-targeted factor H fusion protein | G34: Primary membranous nephropathy | H34: 2026-02-10 | I34: https://www.astrazeneca.com/content/dam/az/Investor_Relations/annual-report-2025/pdf/AstraZeneca_Development_Pipeline_2025.pdf
A35: AstraZeneca | B35: Rare Disease | C35: Rare disease | D35: ALXN2030 | E35: Phase II | F35: Complement C3-targeting siRNA | G35: Antibody-mediated rejection | H35: 2026-02-10 | I35: https://www.astrazeneca.com/content/dam/az/Investor_Relations/annual-report-2025/pdf/AstraZeneca_Development_Pipeline_2025.pdf
A36: AstraZeneca | B36: Rare Disease | C36: Rare disease | D36: ALXN2420 | E36: Phase II | F36: Growth hormone receptor antagonist | G36: Acromegaly | H36: 2026-02-10 | I36: https://www.astrazeneca.com/content/dam/az/Investor_Relations/annual-report-2025/pdf/AstraZeneca_Development_Pipeline_2025.pdf
A37: AstraZeneca | B37: Rare Disease | C37: Rare disease | D37: tarperprumig | E37: Phase II | F37: Kinase inhibitor | G37: ANCA-associated vasculitis | H37: 2026-02-10 | I37: https://www.astrazeneca.com/content/dam/az/Investor_Relations/annual-report-2025/pdf/AstraZeneca_Development_Pipeline_2025.pdf
A38: AstraZeneca | B38: Rare Disease | C38: Rare disease | D38: anselamimab | E38: Phase III / registration | F38: Fibril-reactive monoclonal antibody | G38: AL amyloidosis | H38: 2026-02-10 | I38: https://www.astrazeneca.com/content/dam/az/Investor_Relations/annual-report-2025/pdf/AstraZeneca_Development_Pipeline_2025.pdf
A39: AstraZeneca | B39: Rare Disease | C39: Rare disease | D39: cliramitug | E39: Phase III | F39: Transthyretin depleter | G39: Transthyretin amyloid cardiomyopathy | H39: 2026-02-10 | I39: https://www.astrazeneca.com/content/dam/az/Investor_Relations/annual-report-2025/pdf/AstraZeneca_Development_Pipeline_2025.pdf
A40: AstraZeneca | B40: Rare Disease | C40: Rare disease | D40: efzimfotase alfa | E40: Phase III | F40: Next-generation TNSALP enzyme replacement therapy | G40: Hypophosphatasia | H40: 2026-02-10 | I40: https://www.astrazeneca.com/content/dam/az/Investor_Relations/annual-report-2025/pdf/AstraZeneca_Development_Pipeline_2025.pdf
A41: AstraZeneca | B41: Rare Disease | C41: Rare disease | D41: eneboparatide | E41: Phase III | F41: Parathyroid hormone receptor 1 agonist | G41: Hypoparathyroidism | H41: 2026-02-10 | I41: https://www.astrazeneca.com/content/dam/az/Investor_Relations/annual-report-2025/pdf/AstraZeneca_Development_Pipeline_2025.pdf
A42: AstraZeneca | B42: Rare Disease | C42: Rare disease | D42: gefurulimab | E42: Phase III / registration | F42: Dual-binding anti-C5 nanobody | G42: Generalized myasthenia gravis | H42: 2026-02-10 | I42: https://www.astrazeneca.com/content/dam/az/Investor_Relations/annual-report-2025/pdf/AstraZeneca_Development_Pipeline_2025.pdf
A43: AstraZeneca | B43: Vaccines & Immune Therapies | C43: Infectious disease | D43: AZD0292 | E43: Phase II | F43: Pseudomonas Psl/PcrV bispecific antibody | G43: Bronchiectasis | H43: 2026-02-10 | I43: https://www.astrazeneca.com/content/dam/az/Investor_Relations/annual-report-2025/pdf/AstraZeneca_Development_Pipeline_2025.pdf
A44: AstraZeneca | B44: Vaccines & Immune Therapies | C44: Infectious disease | D44: AZD5148 | E44: Phase II | F44: C. difficile TcdB monoclonal antibody | G44: Reduction of C. difficile recurrence | H44: 2026-02-10 | I44: https://www.astrazeneca.com/content/dam/az/Investor_Relations/annual-report-2025/pdf/AstraZeneca_Development_Pipeline_2025.pdf
A45: AstraZeneca | B45: Vaccines & Immune Therapies | C45: Infectious disease | D45: AZD7760 | E45: Phase II | F45: Anti-virulence monoclonal antibody combination | G45: Prevention of Staphylococcus aureus infection | H45: 2026-02-10 | I45: https://www.astrazeneca.com/content/dam/az/Investor_Relations/annual-report-2025/pdf/AstraZeneca_Development_Pipeline_2025.pdf
A46: Bristol Myers Squibb | B46: Oncology | C46: Solid-tumor oncology | D46: pumitamig | E46: Phase III | F46: PD-L1 x VEGF-A bispecific antibody | G46: NSCLC, ES-SCLC, TNBC and other solid tumors | H46: 2026-02-05 | I46: https://annual-report.bms.com/assets/bms-ar/documents/2025/2025-bms-development-portfolio.pdf | J46: Multiple indications counted once under the lead asset.
A47: Bristol Myers Squibb | B47: Oncology | C47: Solid-tumor oncology | D47: izalontamab brengitecan (iza-bren) | E47: Phase II | F47: EGFR x HER3 bispecific antibody-drug conjugate | G47: TNBC, EGFR-mutated NSCLC and urothelial cancer | H47: 2026-02-05 | I47: https://annual-report.bms.com/assets/bms-ar/documents/2025/2025-bms-development-portfolio.pdf
A48: Bristol Myers Squibb | B48: Oncology | C48: Solid-tumor oncology | D48: navlimetostat | E48: Phase II | F48: PRMT5 inhibitor | G48: NSCLC, pancreatic cancer and other solid tumors | H48: 2026-02-05 | I48: https://annual-report.bms.com/assets/bms-ar/documents/2025/2025-bms-development-portfolio.pdf
A49: Bristol Myers Squibb | B49: Oncology | C49: Solid-tumor oncology | D49: AR ligand-directed degrader | E49: Phase III | F49: Androgen receptor ligand-directed degrader | G49: Metastatic castration-resistant prostate cancer | H49: 2026-02-05 | I49: https://annual-report.bms.com/assets/bms-ar/documents/2025/2025-bms-development-portfolio.pdf
A50: Bristol Myers Squibb | B50: Oncology | C50: Solid-tumor oncology | D50: atigotatug + nivolumab | E50: Phase III | F50: Investigational immuno-oncology combination | G50: First-line extensive-stage small-cell lung cancer | H50: 2026-02-05 | I50: https://annual-report.bms.com/assets/bms-ar/documents/2025/2025-bms-development-portfolio.pdf | K50: Opdivo / Opdivo Qvantig | L50: Marketed component: nivolumab | M50: OPDIVO_FRANCHISE
A51: Bristol Myers Squibb | B51: Oncology | C51: Solid-tumor oncology | D51: nivolumab + relatlimab HD | E51: Phase III | F51: PD-1 plus LAG-3 immuno-oncology combination | G51: First-line NSCLC with PD-L1 >=1% | H51: 2026-02-05 | I51: https://annual-report.bms.com/assets/bms-ar/documents/2025/2025-bms-development-portfolio.pdf | K51: Opdualag | L51: Related marketed fixed-dose combination: nivolumab + relatlimab | M51: OPDUALAG | OPDIVO_FRANCHISE
A52: Bristol Myers Squibb | B52: Oncology | C52: Solid-tumor oncology | D52: RYZ101 | E52: Phase III | F52: SSTR2-targeted radiopharmaceutical | G52: SSTR2-positive gastroenteropancreatic neuroendocrine tumors | H52: 2026-02-05 | I52: https://annual-report.bms.com/assets/bms-ar/documents/2025/2025-bms-development-portfolio.pdf
A53: Bristol Myers Squibb | B53: Hematology | C53: Hematology | D53: arlo-cel | E53: Phase III | F53: GPRC5D-directed autologous CAR-T | G53: Multiple myeloma | H53: 2026-02-05 | I53: https://annual-report.bms.com/assets/bms-ar/documents/2025/2025-bms-development-portfolio.pdf
A54: Bristol Myers Squibb | B54: Hematology | C54: Hematology | D54: golcadomide | E54: Phase III | F54: CELMoD / targeted protein degradation | G54: Follicular lymphoma and high-risk large B-cell lymphoma | H54: 2026-02-05 | I54: https://annual-report.bms.com/assets/bms-ar/documents/2025/2025-bms-development-portfolio.pdf
A55: Bristol Myers Squibb | B55: Hematology | C55: Hematology | D55: iberdomide | E55: Phase III | F55: CELMoD / targeted protein degradation | G55: Multiple myeloma | H55: 2026-02-05 | I55: https://annual-report.bms.com/assets/bms-ar/documents/2025/2025-bms-development-portfolio.pdf
A56: Bristol Myers Squibb | B56: Hematology | C56: Hematology | D56: mezigdomide | E56: Phase III / registration | F56: CELMoD / targeted protein degradation | G56: Relapsed/refractory multiple myeloma | H56: 2026-02-05 | I56: https://annual-report.bms.com/assets/bms-ar/documents/2025/2025-bms-development-portfolio.pdf
A57: Bristol Myers Squibb | B57: Immunology | C57: Immunology, respiratory & fibrosis | D57: zola-cel (CD19 NEX-T) | E57: Phase III | F57: CD19-directed CAR-T cell therapy | G57: Systemic lupus erythematosus and systemic sclerosis | H57: 2026-02-05 | I57: https://annual-report.bms.com/assets/bms-ar/documents/2025/2025-bms-development-portfolio.pdf
A58: Bristol Myers Squibb | B58: Immunology | C58: Immunology, respiratory & fibrosis | D58: admilparant | E58: Phase III | F58: Oral LPA1 antagonist | G58: Idiopathic and progressive pulmonary fibrosis | H58: 2026-02-05 | I58: https://annual-report.bms.com/assets/bms-ar/documents/2025/2025-bms-development-portfolio.pdf
A59: Bristol Myers Squibb | B59: Immunology | C59: Immunology, respiratory & fibrosis | D59: obexelimab | E59: Phase III | F59: B-cell-directed monoclonal antibody | G59: IgG4-related disease | H59: 2026-02-05 | I59: https://annual-report.bms.com/assets/bms-ar/documents/2025/2025-bms-development-portfolio.pdf
A60: Bristol Myers Squibb | B60: Cardiovascular | C60: Cardiovascular | D60: MYK-224 | E60: Phase II | F60: Cardiac myosin inhibitor | G60: Heart failure with preserved ejection fraction | H60: 2026-02-05 | I60: https://annual-report.bms.com/assets/bms-ar/documents/2025/2025-bms-development-portfolio.pdf
A61: Bristol Myers Squibb | B61: Cardiovascular | C61: Cardiovascular | D61: milvexian | E61: Phase III | F61: Factor XIa inhibitor | G61: Atrial fibrillation and secondary stroke prevention | H61: 2026-02-05 | I61: https://annual-report.bms.com/assets/bms-ar/documents/2025/2025-bms-development-portfolio.pdf
A62: Bristol Myers Squibb | B62: Neuroscience | C62: Neuroscience | D62: anti-MTBR tau | E62: Phase II | F62: Tau-targeting monoclonal antibody | G62: Alzheimer's disease | H62: 2026-02-05 | I62: https://annual-report.bms.com/assets/bms-ar/documents/2025/2025-bms-development-portfolio.pdf
A63: Bristol Myers Squibb | B63: Neuroscience | C63: Neuroscience | D63: FAAH/MAGL dual inhibitor | E63: Phase II | F63: Small-molecule dual enzyme inhibitor | G63: Alzheimer's disease agitation and multiple-sclerosis spasticity | H63: 2026-02-05 | I63: https://annual-report.bms.com/assets/bms-ar/documents/2025/2025-bms-development-portfolio.pdf

Sheet Overlap_Units
A1: AZ + BMS overlap units - evidence behind bubble counts
A2: One row equals one distinct shared territory/class. Bubble counts are formula-driven from this table. Directness is an analyst-coded input: 1 limited, 2 moderate, 3 strong.
A4: Disease area | B4: Factor | C4: Overlap unit | D4: AZ evidence / programs | E4: BMS evidence / programs | F4: Directness (1-3) | G4: Rationale | H4: AZ source URL | I4: BMS source URL
A5: Solid-tumor oncology | B5: Shared indications | C5: NSCLC | D5: IPH5201; rilvegostomig; volrustomig | E5: pumitamig; iza-bren; navlimetostat; nivolumab + relatlimab HD | F5: 3 | G5: Multiple programs from both companies are being developed in NSCLC, creating direct disease-level overlap. | H5: https://www.astrazeneca.com/content/dam/az/Investor_Relations/annual-report-2025/pdf/AstraZeneca_Development_Pipeline_2025.pdf | I5: https://www.bms.com/assets/bms/us/en-us/pdf/investor-info/doc_presentations/2026/bms-pipeline-february-2026.pdf
A6: Solid-tumor oncology | B6: Shared indications | C6: Prostate cancer | D6: FPI-2265; saruparib | E6: AR ligand-directed degrader | F6: 3 | G6: Both companies have late-stage prostate-cancer programs, although targets and modalities differ. | H6: https://www.astrazeneca.com/content/dam/az/Investor_Relations/annual-report-2025/pdf/AstraZeneca_Development_Pipeline_2025.pdf | I6: https://www.bms.com/assets/bms/us/en-us/pdf/investor-info/doc_presentations/2026/bms-pipeline-february-2026.pdf
A7: Solid-tumor oncology | B7: Shared modalities | C7: Small-molecule targeted therapy | D7: AZD9574; camizestrant; saruparib | E7: navlimetostat; AR ligand-directed degrader | F7: 2 | G7: Both use oral/small-molecule targeted approaches in solid tumors. | H7: https://www.astrazeneca.com/content/dam/az/Investor_Relations/annual-report-2025/pdf/AstraZeneca_Development_Pipeline_2025.pdf | I7: https://www.bms.com/assets/bms/us/en-us/pdf/investor-info/doc_presentations/2026/bms-pipeline-february-2026.pdf
A8: Solid-tumor oncology | B8: Shared modalities | C8: Bispecific / dual-target biologics | D8: rilvegostomig; volrustomig | E8: pumitamig | F8: 3 | G8: Both have late-stage dual-target immuno-oncology biologics. | H8: https://www.astrazeneca.com/content/dam/az/Investor_Relations/annual-report-2025/pdf/AstraZeneca_Development_Pipeline_2025.pdf | I8: https://www.bms.com/assets/bms/us/en-us/pdf/investor-info/doc_presentations/2026/bms-pipeline-february-2026.pdf
A9: Solid-tumor oncology | B9: Shared modalities | C9: Antibody-drug conjugates | D9: puxitatug samrotecan; sonesitatug vedotin; tilatamig samrotecan; torvutatug samrotecan | E9: izalontamab brengitecan | F9: 3 | G9: Both have substantial ADC activity, with AstraZeneca contributing greater breadth. | H9: https://www.astrazeneca.com/content/dam/az/Investor_Relations/annual-report-2025/pdf/AstraZeneca_Development_Pipeline_2025.pdf | I9: https://www.bms.com/assets/bms/us/en-us/pdf/investor-info/doc_presentations/2026/bms-pipeline-february-2026.pdf
A10: Solid-tumor oncology | B10: Shared modalities | C10: Radiopharmaceuticals | D10: FPI-2265 | E10: RYZ101 | F10: 2 | G10: Both have targeted radiopharmaceutical programs, but in different tumor types and targets. | H10: https://www.astrazeneca.com/content/dam/az/Investor_Relations/annual-report-2025/pdf/AstraZeneca_Development_Pipeline_2025.pdf | I10: https://www.bms.com/assets/bms/us/en-us/pdf/investor-info/doc_presentations/2026/bms-pipeline-february-2026.pdf
A11: Solid-tumor oncology | B11: Shared target / mechanism | C11: PD-(L)1-based immuno-oncology | D11: rilvegostomig; volrustomig | E11: pumitamig; nivolumab + relatlimab HD; atigotatug + nivolumab | F11: 3 | G11: Both portfolios use PD-1/PD-L1-centered combinations or multispecific approaches. | H11: https://www.astrazeneca.com/content/dam/az/Investor_Relations/annual-report-2025/pdf/AstraZeneca_Development_Pipeline_2025.pdf | I11: https://www.bms.com/assets/bms/us/en-us/pdf/investor-info/doc_presentations/2026/bms-pipeline-february-2026.pdf
A12: Solid-tumor oncology | B12: Shared target / mechanism | C12: EGFR-directed therapeutics | D12: tilatamig samrotecan | E12: izalontamab brengitecan | F12: 2 | G12: Both have EGFR-directed ADC programs, paired with different second targets. | H12: https://www.astrazeneca.com/content/dam/az/Investor_Relations/annual-report-2025/pdf/AstraZeneca_Development_Pipeline_2025.pdf | I12: https://www.bms.com/assets/bms/us/en-us/pdf/investor-info/doc_presentations/2026/bms-pipeline-february-2026.pdf
A13: Solid-tumor oncology | B13: Stage alignment | C13: Phase II | D13: AZD9574; FPI-2265; IPH5201; tilatamig samrotecan | E13: iza-bren; navlimetostat | F13: 2 | G13: Both companies have Phase II programs in the disease area. | H13: https://www.astrazeneca.com/content/dam/az/Investor_Relations/annual-report-2025/pdf/AstraZeneca_Development_Pipeline_2025.pdf | I13: https://www.bms.com/assets/bms/us/en-us/pdf/investor-info/doc_presentations/2026/bms-pipeline-february-2026.pdf
A14: Solid-tumor oncology | B14: Stage alignment | C14: Phase III / registration | D14: camizestrant; puxitatug samrotecan; rilvegostomig; saruparib; sonesitatug vedotin; torvutatug samrotecan; volrustomig | E14: pumitamig; AR ligand-directed degrader; atigotatug + nivolumab; nivolumab + relatlimab HD; RYZ101 | F14: 3 | G14: Both have broad Phase III/registration portfolios in solid tumors. | H14: https://www.astrazeneca.com/content/dam/az/Investor_Relations/annual-report-2025/pdf/AstraZeneca_Development_Pipeline_2025.pdf | I14: https://www.bms.com/assets/bms/us/en-us/pdf/investor-info/doc_presentations/2026/bms-pipeline-february-2026.pdf
A15: Hematology | B15: Shared indications | C15: Multiple myeloma | D15: AZD0120; AZD0305 | E15: arlo-cel; iberdomide; mezigdomide | F15: 3 | G15: Both companies have multiple late-stage programs in multiple myeloma. | H15: https://www.astrazeneca.com/content/dam/az/Investor_Relations/annual-report-2025/pdf/AstraZeneca_Development_Pipeline_2025.pdf | I15: https://www.bms.com/assets/bms/us/en-us/pdf/investor-info/doc_presentations/2026/bms-pipeline-february-2026.pdf
A16: Hematology | B16: Shared indications | C16: B-cell lymphoma | D16: surovatamig | E16: golcadomide | F16: 3 | G16: Both have Phase III programs in B-cell lymphoma territories. | H16: https://www.astrazeneca.com/content/dam/az/Investor_Relations/annual-report-2025/pdf/AstraZeneca_Development_Pipeline_2025.pdf | I16: https://www.bms.com/assets/bms/us/en-us/pdf/investor-info/doc_presentations/2026/bms-pipeline-february-2026.pdf
... A27: Cardiovascular | B27: Stage alignment | C27: Phase III / registration | D27: baxdrostat; laroprovstat | E27: milvexian | F27: 1 | G27: Both have Phase III programs, but in different cardiovascular indications. | H27: https://www.astrazeneca.com/content/dam/az/Investor_Relations/annual-report-2025/pdf/AstraZeneca_Development_Pipeline_2025.pdf | I27: https://www.bms.com/assets/bms/us/en-us/pdf/investor-info/doc_presentations/2026/bms-pipeline-february-2026.pdf

Sheet Overlap_Matrix
A1: AstraZeneca + BMS: count-based portfolio collision matrix
A2: Counts represent distinct shared territories/classes and are calculated from Overlap_Units. Intensity is the maximum directness score among the units in each cell. Portfolio balance has been removed.
A4: Disease area | B4: Plot label | C4: AZ programs | D4: BMS programs | E4: Combined programs | F4: Shared indications | G4: Indication intensity | H4: Shared modalities | I4: Modality intensity | J4: Shared target / mechanism | K4: Target intensity | L4: Stage alignment | M4: Stage intensity | N4: Strategic read
A5: Solid-tumor oncology | B5: Solid tumors | C5: =COUNTIFS(Asset_Data!$A:$A,"AstraZeneca",Asset_Data!$C:$C,$A5) | D5: =COUNTIFS(Asset_Data!$A:$A,"Bristol Myers Squibb",Asset_Data!$C:$C,$A5) | E5: =SUM(C5:D5) | F5: =COUNTIFS(Overlap_Units!$A:$A,$A5,Overlap_Units!$B:$B,F4) | G5: =IF(F5=0,0,MAXIFS(Overlap_Units!$F:$F,Overlap_Units!$A:$A,$A5,Overlap_Units!$B:$B,F4)) | H5: =COUNTIFS(Overlap_Units!$A:$A,$A5,Overlap_Units!$B:$B,H4) | I5: =IF(H5=0,0,MAXIFS(Overlap_Units!$F:$F,Overlap_Units!$A:$A,$A5,Overlap_Units!$B:$B,H4)) | J5: =COUNTIFS(Overlap_Units!$A:$A,$A5,Overlap_Units!$B:$B,J4) | K5: =IF(J5=0,0,MAXIFS(Overlap_Units!$F:$F,Overlap_Units!$A:$A,$A5,Overlap_Units!$B:$B,J4)) | L5: =COUNTIFS(Overlap_Units!$A:$A,$A5,Overlap_Units!$B:$B,L4) | M5: =IF(L5=0,0,MAXIFS(Overlap_Units!$F:$F,Overlap_Units!$A:$A,$A5,Overlap_Units!$B:$B,L4)) | N5: Strong collision
A6: Hematology | B6: Hematology | C6: =COUNTIFS(Asset_Data!$A:$A,"AstraZeneca",Asset_Data!$C:$C,$A6) | D6: =COUNTIFS(Asset_Data!$A:$A,"Bristol Myers Squibb",Asset_Data!$C:$C,$A6) | E6: =SUM(C6:D6) | F6: =COUNTIFS(Overlap_Units!$A:$A,$A6,Overlap_Units!$B:$B,F4) | G6: =IF(F6=0,0,MAXIFS(Overlap_Units!$F:$F,Overlap_Units!$A:$A,$A6,Overlap_Units!$B:$B,F4)) | H6: =COUNTIFS(Overlap_Units!$A:$A,$A6,Overlap_Units!$B:$B,H4) | I6: =IF(H6=0,0,MAXIFS(Overlap_Units!$F:$F,Overlap_Units!$A:$A,$A6,Overlap_Units!$B:$B,H4)) | J6: =COUNTIFS(Overlap_Units!$A:$A,$A6,Overlap_Units!$B:$B,J4) | K6: =IF(J6=0,0,MAXIFS(Overlap_Units!$F:$F,Overlap_Units!$A:$A,$A6,Overlap_Units!$B:$B,J4)) | L6: =COUNTIFS(Overlap_Units!$A:$A,$A6,Overlap_Units!$B:$B,L4) | M6: =IF(L6=0,0,MAXIFS(Overlap_Units!$F:$F,Overlap_Units!$A:$A,$A6,Overlap_Units!$B:$B,L4)) | N6: Strong collision
A7: Immunology, respiratory & fibrosis | B7: Immunology / resp. / fibrosis | C7: =COUNTIFS(Asset_Data!$A:$A,"AstraZeneca",Asset_Data!$C:$C,$A7) | D7: =COUNTIFS(Asset_Data!$A:$A,"Bristol Myers Squibb",Asset_Data!$C:$C,$A7) | E7: =SUM(C7:D7) | F7: =COUNTIFS(Overlap_Units!$A:$A,$A7,Overlap_Units!$B:$B,F4) | G7: =IF(F7=0,0,MAXIFS(Overlap_Units!$F:$F,Overlap_Units!$A:$A,$A7,Overlap_Units!$B:$B,F4)) | H7: =COUNTIFS(Overlap_Units!$A:$A,$A7,Overlap_Units!$B:$B,H4) | I7: =IF(H7=0,0,MAXIFS(Overlap_Units!$F:$F,Overlap_Units!$A:$A,$A7,Overlap_Units!$B:$B,H4)) | J7: =COUNTIFS(Overlap_Units!$A:$A,$A7,Overlap_Units!$B:$B,J4) | K7: =IF(J7=0,0,MAXIFS(Overlap_Units!$F:$F,Overlap_Units!$A:$A,$A7,Overlap_Units!$B:$B,J4)) | L7: =COUNTIFS(Overlap_Units!$A:$A,$A7,Overlap_Units!$B:$B,L4) | M7: =IF(L7=0,0,MAXIFS(Overlap_Units!$F:$F,Overlap_Units!$A:$A,$A7,Overlap_Units!$B:$B,L4)) | N7: Platform adjacency
A8: Cardiovascular | B8: CV | C8: =COUNTIFS(Asset_Data!$A:$A,"AstraZeneca",Asset_Data!$C:$C,$A8) | D8: =COUNTIFS(Asset_Data!$A:$A,"Bristol Myers Squibb",Asset_Data!$C:$C,$A8) | E8: =SUM(C8:D8) | F8: =COUNTIFS(Overlap_Units!$A:$A,$A8,Overlap_Units!$B:$B,F4) | G8: =IF(F8=0,0,MAXIFS(Overlap_Units!$F:$F,Overlap_Units!$A:$A,$A8,Overlap_Units!$B:$B,F4)) | H8: =COUNTIFS(Overlap_Units!$A:$A,$A8,Overlap_Units!$B:$B,H4) | I8: =IF(H8=0,0,MAXIFS(Overlap_Units!$F:$F,Overlap_Units!$A:$A,$A8,Overlap_Units!$B:$B,H4)) | J8: =COUNTIFS(Overlap_Units!$A:$A,$A8,Overlap_Units!$B:$B,J4) | K8: =IF(J8=0,0,MAXIFS(Overlap_Units!$F:$F,Overlap_Units!$A:$A,$A8,Overlap_Units!$B:$B,J4)) | L8: =COUNTIFS(Overlap_Units!$A:$A,$A8,Overlap_Units!$B:$B,L4) | M8: =IF(L8=0,0,MAXIFS(Overlap_Units!$F:$F,Overlap_Units!$A:$A,$A8,Overlap_Units!$B:$B,L4)) | N8: Narrow adjacency
A9: Rare disease | B9: Rare disease | C9: =COUNTIFS(Asset_Data!$A:$A,"AstraZeneca",Asset_Data!$C:$C,$A9) | D9: =COUNTIFS(Asset_Data!$A:$A,"Bristol Myers Squibb",Asset_Data!$C:$C,$A9) | E9: =SUM(C9:D9) | F9: =COUNTIFS(Overlap_Units!$A:$A,$A9,Overlap_Units!$B:$B,F4) | G9: =IF(F9=0,0,MAXIFS(Overlap_Units!$F:$F,Overlap_Units!$A:$A,$A9,Overlap_Units!$B:$B,F4)) | H9: =COUNTIFS(Overlap_Units!$A:$A,$A9,Overlap_Units!$B:$B,H4) | I9: =IF(H9=0,0,MAXIFS(Overlap_Units!$F:$F,Overlap_Units!$A:$A,$A9,Overlap_Units!$B:$B,H4)) | J9: =COUNTIFS(Overlap_Units!$A:$A,$A9,Overlap_Units!$B:$B,J4) | K9: =IF(J9=0,0,MAXIFS(Overlap_Units!$F:$F,Overlap_Units!$A:$A,$A9,Overlap_Units!$B:$B,J4)) | L9: =COUNTIFS(Overlap_Units!$A:$A,$A9,Overlap_Units!$B:$B,L4) | M9: =IF(L9=0,0,MAXIFS(Overlap_Units!$F:$F,Overlap_Units!$A:$A,$A9,Overlap_Units!$B:$B,L4)) | N9: AZ-led fit
A10: Renal & metabolic | B10: Renal / metabolic | C10: =COUNTIFS(Asset_Data!$A:$A,"AstraZeneca",Asset_Data!$C:$C,$A10) | D10: =COUNTIFS(Asset_Data!$A:$A,"Bristol Myers Squibb",Asset_Data!$C:$C,$A10) | E10: =SUM(C10:D10) | F10: =COUNTIFS(Overlap_Units!$A:$A,$A10,Overlap_Units!$B:$B,F4) | G10: =IF(F10=0,0,MAXIFS(Overlap_Units!$F:$F,Overlap_Units!$A:$A,$A10,Overlap_Units!$B:$B,F4)) | H10: =COUNTIFS(Overlap_Units!$A:$A,$A10,Overlap_Units!$B:$B,H4) | I10: =IF(H10=0,0,MAXIFS(Overlap_Units!$F:$F,Overlap_Units!$A:$A,$A10,Overlap_Units!$B:$B,H4)) | J10: =COUNTIFS(Overlap_Units!$A:$A,$A10,Overlap_Units!$B:$B,J4) | K10: =IF(J10=0,0,MAXIFS(Overlap_Units!$F:$F,Overlap_Units!$A:$A,$A10,Overlap_Units!$B:$B,J4)) | L10: =COUNTIFS(Overlap_Units!$A:$A,$A10,Overlap_Units!$B:$B,L4) | M10: =IF(L10=0,0,MAXIFS(Overlap_Units!$F:$F,Overlap_Units!$A:$A,$A10,Overlap_Units!$B:$B,L4)) | N10: AZ-led fit
A11: Infectious disease | B11: Infectious disease | C11: =COUNTIFS(Asset_Data!$A:$A,"AstraZeneca",Asset_Data!$C:$C,$A11) | D11: =COUNTIFS(Asset_Data!$A:$A,"Bristol Myers Squibb",Asset_Data!$C:$C,$A11) | E11: =SUM(C11:D11) | F11: =COUNTIFS(Overlap_Units!$A:$A,$A11,Overlap_Units!$B:$B,F4) | G11: =IF(F11=0,0,MAXIFS(Overlap_Units!$F:$F,Overlap_Units!$A:$A,$A11,Overlap_Units!$B:$B,F4)) | H11: =COUNTIFS(Overlap_Units!$A:$A,$A11,Overlap_Units!$B:$B,H4) | I11: =IF(H11=0,0,MAXIFS(Overlap_Units!$F:$F,Overlap_Units!$A:$A,$A11,Overlap_Units!$B:$B,H4)) | J11: =COUNTIFS(Overlap_Units!$A:$A,$A11,Overlap_Units!$B:$B,J4) | K11: =IF(J11=0,0,MAXIFS(Overlap_Units!$F:$F,Overlap_Units!$A:$A,$A11,Overlap_Units!$B:$B,J4)) | L11: =COUNTIFS(Overlap_Units!$A:$A,$A11,Overlap_Units!$B:$B,L4) | M11: =IF(L11=0,0,MAXIFS(Overlap_Units!$F:$F,Overlap_Units!$A:$A,$A11,Overlap_Units!$B:$B,L4)) | N11: AZ-led fit
A12: Neuroscience | B12: Neuroscience | C12: =COUNTIFS(Asset_Data!$A:$A,"AstraZeneca",Asset_Data!$C:$C,$A12) | D12: =COUNTIFS(Asset_Data!$A:$A,"Bristol Myers Squibb",Asset_Data!$C:$C,$A12) | E12: =SUM(C12:D12) | F12: =COUNTIFS(Overlap_Units!$A:$A,$A12,Overlap_Units!$B:$B,F4) | G12: =IF(F12=0,0,MAXIFS(Overlap_Units!$F:$F,Overlap_Units!$A:$A,$A12,Overlap_Units!$B:$B,F4)) | H12: =COUNTIFS(Overlap_Units!$A:$A,$A12,Overlap_Units!$B:$B,H4) | I12: =IF(H12=0,0,MAXIFS(Overlap_Units!$F:$F,Overlap_Units!$A:$A,$A12,Overlap_Units!$B:$B,H4)) | J12: =COUNTIFS(Overlap_Units!$A:$A,$A12,Overlap_Units!$B:$B,J4) | K12: =IF(J12=0,0,MAXIFS(Overlap_Units!$F:$F,Overlap_Units!$A:$A,$A12,Overlap_Units!$B:$B,J4)) | L12: =COUNTIFS(Overlap_Units!$A:$A,$A12,Overlap_Units!$B:$B,L4) | M12: =IF(L12=0,0,MAXIFS(Overlap_Units!$F:$F,Overlap_Units!$A:$A,$A12,Overlap_Units!$B:$B,L4)) | N12: BMS-led fit
A15: Definition: overlap count = number of distinct shared territories/classes, not the number of all possible AZ-BMS asset pairs. Late-stage program = unique lead asset in Phase II or Phase III/pivotal/registration.

Sheet Plot_Data
A1: Disease area | B1: Plot label | C1: Factor | D1: Overlap count | E1: Intensity | F1: AZ programs | G1: BMS programs | H1: Relationship
A2: =Overlap_Matrix!A5 | B2: =Overlap_Matrix!B5 | C2: Shared indications | D2: =Overlap_Matrix!F5 | E2: =Overlap_Matrix!G5 | F2: =Overlap_Matrix!C5 | G2: =Overlap_Matrix!D5 | H2: =Overlap_Matrix!N5
A3: =Overlap_Matrix!A5 | B3: =Overlap_Matrix!B5 | C3: Shared modalities | D3: =Overlap_Matrix!H5 | E3: =Overlap_Matrix!I5 | F3: =Overlap_Matrix!C5 | G3: =Overlap_Matrix!D5 | H3: =Overlap_Matrix!N5
A4: =Overlap_Matrix!A5 | B4: =Overlap_Matrix!B5 | C4: Shared target / mechanism | D4: =Overlap_Matrix!J5 | E4: =Overlap_Matrix!K5 | F4: =Overlap_Matrix!C5 | G4: =Overlap_Matrix!D5 | H4: =Overlap_Matrix!N5
A5: =Overlap_Matrix!A5 | B5: =Overlap_Matrix!B5 | C5: Stage alignment | D5: =Overlap_Matrix!L5 | E5: =Overlap_Matrix!M5 | F5: =Overlap_Matrix!C5 | G5: =Overlap_Matrix!D5 | H5: =Overlap_Matrix!N5
A6: =Overlap_Matrix!A6 | B6: =Overlap_Matrix!B6 | C6: Shared indications | D6: =Overlap_Matrix!F6 | E6: =Overlap_Matrix!G6 | F6: =Overlap_Matrix!C6 | G6: =Overlap_Matrix!D6 | H6: =Overlap_Matrix!N6
A7: =Overlap_Matrix!A6 | B7: =Overlap_Matrix!B6 | C7: Shared modalities | D7: =Overlap_Matrix!H6 | E7: =Overlap_Matrix!I6 | F7: =Overlap_Matrix!C6 | G7: =Overlap_Matrix!D6 | H7: =Overlap_Matrix!N6
A8: =Overlap_Matrix!A6 | B8: =Overlap_Matrix!B6 | C8: Shared target / mechanism | D8: =Overlap_Matrix!J6 | E8: =Overlap_Matrix!K6 | F8: =Overlap_Matrix!C6 | G8: =Overlap_Matrix!D6 | H8: =Overlap_Matrix!N6
A9: =Overlap_Matrix!A6 | B9: =Overlap_Matrix!B6 | C9: Stage alignment | D9: =Overlap_Matrix!L6 | E9: =Overlap_Matrix!M6 | F9: =Overlap_Matrix!C6 | G9: =Overlap_Matrix!D6 | H9: =Overlap_Matrix!N6
A10: =Overlap_Matrix!A7 | B10: =Overlap_Matrix!B7 | C10: Shared indications | D10: =Overlap_Matrix!F7 | E10: =Overlap_Matrix!G7 | F10: =Overlap_Matrix!C7 | G10: =Overlap_Matrix!D7 | H10: =Overlap_Matrix!N7
A11: =Overlap_Matrix!A7 | B11: =Overlap_Matrix!B7 | C11: Shared modalities | D11: =Overlap_Matrix!H7 | E11: =Overlap_Matrix!I7 | F11: =Overlap_Matrix!C7 | G11: =Overlap_Matrix!D7 | H11: =Overlap_Matrix!N7
A12: =Overlap_Matrix!A7 | B12: =Overlap_Matrix!B7 | C12: Shared target / mechanism | D12: =Overlap_Matrix!J7 | E12: =Overlap_Matrix!K7 | F12: =Overlap_Matrix!C7 | G12: =Overlap_Matrix!D7 | H12: =Overlap_Matrix!N7
A13: =Overlap_Matrix!A7 | B13: =Overlap_Matrix!B7 | C13: Stage alignment | D13: =Overlap_Matrix!L7 | E13: =Overlap_Matrix!M7 | F13: =Overlap_Matrix!C7 | G13: =Overlap_Matrix!D7 | H13: =Overlap_Matrix!N7
A14: =Overlap_Matrix!A8 | B14: =Overlap_Matrix!B8 | C14: Shared indications | D14: =Overlap_Matrix!F8 | E14: =Overlap_Matrix!G8 | F14: =Overlap_Matrix!C8 | G14: =Overlap_Matrix!D8 | H14: =Overlap_Matrix!N8
A15: =Overlap_Matrix!A8 | B15: =Overlap_Matrix!B8 | C15: Shared modalities | D15: =Overlap_Matrix!H8 | E15: =Overlap_Matrix!I8 | F15: =Overlap_Matrix!C8 | G15: =Overlap_Matrix!D8 | H15: =Overlap_Matrix!N8
A16: =Overlap_Matrix!A8 | B16: =Overlap_Matrix!B8 | C16: Shared target / mechanism | D16: =Overlap_Matrix!J8 | E16: =Overlap_Matrix!K8 | F16: =Overlap_Matrix!C8 | G16: =Overlap_Matrix!D8 | H16: =Overlap_Matrix!N8
A17: =Overlap_Matrix!A8 | B17: =Overlap_Matrix!B8 | C17: Stage alignment | D17: =Overlap_Matrix!L8 | E17: =Overlap_Matrix!M8 | F17: =Overlap_Matrix!C8 | G17: =Overlap_Matrix!D8 | H17: =Overlap_Matrix!N8
A18: =Overlap_Matrix!A9 | B18: =Overlap_Matrix!B9 | C18: Shared indications | D18: =Overlap_Matrix!F9 | E18: =Overlap_Matrix!G9 | F18: =Overlap_Matrix!C9 | G18: =Overlap_Matrix!D9 | H18: =Overlap_Matrix!N9
A19: =Overlap_Matrix!A9 | B19: =Overlap_Matrix!B9 | C19: Shared modalities | D19: =Overlap_Matrix!H9 | E19: =Overlap_Matrix!I9 | F19: =Overlap_Matrix!C9 | G19: =Overlap_Matrix!D9 | H19: =Overlap_Matrix!N9
A20: =Overlap_Matrix!A9 | B20: =Overlap_Matrix!B9 | C20: Shared target / mechanism | D20: =Overlap_Matrix!J9 | E20: =Overlap_Matrix!K9 | F20: =Overlap_Matrix!C9 | G20: =Overlap_Matrix!D9 | H20: =Overlap_Matrix!N9
A21: =Overlap_Matrix!A9 | B21: =Overlap_Matrix!B9 | C21: Stage alignment | D21: =Overlap_Matrix!L9 | E21: =Overlap_Matrix!M9 | F21: =Overlap_Matrix!C9 | G21: =Overlap_Matrix!D9 | H21: =Overlap_Matrix!N9
A22: =Overlap_Matrix!A10 | B22: =Overlap_Matrix!B10 | C22: Shared indications | D22: =Overlap_Matrix!F10 | E22: =Overlap_Matrix!G10 | F22: =Overlap_Matrix!C10 | G22: =Overlap_Matrix!D10 | H22: =Overlap_Matrix!N10
A23: =Overlap_Matrix!A10 | B23: =Overlap_Matrix!B10 | C23: Shared modalities | D23: =Overlap_Matrix!H10 | E23: =Overlap_Matrix!I10 | F23: =Overlap_Matrix!C10 | G23: =Overlap_Matrix!D10 | H23: =Overlap_Matrix!N10
A24: =Overlap_Matrix!A10 | B24: =Overlap_Matrix!B10 | C24: Shared target / mechanism | D24: =Overlap_Matrix!J10 | E24: =Overlap_Matrix!K10 | F24: =Overlap_Matrix!C10 | G24: =Overlap_Matrix!D10 | H24: =Overlap_Matrix!N10
A25: =Overlap_Matrix!A10 | B25: =Overlap_Matrix!B10 | C25: Stage alignment | D25: =Overlap_Matrix!L10 | E25: =Overlap_Matrix!M10 | F25: =Overlap_Matrix!C10 | G25: =Overlap_Matrix!D10 | H25: =Overlap_Matrix!N10
A26: =Overlap_Matrix!A11 | B26: =Overlap_Matrix!B11 | C26: Shared indications | D26: =Overlap_Matrix!F11 | E26: =Overlap_Matrix!G11 | F26: =Overlap_Matrix!C11 | G26: =Overlap_Matrix!D11 | H26: =Overlap_Matrix!N11
A27: =Overlap_Matrix!A11 | B27: =Overlap_Matrix!B11 | C27: Shared modalities | D27: =Overlap_Matrix!H11 | E27: =Overlap_Matrix!I11 | F27: =Overlap_Matrix!C11 | G27: =Overlap_Matrix!D11 | H27: =Overlap_Matrix!N11
A28: =Overlap_Matrix!A11 | B28: =Overlap_Matrix!B11 | C28: Shared target / mechanism | D28: =Overlap_Matrix!J11 | E28: =Overlap_Matrix!K11 | F28: =Overlap_Matrix!C11 | G28: =Overlap_Matrix!D11 | H28: =Overlap_Matrix!N11
A29: =Overlap_Matrix!A11 | B29: =Overlap_Matrix!B11 | C29: Stage alignment | D29: =Overlap_Matrix!L11 | E29: =Overlap_Matrix!M11 | F29: =Overlap_Matrix!C11 | G29: =Overlap_Matrix!D11 | H29: =Overlap_Matrix!N11
A30: =Overlap_Matrix!A12 | B30: =Overlap_Matrix!B12 | C30: Shared indications | D30: =Overlap_Matrix!F12 | E30: =Overlap_Matrix!G12 | F30: =Overlap_Matrix!C12 | G30: =Overlap_Matrix!D12 | H30: =Overlap_Matrix!N12
A31: =Overlap_Matrix!A12 | B31: =Overlap_Matrix!B12 | C31: Shared modalities | D31: =Overlap_Matrix!H12 | E31: =Overlap_Matrix!I12 | F31: =Overlap_Matrix!C12 | G31: =Overlap_Matrix!D12 | H31: =Overlap_Matrix!N12
A32: =Overlap_Matrix!A12 | B32: =Overlap_Matrix!B12 | C32: Shared target / mechanism | D32: =Overlap_Matrix!J12 | E32: =Overlap_Matrix!K12 | F32: =Overlap_Matrix!C12 | G32: =Overlap_Matrix!D12 | H32: =Overlap_Matrix!N12
A33: =Overlap_Matrix!A12 | B33: =Overlap_Matrix!B12 | C33: Stage alignment | D33: =Overlap_Matrix!L12 | E33: =Overlap_Matrix!M12 | F33: =Overlap_Matrix!C12 | G33: =Overlap_Matrix!D12 | H33: =Overlap_Matrix!N12

Sheet Visual_Settings
A1: Visual settings and encoding
A3: Element | B3: Hex | C3: Use | D3: Notes
A4: AstraZeneca primary | B4: #7A1F63 | C4: Stacked bar | D4: Logo-inspired plum
A5: AstraZeneca accent | B5: #D7A900 | C5: Thin bar/legend accent | D5: Logo-inspired gold
A6: BMS primary | B6: #263B73 | C6: Stacked bar | D6: Logo-inspired navy
A7: BMS accent | B7: #76519A | C7: Thin bar/legend accent | D7: Hand-mark-inspired violet
A8: Overlap - limited | B8: #F7D3D0 | C8: Bubble fill | D8: Low directness
A9: Overlap - moderate | B9: #ED756D | C9: Bubble fill | D9: Medium directness
A10: Overlap - strong | B10: #C51F36 | C10: Bubble fill | D10: High directness
A11: Bubble outline | B11: #8E1829 | C11: Bubble border | D11: Consistent red boundary
A12: Page background | B12: #F4F1EC | C12: Canvas | D12: Warm neutral
A13: Card background | B13: #FFFFFF | C13: Main panel | D13: White
A14: Primary text | B14: #182230 | C14: Text | D14: Dark ink
A17: Encoding definitions
A18: Stacked-bar height | B18: Number of unique late-stage programs by company and disease area
A19: Bubble label + size | B19: Number of distinct shared overlap units in the corresponding disease area and portfolio dimension
A20: Bubble red tone | B20: Analyst-coded directness: 1 limited, 2 moderate, 3 strong
A21: Hollow circle | B21: No identified overlap unit under the current normalization

Sheet Summary
A1: Portfolio summary (formula-driven)
A3: Normalized area | B3: AstraZeneca | C3: Bristol Myers Squibb | D3: Combined | E3: Portfolio relationship
A4: Solid-tumor oncology | B4: =COUNTIFS(Asset_Data!$A:$A,"AstraZeneca",Asset_Data!$C:$C,$A4) | C4: =COUNTIFS(Asset_Data!$A:$A,"Bristol Myers Squibb",Asset_Data!$C:$C,$A4) | D4: =SUM(B4:C4) | E4: =IF(AND(B4>0,C4>0),"Shared territory","One-sided strength")
A5: Immunology, respiratory & fibrosis | B5: =COUNTIFS(Asset_Data!$A:$A,"AstraZeneca",Asset_Data!$C:$C,$A5) | C5: =COUNTIFS(Asset_Data!$A:$A,"Bristol Myers Squibb",Asset_Data!$C:$C,$A5) | D5: =SUM(B5:C5) | E5: =IF(AND(B5>0,C5>0),"Shared territory","One-sided strength")
A6: Hematology | B6: =COUNTIFS(Asset_Data!$A:$A,"AstraZeneca",Asset_Data!$C:$C,$A6) | C6: =COUNTIFS(Asset_Data!$A:$A,"Bristol Myers Squibb",Asset_Data!$C:$C,$A6) | D6: =SUM(B6:C6) | E6: =IF(AND(B6>0,C6>0),"Shared territory","One-sided strength")
A7: Cardiovascular | B7: =COUNTIFS(Asset_Data!$A:$A,"AstraZeneca",Asset_Data!$C:$C,$A7) | C7: =COUNTIFS(Asset_Data!$A:$A,"Bristol Myers Squibb",Asset_Data!$C:$C,$A7) | D7: =SUM(B7:C7) | E7: =IF(AND(B7>0,C7>0),"Shared territory","One-sided strength")
A8: Rare disease | B8: =COUNTIFS(Asset_Data!$A:$A,"AstraZeneca",Asset_Data!$C:$C,$A8) | C8: =COUNTIFS(Asset_Data!$A:$A,"Bristol Myers Squibb",Asset_Data!$C:$C,$A8) | D8: =SUM(B8:C8) | E8: =IF(AND(B8>0,C8>0),"Shared territory","One-sided strength")
A9: Renal & metabolic | B9: =COUNTIFS(Asset_Data!$A:$A,"AstraZeneca",Asset_Data!$C:$C,$A9) | C9: =COUNTIFS(Asset_Data!$A:$A,"Bristol Myers Squibb",Asset_Data!$C:$C,$A9) | D9: =SUM(B9:C9) | E9: =IF(AND(B9>0,C9>0),"Shared territory","One-sided strength")
A10: Infectious disease | B10: =COUNTIFS(Asset_Data!$A:$A,"AstraZeneca",Asset_Data!$C:$C,$A10) | C10: =COUNTIFS(Asset_Data!$A:$A,"Bristol Myers Squibb",Asset_Data!$C:$C,$A10) | D10: =SUM(B10:C10) | E10: =IF(AND(B10>0,C10>0),"Shared territory","One-sided strength")
A11: Neuroscience | B11: =COUNTIFS(Asset_Data!$A:$A,"AstraZeneca",Asset_Data!$C:$C,$A11) | C11: =COUNTIFS(Asset_Data!$A:$A,"Bristol Myers Squibb",Asset_Data!$C:$C,$A11) | D11: =SUM(B11:C11) | E11: =IF(AND(B11>0,C11>0),"Shared territory","One-sided strength")
A12: Total | B12: =SUM(B4:B11) | C12: =SUM(C4:C11) | D12: =SUM(D4:D11)

Sheet LinkedIn_Draft
A1: LinkedIn post draft
A3: The AstraZeneca–BMS rumor appears to be off the table. But the portfolio thought experiment is still interesting. I mapped the companies’ Phase II/III investigational portfolios using matched February 2026 company disclosures. The result looks less like a simple “R&D machine” and more like a mix of portfolio fit and collision. The collision zone is oncology. Across the mapped portfolio, the two companies have 18 solid-tumor programs and 8 hematology programs. Both are active in immuno-oncology and lung cancer, while the broader pipelines span ADCs, bispecifics, radiopharmaceuticals, cell therapy and targeted protein degradation. The complementarity is mostly outside oncology. AstraZeneca contributes much more breadth in rare disease, renal/metabolic disease and infectious disease. BMS adds a distinct neuroscience position, while both companies also overlap in immunology/respiratory/fibrosis and cardiovascular disease. The real integration question would not be whether the combined company had enough assets. It would be which programs, platforms, teams and partnerships would survive portfolio prioritization. More breadth creates more optionality—but also more duplication and harder choices. My takeaway: the strategic value would depend less on adding the two pipelines together, and more on how aggressively management rationalized the overlap without disrupting the science that created it. What would you scrutinize first: portfolio overlap, patent cliffs or integration risk? Data note: unique lead investigational assets/programs in Phase II or III/pivotal/registration; matched AstraZeneca (Feb. 10, 2026) and BMS (Feb. 5, 2026) disclosures; approved-indication expansions and significant life-cycle-management programs excluded.
A5: Optional shorter opening
A6: The rumor may be dead. The portfolio question is not: would AstraZeneca + BMS create strategic fit—or force a wave of R&D rationalization?
A8: Suggested hashtags
A9: #Pharma #Biotech #DrugDevelopment #Oncology #Strategy #MergersAndAcquisitions

Sheet Sources
A1: Source | B1: Date | C1: Use | D1: URL
A2: AstraZeneca Development Pipeline 2025 | B2: 2026-02-10 | C2: Matched portfolio count and program stage | D2: https://www.astrazeneca.com/content/dam/az/Investor_Relations/annual-report-2025/pdf/AstraZeneca_Development_Pipeline_2025.pdf
A3: BMS Development Portfolio 2025 | B3: 2026-02-05 | C3: Matched portfolio count and program stage | D3: https://annual-report.bms.com/assets/bms-ar/documents/2025/2025-bms-development-portfolio.pdf
A4: ClinicalTrials.gov | B4: Records checked through 2026-08-05 | C4: Trial phase, setting and primary-completion timing | D4: https://clinicaltrials.gov/
A5: AstraZeneca 2025 Form 20-F | B5: 2026-02-24 | C5: 2023-2025 product revenue and disclosed patent / exclusivity dates | D5: https://www.sec.gov/Archives/edgar/data/901832/000110465926019130/azn-20251231x20f.htm
A6: BMS Key Facts | B6: Updated May 2026 | C6: 2025 product revenue benchmarks | D6: https://www.bms.com/investors/financial-reporting/key-facts.html
A7: BMS FY2021 Results | B7: 2022-02-04 | C7: Historical multiple-myeloma franchise benchmark | D7: https://news.bms.com/news/details/2022/Bristol-Myers-Squibb-Reports-Fourth-Quarter-and-Full-Year-Financial-Results-for-2021/default.aspx
A8: AstraZeneca H1 and Q2 2026 results | B8: 2026-07-27 | C8: Etcamah and Baxfendy brand status; H1 2026 product revenue; Farxiga LOE impact | D8: https://www.rns-pdf.londonstockexchange.com/rns/9440N_1-2026-7-26.pdf
A9: BMS 2025 Form 10-K | B9: 2026-02-10 | C9: 2023-2025 product revenue and minimum market-exclusivity dates | D9: https://www.sec.gov/Archives/edgar/data/14272/000001427226000004/bmy-20251231.htm
A10: BMS Q2 2026 results | B10: 2026-07-30 | C10: H1 2026 product revenue used to derive 2026E run-rate scenarios | D10: https://www.bms.com/assets/bms/us/en-us/pdf/investor-info/doc_financials/quarterly_reports/2026/ghBMY-Q2-2026-Earnings-Press-Release.pdf

Sheet Infographic
A1: LinkedIn infographic - stacked footprint + count-based lollipop matrix
A2: Bars use logo-inspired company colors; bubbles use a red directness scale.

Sheet Fit_Collision_Matrix
A1: Fit vs collision matrix - indication territory × modality family
A2: AZ-only and BMS-only cells indicate complementarity in the matched late-stage snapshot; overlap cells indicate both companies occupy the same normalized modality × indication territory.
A4: Disease area | B4: Modality family | C4: Indication territory | D4: Status | E4: AZ count | F4: BMS count | G4: AZ programs | H4: BMS programs | I4: AZ source | J4: BMS source
A5: Solid-tumor oncology | B5: Antibody-drug conjugate | C5: NSCLC | D5: bms-only | E5: 0 | F5: 1 | H5: izalontamab brengitecan (iza-bren) | I5: https://www.astrazeneca.com/content/dam/az/Investor_Relations/annual-report-2025/pdf/AstraZeneca_Development_Pipeline_2025.pdf | J5: https://annual-report.bms.com/assets/bms-ar/documents/2025/2025-bms-development-portfolio.pdf
A6: Solid-tumor oncology | B6: Antibody-drug conjugate | C6: Breast cancer | D6: bms-only | E6: 0 | F6: 1 | H6: izalontamab brengitecan (iza-bren) | I6: https://www.astrazeneca.com/content/dam/az/Investor_Relations/annual-report-2025/pdf/AstraZeneca_Development_Pipeline_2025.pdf | J6: https://annual-report.bms.com/assets/bms-ar/documents/2025/2025-bms-development-portfolio.pdf
A7: Solid-tumor oncology | B7: Antibody-drug conjugate | C7: Gastric / GEJ | D7: az-only | E7: 1 | F7: 0 | G7: sonesitatug vedotin | I7: https://www.astrazeneca.com/content/dam/az/Investor_Relations/annual-report-2025/pdf/AstraZeneca_Development_Pipeline_2025.pdf | J7: https://annual-report.bms.com/assets/bms-ar/documents/2025/2025-bms-development-portfolio.pdf
A8: Solid-tumor oncology | B8: Antibody-drug conjugate | C8: Ovarian cancer | D8: az-only | E8: 1 | F8: 0 | G8: torvutatug samrotecan (AZD5335) | I8: https://www.astrazeneca.com/content/dam/az/Investor_Relations/annual-report-2025/pdf/AstraZeneca_Development_Pipeline_2025.pdf | J8: https://annual-report.bms.com/assets/bms-ar/documents/2025/2025-bms-development-portfolio.pdf
A9: Solid-tumor oncology | B9: Antibody-drug conjugate | C9: Endometrial cancer | D9: az-only | E9: 1 | F9: 0 | G9: puxitatug samrotecan | I9: https://www.astrazeneca.com/content/dam/az/Investor_Relations/annual-report-2025/pdf/AstraZeneca_Development_Pipeline_2025.pdf | J9: https://annual-report.bms.com/assets/bms-ar/documents/2025/2025-bms-development-portfolio.pdf
A10: Solid-tumor oncology | B10: Antibody-drug conjugate | C10: Urothelial cancer | D10: bms-only | E10: 0 | F10: 1 | H10: izalontamab brengitecan (iza-bren) | I10: https://www.astrazeneca.com/content/dam/az/Investor_Relations/annual-report-2025/pdf/AstraZeneca_Development_Pipeline_2025.pdf | J10: https://annual-report.bms.com/assets/bms-ar/documents/2025/2025-bms-development-portfolio.pdf
A11: Solid-tumor oncology | B11: Antibody-drug conjugate | C11: Other solid tumors | D11: az-only | E11: 4 | F11: 0 | G11: puxitatug samrotecan; sonesitatug vedotin; tilatamig samrotecan; torvutatug samrotecan (AZD5335) | I11: https://www.astrazeneca.com/content/dam/az/Investor_Relations/annual-report-2025/pdf/AstraZeneca_Development_Pipeline_2025.pdf | J11: https://annual-report.bms.com/assets/bms-ar/documents/2025/2025-bms-development-portfolio.pdf
A12: Solid-tumor oncology | B12: Bispecific / dual-target antibody | C12: NSCLC | D12: overlap | E12: 2 | F12: 1 | G12: rilvegostomig; volrustomig | H12: pumitamig | I12: https://www.astrazeneca.com/content/dam/az/Investor_Relations/annual-report-2025/pdf/AstraZeneca_Development_Pipeline_2025.pdf | J12: https://annual-report.bms.com/assets/bms-ar/documents/2025/2025-bms-development-portfolio.pdf
A13: Solid-tumor oncology | B13: Bispecific / dual-target antibody | C13: SCLC | D13: bms-only | E13: 0 | F13: 1 | H13: pumitamig | I13: https://www.astrazeneca.com/content/dam/az/Investor_Relations/annual-report-2025/pdf/AstraZeneca_Development_Pipeline_2025.pdf | J13: https://annual-report.bms.com/assets/bms-ar/documents/2025/2025-bms-development-portfolio.pdf
A14: Solid-tumor oncology | B14: Bispecific / dual-target antibody | C14: Breast cancer | D14: bms-only | E14: 0 | F14: 1 | H14: pumitamig | I14: https://www.astrazeneca.com/content/dam/az/Investor_Relations/annual-report-2025/pdf/AstraZeneca_Development_Pipeline_2025.pdf | J14: https://annual-report.bms.com/assets/bms-ar/documents/2025/2025-bms-development-portfolio.pdf
A15: Solid-tumor oncology | B15: Bispecific / dual-target antibody | C15: Gastric / GEJ | D15: az-only | E15: 1 | F15: 0 | G15: rilvegostomig | I15: https://www.astrazeneca.com/content/dam/az/Investor_Relations/annual-report-2025/pdf/AstraZeneca_Development_Pipeline_2025.pdf | J15: https://annual-report.bms.com/assets/bms-ar/documents/2025/2025-bms-development-portfolio.pdf
A16: Solid-tumor oncology | B16: Bispecific / dual-target antibody | C16: HCC / biliary | D16: az-only | E16: 1 | F16: 0 | G16: rilvegostomig | I16: https://www.astrazeneca.com/content/dam/az/Investor_Relations/annual-report-2025/pdf/AstraZeneca_Development_Pipeline_2025.pdf | J16: https://annual-report.bms.com/assets/bms-ar/documents/2025/2025-bms-development-portfolio.pdf
A17: Solid-tumor oncology | B17: Bispecific / dual-target antibody | C17: Other solid tumors | D17: overlap | E17: 2 | F17: 1 | G17: rilvegostomig; volrustomig | H17: pumitamig | I17: https://www.astrazeneca.com/content/dam/az/Investor_Relations/annual-report-2025/pdf/AstraZeneca_Development_Pipeline_2025.pdf | J17: https://annual-report.bms.com/assets/bms-ar/documents/2025/2025-bms-development-portfolio.pdf
A18: Solid-tumor oncology | B18: Small molecule / targeted degradation | C18: NSCLC | D18: bms-only | E18: 0 | F18: 1 | H18: navlimetostat | I18: https://www.astrazeneca.com/content/dam/az/Investor_Relations/annual-report-2025/pdf/AstraZeneca_Development_Pipeline_2025.pdf | J18: https://annual-report.bms.com/assets/bms-ar/documents/2025/2025-bms-development-portfolio.pdf
A19: Solid-tumor oncology | B19: Small molecule / targeted degradation | C19: Breast cancer | D19: az-only | E19: 2 | F19: 0 | G19: camizestrant; saruparib | I19: https://www.astrazeneca.com/content/dam/az/Investor_Relations/annual-report-2025/pdf/AstraZeneca_Development_Pipeline_2025.pdf | J19: https://annual-report.bms.com/assets/bms-ar/documents/2025/2025-bms-development-portfolio.pdf
A20: Solid-tumor oncology | B20: Small molecule / targeted degradation | C20: Prostate cancer | D20: overlap | E20: 1 | F20: 1 | G20: saruparib | H20: AR ligand-directed degrader | I20: https://www.astrazeneca.com/content/dam/az/Investor_Relations/annual-report-2025/pdf/AstraZeneca_Development_Pipeline_2025.pdf | J20: https://annual-report.bms.com/assets/bms-ar/documents/2025/2025-bms-development-portfolio.pdf
A21: Solid-tumor oncology | B21: Small molecule / targeted degradation | C21: Pancreatic cancer | D21: bms-only | E21: 0 | F21: 1 | H21: navlimetostat | I21: https://www.astrazeneca.com/content/dam/az/Investor_Relations/annual-report-2025/pdf/AstraZeneca_Development_Pipeline_2025.pdf | J21: https://annual-report.bms.com/assets/bms-ar/documents/2025/2025-bms-development-portfolio.pdf
A22: Solid-tumor oncology | B22: Small molecule / targeted degradation | C22: Other solid tumors | D22: overlap | E22: 1 | F22: 1 | G22: AZD9574 | H22: navlimetostat | I22: https://www.astrazeneca.com/content/dam/az/Investor_Relations/annual-report-2025/pdf/AstraZeneca_Development_Pipeline_2025.pdf | J22: https://annual-report.bms.com/assets/bms-ar/documents/2025/2025-bms-development-portfolio.pdf
A23: Solid-tumor oncology | B23: mAb / IO combination | C23: NSCLC | D23: overlap | E23: 1 | F23: 1 | G23: IPH5201 | H23: nivolumab + relatlimab HD | I23: https://www.astrazeneca.com/content/dam/az/Investor_Relations/annual-report-2025/pdf/AstraZeneca_Development_Pipeline_2025.pdf | J23: https://annual-report.bms.com/assets/bms-ar/documents/2025/2025-bms-development-portfolio.pdf
A24: Solid-tumor oncology | B24: mAb / IO combination | C24: SCLC | D24: bms-only | E24: 0 | F24: 1 | H24: atigotatug + nivolumab | I24: https://www.astrazeneca.com/content/dam/az/Investor_Relations/annual-report-2025/pdf/AstraZeneca_Development_Pipeline_2025.pdf | J24: https://annual-report.bms.com/assets/bms-ar/documents/2025/2025-bms-development-portfolio.pdf
A25: Solid-tumor oncology | B25: Radiopharmaceutical | C25: Prostate cancer | D25: az-only | E25: 1 | F25: 0 | G25: FPI-2265 | I25: https://www.astrazeneca.com/content/dam/az/Investor_Relations/annual-report-2025/pdf/AstraZeneca_Development_Pipeline_2025.pdf | J25: https://annual-report.bms.com/assets/bms-ar/documents/2025/2025-bms-development-portfolio.pdf
A26: Solid-tumor oncology | B26: Radiopharmaceutical | C26: GEP-NET | D26: bms-only | E26: 0 | F26: 1 | H26: RYZ101 | I26: https://www.astrazeneca.com/content/dam/az/Investor_Relations/annual-report-2025/pdf/AstraZeneca_Development_Pipeline_2025.pdf | J26: https://annual-report.bms.com/assets/bms-ar/documents/2025/2025-bms-development-portfolio.pdf
A27: Hematology | B27: CAR-T | C27: Multiple myeloma | D27: overlap | E27: 1 | F27: 1 | G27: AZD0120 | H27: arlo-cel | I27: https://www.astrazeneca.com/content/dam/az/Investor_Relations/annual-report-2025/pdf/AstraZeneca_Development_Pipeline_2025.pdf | J27: https://annual-report.bms.com/assets/bms-ar/documents/2025/2025-bms-development-portfolio.pdf
A28: Hematology | B28: Antibody-drug conjugate | C28: Multiple myeloma | D28: az-only | E28: 1 | F28: 0 | G28: AZD0305 | I28: https://www.astrazeneca.com/content/dam/az/Investor_Relations/annual-report-2025/pdf/AstraZeneca_Development_Pipeline_2025.pdf | J28: https://annual-report.bms.com/assets/bms-ar/documents/2025/2025-bms-development-portfolio.pdf
A29: Hematology | B29: T-cell engager | C29: B-cell lymphoma | D29: az-only | E29: 1 | F29: 0 | G29: surovatamig | I29: https://www.astrazeneca.com/content/dam/az/Investor_Relations/annual-report-2025/pdf/AstraZeneca_Development_Pipeline_2025.pdf | J29: https://annual-report.bms.com/assets/bms-ar/documents/2025/2025-bms-development-portfolio.pdf
A30: Hematology | B30: T-cell engager | C30: B-ALL | D30: az-only | E30: 1 | F30: 0 | G30: surovatamig | I30: https://www.astrazeneca.com/content/dam/az/Investor_Relations/annual-report-2025/pdf/AstraZeneca_Development_Pipeline_2025.pdf | J30: https://annual-report.bms.com/assets/bms-ar/documents/2025/2025-bms-development-portfolio.pdf
A31: Hematology | B31: Targeted protein degradation / CELMoD | C31: Multiple myeloma | D31: bms-only | E31: 0 | F31: 2 | H31: iberdomide; mezigdomide | I31: https://www.astrazeneca.com/content/dam/az/Investor_Relations/annual-report-2025/pdf/AstraZeneca_Development_Pipeline_2025.pdf | J31: https://annual-report.bms.com/assets/bms-ar/documents/2025/2025-bms-development-portfolio.pdf
A32: Hematology | B32: Targeted protein degradation / CELMoD | C32: B-cell lymphoma | D32: bms-only | E32: 0 | F32: 1 | H32: golcadomide | I32: https://www.astrazeneca.com/content/dam/az/Investor_Relations/annual-report-2025/pdf/AstraZeneca_Development_Pipeline_2025.pdf | J32: https://annual-report.bms.com/assets/bms-ar/documents/2025/2025-bms-development-portfolio.pdf
A33: Hematology | B33: Small molecule | C33: Hodgkin lymphoma | D33: az-only | E33: 1 | F33: 0 | G33: AZD3470 | I33: https://www.astrazeneca.com/content/dam/az/Investor_Relations/annual-report-2025/pdf/AstraZeneca_Development_Pipeline_2025.pdf | J33: https://annual-report.bms.com/assets/bms-ar/documents/2025/2025-bms-development-portfolio.pdf
A34: Immunology, respiratory & fibrosis | B34: Oral / systemic small molecule | C34: Asthma | D34: az-only | E34: 1 | F34: 0 | G34: atuliflapon | I34: https://www.astrazeneca.com/content/dam/az/Investor_Relations/annual-report-2025/pdf/AstraZeneca_Development_Pipeline_2025.pdf | J34: https://annual-report.bms.com/assets/bms-ar/documents/2025/2025-bms-development-portfolio.pdf
A35: Immunology, respiratory & fibrosis | B35: Oral / systemic small molecule | C35: COPD | D35: az-only | E35: 1 | F35: 0 | G35: AZD6793 | I35: https://www.astrazeneca.com/content/dam/az/Investor_Relations/annual-report-2025/pdf/AstraZeneca_Development_Pipeline_2025.pdf | J35: https://annual-report.bms.com/assets/bms-ar/documents/2025/2025-bms-development-portfolio.pdf
A36: Immunology, respiratory & fibrosis | B36: Oral / systemic small molecule | C36: Pulmonary fibrosis | D36: bms-only | E36: 0 | F36: 1 | H36: admilparant | I36: https://www.astrazeneca.com/content/dam/az/Investor_Relations/annual-report-2025/pdf/AstraZeneca_Development_Pipeline_2025.pdf | J36: https://annual-report.bms.com/assets/bms-ar/documents/2025/2025-bms-development-portfolio.pdf
A37: Immunology, respiratory & fibrosis | B37: Inhaled small molecule | C37: Asthma | D37: az-only | E37: 1 | F37: 0 | G37: AZD4604 | I37: https://www.astrazeneca.com/content/dam/az/Investor_Relations/annual-report-2025/pdf/AstraZeneca_Development_Pipeline_2025.pdf | J37: https://annual-report.bms.com/assets/bms-ar/documents/2025/2025-bms-development-portfolio.pdf
A38: Immunology, respiratory & fibrosis | B38: Monoclonal / bispecific antibody | C38: COPD | D38: az-only | E38: 1 | F38: 0 | G38: tozorakimab | I38: https://www.astrazeneca.com/content/dam/az/Investor_Relations/annual-report-2025/pdf/AstraZeneca_Development_Pipeline_2025.pdf | J38: https://annual-report.bms.com/assets/bms-ar/documents/2025/2025-bms-development-portfolio.pdf
A39: Immunology, respiratory & fibrosis | B39: Monoclonal / bispecific antibody | C39: Rheumatoid arthritis | D39: az-only | E39: 1 | F39: 0 | G39: AZD1163 | I39: https://www.astrazeneca.com/content/dam/az/Investor_Relations/annual-report-2025/pdf/AstraZeneca_Development_Pipeline_2025.pdf | J39: https://annual-report.bms.com/assets/bms-ar/documents/2025/2025-bms-development-portfolio.pdf
A40: Immunology, respiratory & fibrosis | B40: Monoclonal / bispecific antibody | C40: Crohn's disease | D40: az-only | E40: 1 | F40: 0 | G40: AZD7798 | I40: https://www.astrazeneca.com/content/dam/az/Investor_Relations/annual-report-2025/pdf/AstraZeneca_Development_Pipeline_2025.pdf | J40: https://annual-report.bms.com/assets/bms-ar/documents/2025/2025-bms-development-portfolio.pdf
A41: Immunology, respiratory & fibrosis | B41: Monoclonal / bispecific antibody | C41: IgG4-related disease | D41: bms-only | E41: 0 | F41: 1 | H41: obexelimab | I41: https://www.astrazeneca.com/content/dam/az/Investor_Relations/annual-report-2025/pdf/AstraZeneca_Development_Pipeline_2025.pdf | J41: https://annual-report.bms.com/assets/bms-ar/documents/2025/2025-bms-development-portfolio.pdf
A42: Immunology, respiratory & fibrosis | B42: Monoclonal / bispecific antibody | C42: Severe viral LRTD | D42: az-only | E42: 1 | F42: 0 | G42: tozorakimab | I42: https://www.astrazeneca.com/content/dam/az/Investor_Relations/annual-report-2025/pdf/AstraZeneca_Development_Pipeline_2025.pdf | J42: https://annual-report.bms.com/assets/bms-ar/documents/2025/2025-bms-development-portfolio.pdf
A43: Immunology, respiratory & fibrosis | B43: Inhaled biologic | C43: Asthma | D43: az-only | E43: 1 | F43: 0 | G43: AZD8630 | I43: https://www.astrazeneca.com/content/dam/az/Investor_Relations/annual-report-2025/pdf/AstraZeneca_Development_Pipeline_2025.pdf | J43: https://annual-report.bms.com/assets/bms-ar/documents/2025/2025-bms-development-portfolio.pdf
A44: Immunology, respiratory & fibrosis | B44: CAR-T | C44: SLE / systemic sclerosis | D44: bms-only | E44: 0 | F44: 1 | H44: zola-cel (CD19 NEX-T) | I44: https://www.astrazeneca.com/content/dam/az/Investor_Relations/annual-report-2025/pdf/AstraZeneca_Development_Pipeline_2025.pdf | J44: https://annual-report.bms.com/assets/bms-ar/documents/2025/2025-bms-development-portfolio.pdf
A45: Cardiovascular | B45: Small molecule / oral therapy | C45: Heart failure | D45: overlap | E45: 1 | F45: 1 | G45: AZD5462 | H45: MYK-224 | I45: https://www.astrazeneca.com/content/dam/az/Investor_Relations/annual-report-2025/pdf/AstraZeneca_Development_Pipeline_2025.pdf | J45: https://annual-report.bms.com/assets/bms-ar/documents/2025/2025-bms-development-portfolio.pdf
A46: Cardiovascular | B46: Small molecule / oral therapy | C46: Hypertension / aldosteronism | D46: az-only | E46: 1 | F46: 0 | G46: baxdrostat | I46: https://www.astrazeneca.com/content/dam/az/Investor_Relations/annual-report-2025/pdf/AstraZeneca_Development_Pipeline_2025.pdf | J46: https://annual-report.bms.com/assets/bms-ar/documents/2025/2025-bms-development-portfolio.pdf
A47: Cardiovascular | B47: Small molecule / oral therapy | C47: AF / stroke prevention | D47: bms-only | E47: 0 | F47: 1 | H47: milvexian | I47: https://www.astrazeneca.com/content/dam/az/Investor_Relations/annual-report-2025/pdf/AstraZeneca_Development_Pipeline_2025.pdf | J47: https://annual-report.bms.com/assets/bms-ar/documents/2025/2025-bms-development-portfolio.pdf
A48: Cardiovascular | B48: Other targeted therapy | C48: Dyslipidemia | D48: az-only | E48: 1 | F48: 0 | G48: laroprovstat | I48: https://www.astrazeneca.com/content/dam/az/Investor_Relations/annual-report-2025/pdf/AstraZeneca_Development_Pipeline_2025.pdf | J48: https://annual-report.bms.com/assets/bms-ar/documents/2025/2025-bms-development-portfolio.pdf
A49: Rare disease | B49: Protein / fusion therapeutic | C49: Primary membranous nephropathy | D49: az-only | E49: 1 | F49: 0 | G49: ALXN1920 | I49: https://www.astrazeneca.com/content/dam/az/Investor_Relations/annual-report-2025/pdf/AstraZeneca_Development_Pipeline_2025.pdf | J49: https://annual-report.bms.com/assets/bms-ar/documents/2025/2025-bms-development-portfolio.pdf
A50: Rare disease | B50: RNA / siRNA | C50: Antibody-mediated rejection | D50: az-only | E50: 1 | F50: 0 | G50: ALXN2030 | I50: https://www.astrazeneca.com/content/dam/az/Investor_Relations/annual-report-2025/pdf/AstraZeneca_Development_Pipeline_2025.pdf | J50: https://annual-report.bms.com/assets/bms-ar/documents/2025/2025-bms-development-portfolio.pdf
A51: Rare disease | B51: Small molecule / kinase inhibitor | C51: ANCA vasculitis | D51: az-only | E51: 1 | F51: 0 | G51: tarperprumig | I51: https://www.astrazeneca.com/content/dam/az/Investor_Relations/annual-report-2025/pdf/AstraZeneca_Development_Pipeline_2025.pdf | J51: https://annual-report.bms.com/assets/bms-ar/documents/2025/2025-bms-development-portfolio.pdf
A52: Rare disease | B52: mAb / nanobody | C52: AL amyloidosis | D52: az-only | E52: 1 | F52: 0 | G52: anselamimab | I52: https://www.astrazeneca.com/content/dam/az/Investor_Relations/annual-report-2025/pdf/AstraZeneca_Development_Pipeline_2025.pdf | J52: https://annual-report.bms.com/assets/bms-ar/documents/2025/2025-bms-development-portfolio.pdf
A53: Rare disease | B53: mAb / nanobody | C53: ATTR-CM | D53: az-only | E53: 1 | F53: 0 | G53: cliramitug | I53: https://www.astrazeneca.com/content/dam/az/Investor_Relations/annual-report-2025/pdf/AstraZeneca_Development_Pipeline_2025.pdf | J53: https://annual-report.bms.com/assets/bms-ar/documents/2025/2025-bms-development-portfolio.pdf
A54: Rare disease | B54: mAb / nanobody | C54: gMG | D54: az-only | E54: 1 | F54: 0 | G54: gefurulimab | I54: https://www.astrazeneca.com/content/dam/az/Investor_Relations/annual-report-2025/pdf/AstraZeneca_Development_Pipeline_2025.pdf | J54: https://annual-report.bms.com/assets/bms-ar/documents/2025/2025-bms-development-portfolio.pdf
A55: Rare disease | B55: Enzyme replacement | C55: Hypophosphatasia | D55: az-only | E55: 1 | F55: 0 | G55: efzimfotase alfa | I55: https://www.astrazeneca.com/content/dam/az/Investor_Relations/annual-report-2025/pdf/AstraZeneca_Development_Pipeline_2025.pdf | J55: https://annual-report.bms.com/assets/bms-ar/documents/2025/2025-bms-development-portfolio.pdf
A56: Rare disease | B56: Peptide / receptor agonist-antagonist | C56: Acromegaly | D56: az-only | E56: 1 | F56: 0 | G56: ALXN2420 | I56: https://www.astrazeneca.com/content/dam/az/Investor_Relations/annual-report-2025/pdf/AstraZeneca_Development_Pipeline_2025.pdf | J56: https://annual-report.bms.com/assets/bms-ar/documents/2025/2025-bms-development-portfolio.pdf
A57: Rare disease | B57: Peptide / receptor agonist-antagonist | C57: Hypoparathyroidism | D57: az-only | E57: 1 | F57: 0 | G57: eneboparatide | I57: https://www.astrazeneca.com/content/dam/az/Investor_Relations/annual-report-2025/pdf/AstraZeneca_Development_Pipeline_2025.pdf | J57: https://annual-report.bms.com/assets/bms-ar/documents/2025/2025-bms-development-portfolio.pdf
A58: Renal & metabolic | B58: Peptide / incretin | C58: Obesity / weight management | D58: az-only | E58: 1 | F58: 0 | G58: AZD6234 | I58: https://www.astrazeneca.com/content/dam/az/Investor_Relations/annual-report-2025/pdf/AstraZeneca_Development_Pipeline_2025.pdf | J58: https://annual-report.bms.com/assets/bms-ar/documents/2025/2025-bms-development-portfolio.pdf
A59: Renal & metabolic | B59: Oral small molecule | C59: Obesity / weight management | D59: az-only | E59: 1 | F59: 0 | G59: elecoglipron (AZD5004) | I59: https://www.astrazeneca.com/content/dam/az/Investor_Relations/annual-report-2025/pdf/AstraZeneca_Development_Pipeline_2025.pdf | J59: https://annual-report.bms.com/assets/bms-ar/documents/2025/2025-bms-development-portfolio.pdf
... A68: Infectious disease | B68: Antibody combination | C68: S. aureus prevention | D68: az-only | E68: 1 | F68: 0 | G68: AZD7760 | I68: https://www.astrazeneca.com/content/dam/az/Investor_Relations/annual-report-2025/pdf/AstraZeneca_Development_Pipeline_2025.pdf | J68: https://annual-report.bms.com/assets/bms-ar/documents/2025/2025-bms-development-portfolio.pdf
A69: Neuroscience | B69: Monoclonal antibody | C69: Alzheimer's disease | D69: bms-only | E69: 0 | F69: 1 | H69: anti-MTBR tau | I69: https://www.astrazeneca.com/content/dam/az/Investor_Relations/annual-report-2025/pdf/AstraZeneca_Development_Pipeline_2025.pdf | J69: https://annual-report.bms.com/assets/bms-ar/documents/2025/2025-bms-development-portfolio.pdf
A70: Neuroscience | B70: Small molecule | C70: AD agitation | D70: bms-only | E70: 0 | F70: 1 | H70: FAAH/MAGL dual inhibitor | I70: https://www.astrazeneca.com/content/dam/az/Investor_Relations/annual-report-2025/pdf/AstraZeneca_Development_Pipeline_2025.pdf | J70: https://annual-report.bms.com/assets/bms-ar/documents/2025/2025-bms-development-portfolio.pdf
A71: Neuroscience | B71: Small molecule | C71: MS spasticity | D71: bms-only | E71: 0 | F71: 1 | H71: FAAH/MAGL dual inhibitor | I71: https://www.astrazeneca.com/content/dam/az/Investor_Relations/annual-report-2025/pdf/AstraZeneca_Development_Pipeline_2025.pdf | J71: https://annual-report.bms.com/assets/bms-ar/documents/2025/2025-bms-development-portfolio.pdf

Sheet Matrix_Program_Map
A1: Company | B1: Disease area | C1: Program | D1: Normalized modality family | E1: Normalized indication territory | F1: Source URL
A2: Bristol Myers Squibb | B2: Solid-tumor oncology | C2: izalontamab brengitecan (iza-bren) | D2: Antibody-drug conjugate | E2: Breast cancer | F2: https://annual-report.bms.com/assets/bms-ar/documents/2025/2025-bms-development-portfolio.pdf
A3: AstraZeneca | B3: Solid-tumor oncology | C3: puxitatug samrotecan | D3: Antibody-drug conjugate | E3: Endometrial cancer | F3: https://www.astrazeneca.com/content/dam/az/Investor_Relations/annual-report-2025/pdf/AstraZeneca_Development_Pipeline_2025.pdf
A4: AstraZeneca | B4: Solid-tumor oncology | C4: sonesitatug vedotin | D4: Antibody-drug conjugate | E4: Gastric / GEJ | F4: https://www.astrazeneca.com/content/dam/az/Investor_Relations/annual-report-2025/pdf/AstraZeneca_Development_Pipeline_2025.pdf
A5: Bristol Myers Squibb | B5: Solid-tumor oncology | C5: izalontamab brengitecan (iza-bren) | D5: Antibody-drug conjugate | E5: NSCLC | F5: https://annual-report.bms.com/assets/bms-ar/documents/2025/2025-bms-development-portfolio.pdf
A6: AstraZeneca | B6: Solid-tumor oncology | C6: puxitatug samrotecan | D6: Antibody-drug conjugate | E6: Other solid tumors | F6: https://www.astrazeneca.com/content/dam/az/Investor_Relations/annual-report-2025/pdf/AstraZeneca_Development_Pipeline_2025.pdf
A7: AstraZeneca | B7: Solid-tumor oncology | C7: sonesitatug vedotin | D7: Antibody-drug conjugate | E7: Other solid tumors | F7: https://www.astrazeneca.com/content/dam/az/Investor_Relations/annual-report-2025/pdf/AstraZeneca_Development_Pipeline_2025.pdf
A8: AstraZeneca | B8: Solid-tumor oncology | C8: tilatamig samrotecan | D8: Antibody-drug conjugate | E8: Other solid tumors | F8: https://www.astrazeneca.com/content/dam/az/Investor_Relations/annual-report-2025/pdf/AstraZeneca_Development_Pipeline_2025.pdf
A9: AstraZeneca | B9: Solid-tumor oncology | C9: torvutatug samrotecan (AZD5335) | D9: Antibody-drug conjugate | E9: Other solid tumors | F9: https://www.astrazeneca.com/content/dam/az/Investor_Relations/annual-report-2025/pdf/AstraZeneca_Development_Pipeline_2025.pdf
A10: AstraZeneca | B10: Solid-tumor oncology | C10: torvutatug samrotecan (AZD5335) | D10: Antibody-drug conjugate | E10: Ovarian cancer | F10: https://www.astrazeneca.com/content/dam/az/Investor_Relations/annual-report-2025/pdf/AstraZeneca_Development_Pipeline_2025.pdf
A11: Bristol Myers Squibb | B11: Solid-tumor oncology | C11: izalontamab brengitecan (iza-bren) | D11: Antibody-drug conjugate | E11: Urothelial cancer | F11: https://annual-report.bms.com/assets/bms-ar/documents/2025/2025-bms-development-portfolio.pdf
A12: Bristol Myers Squibb | B12: Solid-tumor oncology | C12: pumitamig | D12: Bispecific / dual-target antibody | E12: Breast cancer | F12: https://annual-report.bms.com/assets/bms-ar/documents/2025/2025-bms-development-portfolio.pdf
... A83: Bristol Myers Squibb | B83: Neuroscience | C83: FAAH/MAGL dual inhibitor | D83: Small molecule | E83: MS spasticity | F83: https://annual-report.bms.com/assets/bms-ar/documents/2025/2025-bms-development-portfolio.pdf

Sheet Program_Details
A1: Disease area | B1: Overlap indication | C1: Company | D1: Program | E1: Pipeline stage | F1: Representative modality / mechanism | G1: ClinicalTrials.gov ID | H1: Representative trial | I1: Potential launch indication (analyst scenario) | J1: Clinical setting / line of therapy | K1: Primary completion date | L1: Primary completion year | M1: Launch lag - low (years) | N1: Launch lag - high (years) | O1: Illustrative launch start | P1: Illustrative launch end | Q1: Illustrative launch window | R1: Historical sales of asset | S1: Commercial benchmark IDs | T1: Trial URL | U1: Pipeline source URL | V1: Notes | W1: Brand / marketed component | X1: Brand relationship | Y1: Marketed status | Z1: Sales trend IDs | AA1: Brand / sales source URL
A2: Cardiovascular | B2: Heart failure | C2: AstraZeneca | D2: AZD5462 | E2: Phase IIb | F2: RXFP1 agonist | G2: NCT06299826 | H2: LUMINARA | I2: Chronic heart failure | J2: Stable chronic heart failure; mechanism-focused proof of concept | K2: 46063 | L2: =YEAR(K2) | M2: 3 | N2: 5 | O2: =IF(OR(L2="",M2=""),"",L2+M2) | P2: =IF(OR(L2="",N2=""),"",L2+N2) | Q2: =IF(O2="","Not estimated",TEXT(O2,"0")&"-"&TEXT(P2,"0")) | R2: Not launched - no historical sales | S2: HF_CAMZYOS_2025 | T2: https://clinicaltrials.gov/study/NCT06299826 | U2: https://www.astrazeneca.com/content/dam/az/Investor_Relations/annual-report-2025/pdf/AstraZeneca_Development_Pipeline_2025.pdf | V2: Phase IIb; no pivotal launch assumption is implied.
A3: Cardiovascular | B3: Heart failure | C3: Bristol Myers Squibb | D3: MYK-224 | E3: Phase IIa | F3: Cardiac myosin inhibitor | G3: NCT06122779 | H3: AURORA-HFpEF | I3: Heart failure with preserved ejection fraction | J3: Symptomatic HFpEF; randomized placebo-controlled proof of concept | K3: 46206 | L3: =YEAR(K3) | M3: 3 | N3: 5 | O3: =IF(OR(L3="",M3=""),"",L3+M3) | P3: =IF(OR(L3="",N3=""),"",L3+N3) | Q3: =IF(O3="","Not estimated",TEXT(O3,"0")&"-"&TEXT(P3,"0")) | R3: Not launched - no historical sales | S3: HF_CAMZYOS_2025 | T3: https://clinicaltrials.gov/study/NCT06122779 | U3: https://annual-report.bms.com/assets/bms-ar/documents/2025/2025-bms-development-portfolio.pdf | V3: Cardiac myosin inhibitor; not the same indication as approved Camzyos.
A4: Hematology | B4: B-cell lymphoma | C4: AstraZeneca | D4: surovatamig | E4: Phase III | F4: CD19/CD3 T-cell engager | G4: NCT06549595 | H4: SOUNDTRACK-F1 | I4: Previously untreated follicular lymphoma | J4: First-line; surovatamig plus rituximab versus chemoimmunotherapy | K4: 48178 | L4: =YEAR(K4) | M4: 1 | N4: 2 | O4: =IF(OR(L4="",M4=""),"",L4+M4) | P4: =IF(OR(L4="",N4=""),"",L4+N4) | Q4: =IF(O4="","Not estimated",TEXT(O4,"0")&"-"&TEXT(P4,"0")) | R4: Not launched - no historical sales | S4: LYMPHOMA_BREYANZI_2025 | T4: https://clinicaltrials.gov/study/NCT06549595 | U4: https://www.astrazeneca.com/content/dam/az/Investor_Relations/annual-report-2025/pdf/AstraZeneca_Development_Pipeline_2025.pdf | V4: Representative pivotal study in the B-cell lymphoma territory.
A5: Hematology | B5: B-cell lymphoma | C5: Bristol Myers Squibb | D5: golcadomide | E5: Phase III | F5: CELMoD / targeted protein degradation | G5: NCT06356129 | H5: GOLSEEK-1 | I5: Previously untreated high-risk large B-cell lymphoma | J5: First-line; golcadomide plus R-CHOP | K5: 46979 | L5: =YEAR(K5) | M5: 1 | N5: 2 | O5: =IF(OR(L5="",M5=""),"",L5+M5) | P5: =IF(OR(L5="",N5=""),"",L5+N5) | Q5: =IF(O5="","Not estimated",TEXT(O5,"0")&"-"&TEXT(P5,"0")) | R5: Not launched - no historical sales | S5: LYMPHOMA_BREYANZI_2025 | T5: https://clinicaltrials.gov/study/NCT06356129 | U5: https://annual-report.bms.com/assets/bms-ar/documents/2025/2025-bms-development-portfolio.pdf | V5: Representative Phase III study; additional follicular lymphoma work is underway.
A6: Hematology | B6: Multiple myeloma | C6: AstraZeneca | D6: AZD0120 | E6: Phase Ib/II | F6: CD19/BCMA CAR-T | G6: NCT05850234 | H6: DURGA-1 | I6: Relapsed/refractory multiple myeloma | J6: At least three prior lines; CD19/BCMA dual CAR-T | K6: 46630 | L6: =YEAR(K6) | M6: 4 | N6: 6 | O6: =IF(OR(L6="",M6=""),"",L6+M6) | P6: =IF(OR(L6="",N6=""),"",L6+N6) | Q6: =IF(O6="","Not estimated",TEXT(O6,"0")&"-"&TEXT(P6,"0")) | R6: Not launched - no historical sales | S6: MM_REVLIMID_2021; MM_POMALYST_2021 | T6: https://clinicaltrials.gov/study/NCT05850234 | U6: https://www.astrazeneca.com/content/dam/az/Investor_Relations/annual-report-2025/pdf/AstraZeneca_Development_Pipeline_2025.pdf | V6: Early-stage CAR-T program; launch window is highly uncertain.
A7: Hematology | B7: Multiple myeloma | C7: AstraZeneca | D7: AZD0305 | E7: Phase I/II | F7: GPRC5D MMAE antibody-drug conjugate | G7: NCT06106945 | H7: Modular Phase I/II study | I7: Multiple myeloma | J7: Monotherapy and combination dose escalation/expansion | K7: 46615 | L7: =YEAR(K7) | M7: 4 | N7: 6 | O7: =IF(OR(L7="",M7=""),"",L7+M7) | P7: =IF(OR(L7="",N7=""),"",L7+N7) | Q7: =IF(O7="","Not estimated",TEXT(O7,"0")&"-"&TEXT(P7,"0")) | R7: Not launched - no historical sales | S7: MM_REVLIMID_2021; MM_POMALYST_2021 | T7: https://clinicaltrials.gov/study/NCT06106945 | U7: https://www.astrazeneca.com/content/dam/az/Investor_Relations/annual-report-2025/pdf/AstraZeneca_Development_Pipeline_2025.pdf | V7: GPRC5D ADC; launch window is highly uncertain.
A8: Hematology | B8: Multiple myeloma | C8: Bristol Myers Squibb | D8: arlo-cel | E8: Phase III | F8: GPRC5D-directed autologous CAR-T | G8: NCT06615479 | H8: QUINTESSENTIAL-2 | I8: Relapsed/refractory, lenalidomide-exposed multiple myeloma | J8: Relapsed/refractory setting; versus standard regimens | K8: 46751 | L8: =YEAR(K8) | M8: 1 | N8: 2 | O8: =IF(OR(L8="",M8=""),"",L8+M8) | P8: =IF(OR(L8="",N8=""),"",L8+N8) | Q8: =IF(O8="","Not estimated",TEXT(O8,"0")&"-"&TEXT(P8,"0")) | R8: Not launched - no historical sales | S8: MM_REVLIMID_2021; MM_POMALYST_2021 | T8: https://clinicaltrials.gov/study/NCT06615479 | U8: https://annual-report.bms.com/assets/bms-ar/documents/2025/2025-bms-development-portfolio.pdf | V8: GPRC5D-directed CAR-T; program also has a later-line Phase II study.
A9: Hematology | B9: Multiple myeloma | C9: Bristol Myers Squibb | D9: iberdomide | E9: Phase III | F9: CELMoD / targeted protein degradation | G9: NCT05827016 | H9: EXCALIBER-Maintenance | I9: Newly diagnosed multiple myeloma maintenance | J9: Maintenance following autologous stem-cell transplant | K9: 47192 | L9: =YEAR(K9) | M9: 1 | N9: 2 | O9: =IF(OR(L9="",M9=""),"",L9+M9) | P9: =IF(OR(L9="",N9=""),"",L9+N9) | Q9: =IF(O9="","Not estimated",TEXT(O9,"0")&"-"&TEXT(P9,"0")) | R9: Not launched - no historical sales | S9: MM_REVLIMID_2021; MM_POMALYST_2021 | T9: https://clinicaltrials.gov/study/NCT05827016 | U9: https://annual-report.bms.com/assets/bms-ar/documents/2025/2025-bms-development-portfolio.pdf | V9: Representative Phase III study; the asset has a broader development program.
A10: Hematology | B10: Multiple myeloma | C10: Bristol Myers Squibb | D10: mezigdomide | E10: Phase III | F10: CELMoD / targeted protein degradation | G10: NCT05552976 | H10: SUCCESSOR-2 | I10: Relapsed/refractory multiple myeloma | J10: Mezigdomide-carfilzomib-dexamethasone versus carfilzomib-dexamethasone | K10: 46221 | L10: =YEAR(K10) | M10: 1 | N10: 2 | O10: =IF(OR(L10="",M10=""),"",L10+M10) | P10: =IF(OR(L10="",N10=""),"",L10+N10) | Q10: =IF(O10="","Not estimated",TEXT(O10,"0")&"-"&TEXT(P10,"0")) | R10: Not launched - no historical sales | S10: MM_REVLIMID_2021; MM_POMALYST_2021 | T10: https://clinicaltrials.gov/study/NCT05552976 | U10: https://annual-report.bms.com/assets/bms-ar/documents/2025/2025-bms-development-portfolio.pdf | V10: BMS reported positive Phase III results in 2026; launch timing remains an analyst scenario.
A11: Solid-tumor oncology | B11: NSCLC | C11: AstraZeneca | D11: IPH5201 | E11: Phase II | F11: CD39 monoclonal antibody | G11: NCT05742607 | H11: MATISSE | I11: Resectable stage II-IIIA NSCLC | J11: Untreated; neoadjuvant therapy before surgery followed by adjuvant therapy | K11: 2025-06 | L11: =IF(K11="","",VALUE(LEFT(K11,4))) | M11: 3 | N11: 5 | O11: =IF(OR(L11="",M11=""),"",L11+M11) | P11: =IF(OR(L11="",N11=""),"",L11+N11) | Q11: =IF(O11="","Not estimated",TEXT(O11,"0")&"-"&TEXT(P11,"0")) | R11: Not launched - no historical sales | S11: NSCLC_TAGRISSO_2025; NSCLC_OPDIVO_2025 | T11: https://clinicaltrials.gov/study/NCT05742607 | U11: https://www.astrazeneca.com/content/dam/az/Investor_Relations/annual-report-2025/pdf/AstraZeneca_Development_Pipeline_2025.pdf | V11: Early-stage study; no pivotal launch assumption is implied. | W11: Imfinzi | X11: Marketed combination backbone: Imfinzi (durvalumab) | Y11: IPH5201 remains investigational; Imfinzi is marketed | Z11: IMFINZI | AA11: https://www.sec.gov/Archives/edgar/data/901832/000110465926019130/azn-20251231x20f.htm
A12: Solid-tumor oncology | B12: NSCLC | C12: AstraZeneca | D12: rilvegostomig | E12: Phase III | F12: PD-1/TIGIT bispecific antibody | G12: NCT06692738 | H12: ARTEMIDE-Lung02 | I12: Metastatic squamous NSCLC, PD-L1 >=1% | J12: First-line; rilvegostomig plus platinum chemotherapy | K12: 47154 | L12: =YEAR(K12) | M12: 1 | N12: 2 | O12: =IF(OR(L12="",M12=""),"",L12+M12) | P12: =IF(OR(L12="",N12=""),"",L12+N12) | Q12: =IF(O12="","Not estimated",TEXT(O12,"0")&"-"&TEXT(P12,"0")) | R12: Not launched - no historical sales | S12: NSCLC_TAGRISSO_2025; NSCLC_OPDIVO_2025 | T12: https://clinicaltrials.gov/study/NCT06692738 | U12: https://www.astrazeneca.com/content/dam/az/Investor_Relations/annual-report-2025/pdf/AstraZeneca_Development_Pipeline_2025.pdf | V12: Representative pivotal study; the asset has additional NSCLC programs.
A13: Solid-tumor oncology | B13: NSCLC | C13: AstraZeneca | D13: volrustomig | E13: Phase III | F13: PD-1/CTLA-4 bispecific antibody | G13: NCT05984277 | H13: eVOLVE-Lung02 | I13: Metastatic NSCLC, PD-L1 <50% | J13: First-line; volrustomig plus histology-specific chemotherapy | K13: 46867 | L13: =YEAR(K13) | M13: 1 | N13: 2 | O13: =IF(OR(L13="",M13=""),"",L13+M13) | P13: =IF(OR(L13="",N13=""),"",L13+N13) | Q13: =IF(O13="","Not estimated",TEXT(O13,"0")&"-"&TEXT(P13,"0")) | R13: Not launched - no historical sales | S13: NSCLC_TAGRISSO_2025; NSCLC_OPDIVO_2025 | T13: https://clinicaltrials.gov/study/NCT05984277 | U13: https://www.astrazeneca.com/content/dam/az/Investor_Relations/annual-report-2025/pdf/AstraZeneca_Development_Pipeline_2025.pdf | V13: Representative pivotal study.
A14: Solid-tumor oncology | B14: NSCLC | C14: Bristol Myers Squibb | D14: izalontamab brengitecan (iza-bren) | E14: Phase II/III | F14: EGFR x HER3 bispecific antibody-drug conjugate | G14: NCT07100080 | H14: IZABRIGHT-Lung01 | I14: EGFR-mutated NSCLC after EGFR-TKI failure | J14: Post-EGFR TKI; compared with platinum-pemetrexed | K14: 47102 | L14: =YEAR(K14) | M14: 1 | N14: 3 | O14: =IF(OR(L14="",M14=""),"",L14+M14) | P14: =IF(OR(L14="",N14=""),"",L14+N14) | Q14: =IF(O14="","Not estimated",TEXT(O14,"0")&"-"&TEXT(P14,"0")) | R14: Not launched - no historical sales | S14: NSCLC_TAGRISSO_2025; NSCLC_OPDIVO_2025 | T14: https://clinicaltrials.gov/study/NCT07100080 | U14: https://annual-report.bms.com/assets/bms-ar/documents/2025/2025-bms-development-portfolio.pdf | V14: Phase II/III design.
A15: Solid-tumor oncology | B15: NSCLC | C15: Bristol Myers Squibb | D15: navlimetostat | E15: Phase II | F15: PRMT5 inhibitor | G15: NCT06855771 | H15: MountainTAP-9 | I15: MTAP-deleted advanced or metastatic NSCLC | J15: Previously treated; after progression on prior therapies | K15: 47116 | L15: =YEAR(K15) | M15: 3 | N15: 5 | O15: =IF(OR(L15="",M15=""),"",L15+M15) | P15: =IF(OR(L15="",N15=""),"",L15+N15) | Q15: =IF(O15="","Not estimated",TEXT(O15,"0")&"-"&TEXT(P15,"0")) | R15: Not launched - no historical sales | S15: NSCLC_TAGRISSO_2025; NSCLC_OPDIVO_2025 | T15: https://clinicaltrials.gov/study/NCT06855771 | U15: https://annual-report.bms.com/assets/bms-ar/documents/2025/2025-bms-development-portfolio.pdf | V15: Phase II; a registrational path is not assumed.
A16: Solid-tumor oncology | B16: NSCLC | C16: Bristol Myers Squibb | D16: nivolumab + relatlimab HD | E16: Phase III | F16: PD-1 plus LAG-3 immuno-oncology combination | G16: NCT06561386 | H16: RELATIVITY-1093 | I16: Stage IV/recurrent nonsquamous NSCLC, PD-L1 >=1% | J16: First-line; nivolumab-relatlimab fixed dose plus chemotherapy | K16: 47694 | L16: =YEAR(K16) | M16: 1 | N16: 2 | O16: =IF(OR(L16="",M16=""),"",L16+M16) | P16: =IF(OR(L16="",N16=""),"",L16+N16) | Q16: =IF(O16="","Not estimated",TEXT(O16,"0")&"-"&TEXT(P16,"0")) | R16: Not launched - no historical sales | S16: NSCLC_TAGRISSO_2025; NSCLC_OPDIVO_2025 | T16: https://clinicaltrials.gov/study/NCT06561386 | U16: https://annual-report.bms.com/assets/bms-ar/documents/2025/2025-bms-development-portfolio.pdf | V16: Potential label expansion of an approved combination; counted here as an investigational program in the matched snapshot. | W16: Opdualag | X16: Related marketed fixed-dose combination: nivolumab + relatlimab | Y16: Higher-dose / chemotherapy regimen remains investigational | Z16: OPDUALAG | OPDIVO_FRANCHISE | AA16: https://www.sec.gov/Archives/edgar/data/14272/000001427226000004/bmy-20251231.htm
A17: Solid-tumor oncology | B17: NSCLC | C17: Bristol Myers Squibb | D17: pumitamig | E17: Phase III | F17: PD-L1 x VEGF-A bispecific antibody | G17: NCT07361510 | H17: ROSETTA Lung-202 | I17: Advanced NSCLC, PD-L1 >=50% | J17: First-line monotherapy versus pembrolizumab | K17: 48135 | L17: =YEAR(K17) | M17: 1 | N17: 2 | O17: =IF(OR(L17="",M17=""),"",L17+M17) | P17: =IF(OR(L17="",N17=""),"",L17+N17) | Q17: =IF(O17="","Not estimated",TEXT(O17,"0")&"-"&TEXT(P17,"0")) | R17: Not launched - no historical sales | S17: NSCLC_TAGRISSO_2025; NSCLC_OPDIVO_2025 | T17: https://clinicaltrials.gov/study/NCT07361510 | U17: https://annual-report.bms.com/assets/bms-ar/documents/2025/2025-bms-development-portfolio.pdf | V17: Representative Phase III study; later timing reflects the currently posted trial schedule.
A18: Solid-tumor oncology | B18: Prostate cancer | C18: AstraZeneca | D18: FPI-2265 | E18: Phase II | F18: PSMA-targeted actinium radioconjugate | G18: NCT06402331 | H18: AlphaBreak | I18: PSMA-positive metastatic castration-resistant prostate cancer | J18: Post-lutetium PSMA radioligand therapy; dose optimization | K18: 46379 | L18: =YEAR(K18) | M18: 3 | N18: 5 | O18: =IF(OR(L18="",M18=""),"",L18+M18) | P18: =IF(OR(L18="",N18=""),"",L18+N18) | Q18: =IF(O18="","Not estimated",TEXT(O18,"0")&"-"&TEXT(P18,"0")) | R18: Not launched - no historical sales | T18: https://clinicaltrials.gov/study/NCT06402331 | U18: https://www.astrazeneca.com/content/dam/az/Investor_Relations/annual-report-2025/pdf/AstraZeneca_Development_Pipeline_2025.pdf | V18: Phase II; additional combination work is underway.
A19: Solid-tumor oncology | B19: Prostate cancer | C19: AstraZeneca | D19: saruparib | E19: Phase III | F19: PARP1 inhibitor | G19: NCT06120491 | H19: EvoPAR-Prostate01 | I19: Metastatic castration-sensitive prostate cancer | J19: First-line metastatic setting; with physician-choice new hormonal agent | K19: 46660 | L19: =YEAR(K19) | M19: 1 | N19: 2 | O19: =IF(OR(L19="",M19=""),"",L19+M19) | P19: =IF(OR(L19="",N19=""),"",L19+N19) | Q19: =IF(O19="","Not estimated",TEXT(O19,"0")&"-"&TEXT(P19,"0")) | R19: Not launched - no historical sales | T19: https://clinicaltrials.gov/study/NCT06120491 | U19: https://www.astrazeneca.com/content/dam/az/Investor_Relations/annual-report-2025/pdf/AstraZeneca_Development_Pipeline_2025.pdf | V19: Representative Phase III prostate study.
A20: Solid-tumor oncology | B20: Prostate cancer | C20: Bristol Myers Squibb | D20: AR ligand-directed degrader | E20: Phase III | F20: Androgen receptor ligand-directed degrader | G20: NCT06764485 | H20: rechARge | I20: Metastatic castration-resistant prostate cancer | J20: After prior androgen-receptor pathway inhibitor; versus docetaxel or second ARPI | K20: 46642 | L20: =YEAR(K20) | M20: 1 | N20: 2 | O20: =IF(OR(L20="",M20=""),"",L20+M20) | P20: =IF(OR(L20="",N20=""),"",L20+N20) | Q20: =IF(O20="","Not estimated",TEXT(O20,"0")&"-"&TEXT(P20,"0")) | R20: Not launched - no historical sales | T20: https://clinicaltrials.gov/study/NCT06764485 | U20: https://annual-report.bms.com/assets/bms-ar/documents/2025/2025-bms-development-portfolio.pdf | V20: Program is also known as BMS-986365.

Sheet Commercial_Benchmarks
A1: Benchmark ID | B1: Disease area | C1: Overlap indication | D1: Product | E1: Company | F1: Year | G1: US revenue ($m) | H1: Emerging Markets revenue ($m) | I1: Europe revenue ($m) | J1: Established ROW revenue ($m) | K1: Worldwide revenue ($m) | L1: Sales basis | M1: Relevance | N1: Limitations | O1: Source URL
A2: NSCLC_TAGRISSO_2025 | B2: Solid-tumor oncology | C2: NSCLC | D2: Tagrisso | E2: AstraZeneca | F2: 2025 | G2: 3064 | H2: 1971 | I2: 1423 | J2: 796 | K2: =SUM(G2:J2) | L2: 2025 product sales; calculated from company-reported regions | M2: Commercial scale benchmark for a leading NSCLC franchise. | N2: Worldwide brand revenue across approved indications; not a forecast and not specific to the overlapping programs. | O2: https://www.sec.gov/Archives/edgar/data/901832/000110465926019130/azn-20251231x20f.htm
A3: NSCLC_OPDIVO_2025 | B3: Solid-tumor oncology | C3: NSCLC | D3: Opdivo | E3: Bristol Myers Squibb | F3: 2025 | K3: 10000 | L3: 2025 worldwide revenue | M3: Commercial scale benchmark for BMS immuno-oncology. | N3: All approved indications, not NSCLC-specific; used as a scale benchmark rather than a direct analogue. | O3: https://www.bms.com/investors/financial-reporting/key-facts.html
A4: MM_REVLIMID_2021 | B4: Hematology | C4: Multiple myeloma | D4: Revlimid | E4: Bristol Myers Squibb | F4: 2021 | K4: 12821 | L4: 2021 worldwide revenue; historical high-water benchmark | M4: Illustrates the historic commercial scale of the multiple-myeloma franchise. | N4: Brand revenue across indications; historical revenue does not predict future asset sales. | O4: https://news.bms.com/news/details/2022/Bristol-Myers-Squibb-Reports-Fourth-Quarter-and-Full-Year-Financial-Results-for-2021/default.aspx
A5: MM_POMALYST_2021 | B5: Hematology | C5: Multiple myeloma | D5: Pomalyst / Imnovid | E5: Bristol Myers Squibb | F5: 2021 | K5: 3332 | L5: 2021 worldwide revenue | M5: Additional multiple-myeloma commercial benchmark. | N5: Brand revenue across indications; not a forecast. | O5: https://news.bms.com/news/details/2022/Bristol-Myers-Squibb-Reports-Fourth-Quarter-and-Full-Year-Financial-Results-for-2021/default.aspx
A6: LYMPHOMA_BREYANZI_2025 | B6: Hematology | C6: B-cell lymphoma | D6: Breyanzi | E6: Bristol Myers Squibb | F6: 2025 | K6: 1400 | L6: 2025 worldwide revenue | M6: Commercial benchmark for an established B-cell lymphoma cell-therapy franchise. | N6: All approved indications; not a direct modality match for every program. | O6: https://www.bms.com/investors/financial-reporting/key-facts.html
A7: HF_CAMZYOS_2025 | B7: Cardiovascular | C7: Heart failure | D7: Camzyos | E7: Bristol Myers Squibb | F7: 2025 | K7: 1100 | L7: 2025 worldwide revenue | M7: Commercial benchmark for a cardiac-myosin franchise. | N7: Approved for obstructive hypertrophic cardiomyopathy, not HFpEF; included only as modality/franchise context. | O7: https://www.bms.com/investors/financial-reporting/key-facts.html

Sheet Website_Export
A1: Cell ID | B1: Disease area | C1: Plot label | D1: Factor | E1: Overlap count | F1: Directness | G1: AZ programs | H1: BMS programs | I1: Relationship | J1: Overlap units
A2: solid-tumor-oncology--shared-indications | B2: Solid-tumor oncology | C2: Solid tumors | D2: Shared indications | E2: 2 | F2: 3 | G2: 11 | H2: 7 | I2: Strong collision | J2: NSCLC; Prostate cancer
A3: solid-tumor-oncology--shared-modalities | B3: Solid-tumor oncology | C3: Solid tumors | D3: Shared modalities | E3: 4 | F3: 3 | G3: 11 | H3: 7 | I3: Strong collision | J3: Small-molecule targeted therapy; Bispecific / dual-target biologics; Antibody-drug conjugates; Radiopharmaceuticals
A4: solid-tumor-oncology--shared-target-mechanism | B4: Solid-tumor oncology | C4: Solid tumors | D4: Shared target / mechanism | E4: 2 | F4: 3 | G4: 11 | H4: 7 | I4: Strong collision | J4: PD-(L)1-based immuno-oncology; EGFR-directed therapeutics
A5: solid-tumor-oncology--stage-alignment | B5: Solid-tumor oncology | C5: Solid tumors | D5: Stage alignment | E5: 2 | F5: 3 | G5: 11 | H5: 7 | I5: Strong collision | J5: Phase II; Phase III / registration
A6: hematology--shared-indications | B6: Hematology | C6: Hematology | D6: Shared indications | E6: 2 | F6: 3 | G6: 4 | H6: 4 | I6: Strong collision | J6: Multiple myeloma; B-cell lymphoma
A7: hematology--shared-modalities | B7: Hematology | C7: Hematology | D7: Shared modalities | E7: 2 | F7: 3 | G7: 4 | H7: 4 | I7: Strong collision | J7: Cell therapy / CAR-T; Small-molecule targeted therapy
A8: hematology--shared-target-mechanism | B8: Hematology | C8: Hematology | D8: Shared target / mechanism | E8: 1 | F8: 3 | G8: 4 | H8: 4 | I8: Strong collision | J8: GPRC5D
A9: hematology--stage-alignment | B9: Hematology | C9: Hematology | D9: Stage alignment | E9: 1 | F9: 2 | G9: 4 | H9: 4 | I9: Strong collision | J9: Phase III / registration
A10: immunology-respiratory-and-fibrosis--shared-indications | B10: Immunology, respiratory & fibrosis | C10: Immunology / resp. / fibrosis | D10: Shared indications | E10: 0 | F10: 0 | G10: 7 | H10: 3 | I10: Platform adjacency
A11: immunology-respiratory-and-fibrosis--shared-modalities | B11: Immunology, respiratory & fibrosis | C11: Immunology / resp. / fibrosis | D11: Shared modalities | E11: 2 | F11: 1 | G11: 7 | H11: 3 | I11: Platform adjacency | J11: Small-molecule therapy; Monoclonal antibodies / biologics
A12: immunology-respiratory-and-fibrosis--shared-target-mechanism | B12: Immunology, respiratory & fibrosis | C12: Immunology / resp. / fibrosis | D12: Shared target / mechanism | E12: 0 | F12: 0 | G12: 7 | H12: 3 | I12: Platform adjacency
A13: immunology-respiratory-and-fibrosis--stage-alignment | B13: Immunology, respiratory & fibrosis | C13: Immunology / resp. / fibrosis | D13: Stage alignment | E13: 1 | F13: 1 | G13: 7 | H13: 3 | I13: Platform adjacency | J13: Phase III / registration
A14: cardiovascular--shared-indications | B14: Cardiovascular | C14: CV | D14: Shared indications | E14: 1 | F14: 2 | G14: 3 | H14: 2 | I14: Narrow adjacency | J14: Heart failure
A15: cardiovascular--shared-modalities | B15: Cardiovascular | C15: CV | D15: Shared modalities | E15: 1 | F15: 1 | G15: 3 | H15: 2 | I15: Narrow adjacency | J15: Small-molecule therapy
A16: cardiovascular--shared-target-mechanism | B16: Cardiovascular | C16: CV | D16: Shared target / mechanism | E16: 0 | F16: 0 | G16: 3 | H16: 2 | I16: Narrow adjacency
A17: cardiovascular--stage-alignment | B17: Cardiovascular | C17: CV | D17: Stage alignment | E17: 2 | F17: 2 | G17: 3 | H17: 2 | I17: Narrow adjacency | J17: Phase II; Phase III / registration
A18: rare-disease--shared-indications | B18: Rare disease | C18: Rare disease | D18: Shared indications | E18: 0 | F18: 0 | G18: 9 | H18: 0 | I18: AZ-led fit
A19: rare-disease--shared-modalities | B19: Rare disease | C19: Rare disease | D19: Shared modalities | E19: 0 | F19: 0 | G19: 9 | H19: 0 | I19: AZ-led fit
A20: rare-disease--shared-target-mechanism | B20: Rare disease | C20: Rare disease | D20: Shared target / mechanism | E20: 0 | F20: 0 | G20: 9 | H20: 0 | I20: AZ-led fit
A21: rare-disease--stage-alignment | B21: Rare disease | C21: Rare disease | D21: Stage alignment | E21: 0 | F21: 0 | G21: 9 | H21: 0 | I21: AZ-led fit
A22: renal-and-metabolic--shared-indications | B22: Renal & metabolic | C22: Renal / metabolic | D22: Shared indications | E22: 0 | F22: 0 | G22: 7 | H22: 0 | I22: AZ-led fit
A23: renal-and-metabolic--shared-modalities | B23: Renal & metabolic | C23: Renal / metabolic | D23: Shared modalities | E23: 0 | F23: 0 | G23: 7 | H23: 0 | I23: AZ-led fit
A24: renal-and-metabolic--shared-target-mechanism | B24: Renal & metabolic | C24: Renal / metabolic | D24: Shared target / mechanism | E24: 0 | F24: 0 | G24: 7 | H24: 0 | I24: AZ-led fit
A25: renal-and-metabolic--stage-alignment | B25: Renal & metabolic | C25: Renal / metabolic | D25: Stage alignment | E25: 0 | F25: 0 | G25: 7 | H25: 0 | I25: AZ-led fit
A26: infectious-disease--shared-indications | B26: Infectious disease | C26: Infectious disease | D26: Shared indications | E26: 0 | F26: 0 | G26: 3 | H26: 0 | I26: AZ-led fit
A27: infectious-disease--shared-modalities | B27: Infectious disease | C27: Infectious disease | D27: Shared modalities | E27: 0 | F27: 0 | G27: 3 | H27: 0 | I27: AZ-led fit
A28: infectious-disease--shared-target-mechanism | B28: Infectious disease | C28: Infectious disease | D28: Shared target / mechanism | E28: 0 | F28: 0 | G28: 3 | H28: 0 | I28: AZ-led fit
A29: infectious-disease--stage-alignment | B29: Infectious disease | C29: Infectious disease | D29: Stage alignment | E29: 0 | F29: 0 | G29: 3 | H29: 0 | I29: AZ-led fit
... A33: neuroscience--stage-alignment | B33: Neuroscience | C33: Neuroscience | D33: Stage alignment | E33: 0 | F33: 0 | G33: 0 | H33: 2 | I33: BMS-led fit

Sheet Brand_Context
A1: Brand and marketed-component mapping
A3: Program | B3: Company | C3: Brand / marketed component | D3: Relationship | E3: Marketed status | F3: Sales trend ID(s) | G3: Sales context | H3: Source URL
A4: camizestrant | B4: AstraZeneca | C4: Etcamah | D4: Approved brand for camizestrant (EU and Japan, 2026) | E4: Launched in EU and Japan after the February 2026 pipeline snapshot | F4: ETCAMAH | G4: Etcamah: $3M H1 2026 product revenue (new launch) | H4: https://www.rns-pdf.londonstockexchange.com/rns/9440N_1-2026-7-26.pdf
A5: baxdrostat | B5: AstraZeneca | C5: Baxfendy | D5: Approved brand for baxdrostat (US, 2026) | E5: Launched in the US after the February 2026 pipeline snapshot | F5: BAXFENDY | G5: Baxfendy: $3M H1 2026 product revenue (new launch) | H5: https://www.rns-pdf.londonstockexchange.com/rns/9440N_1-2026-7-26.pdf
A6: IPH5201 | B6: AstraZeneca | C6: Imfinzi | D6: Marketed combination backbone: Imfinzi (durvalumab) | E6: IPH5201 remains investigational; Imfinzi is marketed | F6: IMFINZI | G6: IPH5201 not launched; Imfinzi generated $6.1B in 2025 | H6: https://www.sec.gov/Archives/edgar/data/901832/000110465926019130/azn-20251231x20f.htm
A7: atigotatug + nivolumab | B7: Bristol Myers Squibb | C7: Opdivo / Opdivo Qvantig | D7: Marketed component: nivolumab | E7: Atigotatug combination remains investigational; nivolumab is marketed | F7: OPDIVO_FRANCHISE | G7: Combination not launched; Opdivo franchise generated $10.3B in 2025 | H7: https://www.sec.gov/Archives/edgar/data/14272/000001427226000004/bmy-20251231.htm
A8: nivolumab + relatlimab HD | B8: Bristol Myers Squibb | C8: Opdualag | D8: Related marketed fixed-dose combination: nivolumab + relatlimab | E8: Higher-dose / chemotherapy regimen remains investigational | F8: OPDUALAG | OPDIVO_FRANCHISE | G8: Investigational regimen not launched; Opdualag generated $1.2B in 2025 | H8: https://www.sec.gov/Archives/edgar/data/14272/000001427226000004/bmy-20251231.htm
A9: balcinrenone / dapagliflozin | B9: AstraZeneca | C9: Farxiga / Forxiga | D9: Marketed component: dapagliflozin | E9: Combination remains investigational; dapagliflozin is marketed | F9: FARXIGA | G9: Combination not launched; Farxiga/Forxiga generated $8.5B in 2025 | H9: https://www.sec.gov/Archives/edgar/data/901832/000110465926019130/azn-20251231x20f.htm
A10: zibotentan / dapagliflozin | B10: AstraZeneca | C10: Farxiga / Forxiga | D10: Marketed component: dapagliflozin | E10: Combination remains investigational; dapagliflozin is marketed | F10: FARXIGA | G10: Combination not launched; Farxiga/Forxiga generated $8.5B in 2025 | H10: https://www.sec.gov/Archives/edgar/data/901832/000110465926019130/azn-20251231x20f.htm

Sheet Sales_Assumptions
A1: Sales projection assumptions and patent / exclusivity context
A3: Trend ID | B3: Company | C3: Product | D3: Generic / active ingredient | E3: Relevance | F3: Projection basis | G3: Patent / exclusivity assumption | H3: Patent event(s) | I3: Source URL(s)
A4: ETCAMAH | B4: AstraZeneca | C4: Etcamah | D4: camizestrant | E4: Approved asset brand | F4: Illustrative new-launch uptake scenario from the $3M H1 2026 starting point; not company guidance or consensus. | G4: No product-specific loss-of-exclusivity date was disclosed in the 2025 Form 20-F; no cliff is applied through 2031. | I4: https://www.rns-pdf.londonstockexchange.com/rns/9440N_1-2026-7-26.pdf | https://www.sec.gov/Archives/edgar/data/901832/000110465926019130/azn-20251231x20f.htm
A5: BAXFENDY | B5: AstraZeneca | C5: Baxfendy | D5: baxdrostat | E5: Approved asset brand | F5: Illustrative new-launch uptake scenario from the $3M H1 2026 starting point; not company guidance or consensus. | G5: No product-specific loss-of-exclusivity date was disclosed in the 2025 Form 20-F; no cliff is applied through 2031. | I5: https://www.rns-pdf.londonstockexchange.com/rns/9440N_1-2026-7-26.pdf | https://www.sec.gov/Archives/edgar/data/901832/000110465926019130/azn-20251231x20f.htm
A6: TAGRISSO | B6: AstraZeneca | C6: Tagrisso | D6: osimertinib | E6: NSCLC commercial benchmark | F6: 2026E annualizes H1 2026. Thereafter an illustrative slowing-growth curve is followed by modeled erosion beginning at the earliest disclosed 2032 exclusivity date. | G6: Disclosed minimum exclusivity dates: US/China/EU 2032 and 2035; Japan 2034 and 2035. The scenario applies a cliff from 2032. | H6: 2032: Earliest disclosed LOE | 2035: Later patent layer | I6: https://www.sec.gov/Archives/edgar/data/901832/000110465926019130/azn-20251231x20f.htm | https://www.rns-pdf.londonstockexchange.com/rns/9440N_1-2026-7-26.pdf
A7: IMFINZI | B7: AstraZeneca | C7: Imfinzi | D7: durvalumab | E7: Marketed combination backbone | F7: 2026E annualizes H1 2026. The scenario assumes continued indication growth through 2029, then erosion as disclosed EU/China and US exclusivity dates arrive. | G7: Disclosed minimum exclusivity dates: China/EU 2030, US 2031 and Japan 2033. The scenario applies erosion from 2030. | H7: 2030: EU/China LOE | 2031: US LOE | I7: https://www.sec.gov/Archives/edgar/data/901832/000110465926019130/azn-20251231x20f.htm | https://www.rns-pdf.londonstockexchange.com/rns/9440N_1-2026-7-26.pdf
A8: FARXIGA | B8: AstraZeneca | C8: Farxiga / Forxiga | D8: dapagliflozin | E8: Marketed component in investigational combinations | F8: 2026E annualizes H1 2026. The decline curve explicitly reflects the US loss of exclusivity reported in 2026 and the disclosed 2027 EU date. | G8: US loss of exclusivity is already affecting 2026 results; the disclosed EU date is 2027, with additional regional patent layers extending later. | H8: 2026: US LOE / erosion begins | 2027: EU LOE | I8: https://www.sec.gov/Archives/edgar/data/901832/000110465926019130/azn-20251231x20f.htm | https://www.rns-pdf.londonstockexchange.com/rns/9440N_1-2026-7-26.pdf
A9: OPDIVO_FRANCHISE | B9: Bristol Myers Squibb | C9: Opdivo franchise | D9: nivolumab; includes Opdivo Qvantig from 2025 | E9: Marketed component / IO franchise | F9: 2026E annualizes H1 2026 Opdivo plus Opdivo Qvantig. The scenario then applies material erosion at the disclosed US, EU and Japan exclusivity dates. | G9: Disclosed minimum exclusivity dates for Opdivo: US 2028, EU 2030 and Japan 2031. The scenario applies sequential regional erosion. | H9: 2028: US LOE | 2030: EU LOE | 2031: Japan LOE | I9: https://www.sec.gov/Archives/edgar/data/14272/000001427226000004/bmy-20251231.htm | https://www.bms.com/assets/bms/us/en-us/pdf/investor-info/doc_financials/quarterly_reports/2026/ghBMY-Q2-2026-Earnings-Press-Release.pdf
A10: OPDUALAG | B10: Bristol Myers Squibb | C10: Opdualag | D10: nivolumab + relatlimab-rmbw | E10: Related marketed fixed-dose combination | F10: 2026E annualizes H1 2026. A base-case cliff begins around the currently listed 2033-2034 dates; pending patent-term/SPC extensions could delay the decline. | G10: Current table: US 2034 and EU 2033; pending extensions could move US to 2036 and parts of Europe to 2038. | H10: 2033: EU base date | 2034: US base date | 2036: Potential US extension | I10: https://www.sec.gov/Archives/edgar/data/14272/000001427226000004/bmy-20251231.htm | https://www.bms.com/assets/bms/us/en-us/pdf/investor-info/doc_financials/quarterly_reports/2026/ghBMY-Q2-2026-Earnings-Press-Release.pdf
A11: BREYANZI | B11: Bristol Myers Squibb | C11: Breyanzi | D11: lisocabtagene maraleucel | E11: B-cell lymphoma cell-therapy benchmark | F11: 2026E annualizes H1 2026. The scenario assumes continued uptake followed by erosion at the currently disclosed minimum exclusivity date. | G11: Current minimum exclusivity is 2033 across the US, EU and Japan; a US patent-term-restoration application could extend to 2034. | H11: 2033: Current minimum LOE | 2034: Potential US extension | I11: https://www.sec.gov/Archives/edgar/data/14272/000001427226000004/bmy-20251231.htm | https://www.bms.com/assets/bms/us/en-us/pdf/investor-info/doc_financials/quarterly_reports/2026/ghBMY-Q2-2026-Earnings-Press-Release.pdf
A12: CAMZYOS | B12: Bristol Myers Squibb | C12: Camzyos | D12: mavacamten | E12: Cardiac-myosin commercial benchmark | F12: 2026E annualizes H1 2026. The scenario uses a maturing growth curve and applies erosion at the disclosed US patent expiry. | G12: US patent expiry is 2036; granted/pending extensions indicate 2038 in major European markets and 2039 in Japan. | H12: 2036: US LOE | I12: https://www.sec.gov/Archives/edgar/data/14272/000001427226000004/bmy-20251231.htm | https://www.bms.com/assets/bms/us/en-us/pdf/investor-info/doc_financials/quarterly_reports/2026/ghBMY-Q2-2026-Earnings-Press-Release.pdf
A13: REVLIMID | B13: Bristol Myers Squibb | C13: Revlimid | D13: lenalidomide | E13: Multiple-myeloma franchise benchmark | F13: 2026E annualizes H1 2026. The decline reflects unrestricted US generic entry from 31 January 2026 and existing generic competition outside the US. | G13: US volume-limited generic licenses became unrestricted on 31 January 2026; generics are already present in Europe and Japan. | H13: 2026: Unrestricted US generics | I13: https://www.sec.gov/Archives/edgar/data/14272/000001427226000004/bmy-20251231.htm | https://www.bms.com/assets/bms/us/en-us/pdf/investor-info/doc_financials/quarterly_reports/2026/ghBMY-Q2-2026-Earnings-Press-Release.pdf
A14: POMALYST | B14: Bristol Myers Squibb | C14: Pomalyst / Imnovid | D14: pomalidomide | E14: Multiple-myeloma franchise benchmark | F14: 2026E annualizes H1 2026. The decline reflects expected US generic entry in Q1 2026 and existing European generic competition. | G14: Generic entry was expected in the US in Q1 2026; generics are already present in Europe and the minimum Japanese exclusivity date is 2026. | H14: 2026: US/Japan LOE | I14: https://www.sec.gov/Archives/edgar/data/14272/000001427226000004/bmy-20251231.htm | https://www.bms.com/assets/bms/us/en-us/pdf/investor-info/doc_financials/quarterly_reports/2026/ghBMY-Q2-2026-Earnings-Press-Release.pdf

Sheet Sales_Trends
A1: Reported sales and patent-adjusted analyst scenarios (USD millions)
A2: Blue font = editable forecast assumption; green font = reported / sourced input; black = formula-derived. Projections are analyst scenarios, not company guidance or consensus.
A4: Trend ID | B4: Company | C4: Product | D4: Generic / active | E4: Brand context | F4: Period | G4: Year | H4: Status | I4: Reported / input revenue ($m) | J4: Growth / multiplier assumption | K4: Calculated revenue ($m) | L4: Patent / LOE event | M4: Projection basis | N4: Source URL(s) | O4: Website display value ($m)
A5: ETCAMAH | B5: AstraZeneca | C5: Etcamah | D5: camizestrant | E5: Approved asset brand | F5: H1 26 | G5: 2026 | H5: reported-partial | I5: 3 | K5: =I5 | M5: Illustrative new-launch uptake scenario from the $3M H1 2026 starting point; not company guidance or consensus. | N5: https://www.rns-pdf.londonstockexchange.com/rns/9440N_1-2026-7-26.pdf | https://www.sec.gov/Archives/edgar/data/901832/000110465926019130/azn-20251231x20f.htm | O5: 3
A6: ETCAMAH | B6: AstraZeneca | C6: Etcamah | D6: camizestrant | E6: Approved asset brand | F6: 2026E | G6: 2026.5 | H6: projected | J6: 4 | K6: =K5*(1+J6) | M6: Illustrative new-launch uptake scenario from the $3M H1 2026 starting point; not company guidance or consensus. | N6: https://www.rns-pdf.londonstockexchange.com/rns/9440N_1-2026-7-26.pdf | https://www.sec.gov/Archives/edgar/data/901832/000110465926019130/azn-20251231x20f.htm | O6: 15
A7: ETCAMAH | B7: AstraZeneca | C7: Etcamah | D7: camizestrant | E7: Approved asset brand | F7: 2027 | G7: 2027 | H7: projected | J7: 7 | K7: =K6*(1+J7) | M7: Illustrative new-launch uptake scenario from the $3M H1 2026 starting point; not company guidance or consensus. | N7: https://www.rns-pdf.londonstockexchange.com/rns/9440N_1-2026-7-26.pdf | https://www.sec.gov/Archives/edgar/data/901832/000110465926019130/azn-20251231x20f.htm | O7: 120
A8: ETCAMAH | B8: AstraZeneca | C8: Etcamah | D8: camizestrant | E8: Approved asset brand | F8: 2028 | G8: 2028 | H8: projected | J8: 2 | K8: =K7*(1+J8) | M8: Illustrative new-launch uptake scenario from the $3M H1 2026 starting point; not company guidance or consensus. | N8: https://www.rns-pdf.londonstockexchange.com/rns/9440N_1-2026-7-26.pdf | https://www.sec.gov/Archives/edgar/data/901832/000110465926019130/azn-20251231x20f.htm | O8: 360
A9: ETCAMAH | B9: AstraZeneca | C9: Etcamah | D9: camizestrant | E9: Approved asset brand | F9: 2029 | G9: 2029 | H9: projected | J9: 0.94444444 | K9: =K8*(1+J9) | M9: Illustrative new-launch uptake scenario from the $3M H1 2026 starting point; not company guidance or consensus. | N9: https://www.rns-pdf.londonstockexchange.com/rns/9440N_1-2026-7-26.pdf | https://www.sec.gov/Archives/edgar/data/901832/000110465926019130/azn-20251231x20f.htm | O9: 700
A10: ETCAMAH | B10: AstraZeneca | C10: Etcamah | D10: camizestrant | E10: Approved asset brand | F10: 2030 | G10: 2030 | H10: projected | J10: 0.42857143 | K10: =K9*(1+J10) | M10: Illustrative new-launch uptake scenario from the $3M H1 2026 starting point; not company guidance or consensus. | N10: https://www.rns-pdf.londonstockexchange.com/rns/9440N_1-2026-7-26.pdf | https://www.sec.gov/Archives/edgar/data/901832/000110465926019130/azn-20251231x20f.htm | O10: 1000
A11: ETCAMAH | B11: AstraZeneca | C11: Etcamah | D11: camizestrant | E11: Approved asset brand | F11: 2031 | G11: 2031 | H11: projected | J11: 0.25 | K11: =K10*(1+J11) | M11: Illustrative new-launch uptake scenario from the $3M H1 2026 starting point; not company guidance or consensus. | N11: https://www.rns-pdf.londonstockexchange.com/rns/9440N_1-2026-7-26.pdf | https://www.sec.gov/Archives/edgar/data/901832/000110465926019130/azn-20251231x20f.htm | O11: 1250
A13: BAXFENDY | B13: AstraZeneca | C13: Baxfendy | D13: baxdrostat | E13: Approved asset brand | F13: H1 26 | G13: 2026 | H13: reported-partial | I13: 3 | K13: =I13 | M13: Illustrative new-launch uptake scenario from the $3M H1 2026 starting point; not company guidance or consensus. | N13: https://www.rns-pdf.londonstockexchange.com/rns/9440N_1-2026-7-26.pdf | https://www.sec.gov/Archives/edgar/data/901832/000110465926019130/azn-20251231x20f.htm | O13: 3
A14: BAXFENDY | B14: AstraZeneca | C14: Baxfendy | D14: baxdrostat | E14: Approved asset brand | F14: 2026E | G14: 2026.5 | H14: projected | J14: 4 | K14: =K13*(1+J14) | M14: Illustrative new-launch uptake scenario from the $3M H1 2026 starting point; not company guidance or consensus. | N14: https://www.rns-pdf.londonstockexchange.com/rns/9440N_1-2026-7-26.pdf | https://www.sec.gov/Archives/edgar/data/901832/000110465926019130/azn-20251231x20f.htm | O14: 15
A15: BAXFENDY | B15: AstraZeneca | C15: Baxfendy | D15: baxdrostat | E15: Approved asset brand | F15: 2027 | G15: 2027 | H15: projected | J15: 9 | K15: =K14*(1+J15) | M15: Illustrative new-launch uptake scenario from the $3M H1 2026 starting point; not company guidance or consensus. | N15: https://www.rns-pdf.londonstockexchange.com/rns/9440N_1-2026-7-26.pdf | https://www.sec.gov/Archives/edgar/data/901832/000110465926019130/azn-20251231x20f.htm | O15: 150
A16: BAXFENDY | B16: AstraZeneca | C16: Baxfendy | D16: baxdrostat | E16: Approved asset brand | F16: 2028 | G16: 2028 | H16: projected | J16: 2 | K16: =K15*(1+J16) | M16: Illustrative new-launch uptake scenario from the $3M H1 2026 starting point; not company guidance or consensus. | N16: https://www.rns-pdf.londonstockexchange.com/rns/9440N_1-2026-7-26.pdf | https://www.sec.gov/Archives/edgar/data/901832/000110465926019130/azn-20251231x20f.htm | O16: 450
A17: BAXFENDY | B17: AstraZeneca | C17: Baxfendy | D17: baxdrostat | E17: Approved asset brand | F17: 2029 | G17: 2029 | H17: projected | J17: 0.88888889 | K17: =K16*(1+J17) | M17: Illustrative new-launch uptake scenario from the $3M H1 2026 starting point; not company guidance or consensus. | N17: https://www.rns-pdf.londonstockexchange.com/rns/9440N_1-2026-7-26.pdf | https://www.sec.gov/Archives/edgar/data/901832/000110465926019130/azn-20251231x20f.htm | O17: 850
A18: BAXFENDY | B18: AstraZeneca | C18: Baxfendy | D18: baxdrostat | E18: Approved asset brand | F18: 2030 | G18: 2030 | H18: projected | J18: 0.47058824 | K18: =K17*(1+J18) | M18: Illustrative new-launch uptake scenario from the $3M H1 2026 starting point; not company guidance or consensus. | N18: https://www.rns-pdf.londonstockexchange.com/rns/9440N_1-2026-7-26.pdf | https://www.sec.gov/Archives/edgar/data/901832/000110465926019130/azn-20251231x20f.htm | O18: 1250
A19: BAXFENDY | B19: AstraZeneca | C19: Baxfendy | D19: baxdrostat | E19: Approved asset brand | F19: 2031 | G19: 2031 | H19: projected | J19: 0.24 | K19: =K18*(1+J19) | M19: Illustrative new-launch uptake scenario from the $3M H1 2026 starting point; not company guidance or consensus. | N19: https://www.rns-pdf.londonstockexchange.com/rns/9440N_1-2026-7-26.pdf | https://www.sec.gov/Archives/edgar/data/901832/000110465926019130/azn-20251231x20f.htm | O19: 1550
A21: TAGRISSO | B21: AstraZeneca | C21: Tagrisso | D21: osimertinib | E21: NSCLC commercial benchmark | F21: 2023 | G21: 2023 | H21: reported | I21: 5799 | K21: =I21 | M21: 2026E annualizes H1 2026. Thereafter an illustrative slowing-growth curve is followed by modeled erosion beginning at the earliest disclosed 2032 exclusivity date. | N21: https://www.sec.gov/Archives/edgar/data/901832/000110465926019130/azn-20251231x20f.htm | https://www.rns-pdf.londonstockexchange.com/rns/9440N_1-2026-7-26.pdf | O21: 5799
A22: TAGRISSO | B22: AstraZeneca | C22: Tagrisso | D22: osimertinib | E22: NSCLC commercial benchmark | F22: 2024 | G22: 2024 | H22: reported | I22: 6580 | K22: =I22 | M22: 2026E annualizes H1 2026. Thereafter an illustrative slowing-growth curve is followed by modeled erosion beginning at the earliest disclosed 2032 exclusivity date. | N22: https://www.sec.gov/Archives/edgar/data/901832/000110465926019130/azn-20251231x20f.htm | https://www.rns-pdf.londonstockexchange.com/rns/9440N_1-2026-7-26.pdf | O22: 6580
A23: TAGRISSO | B23: AstraZeneca | C23: Tagrisso | D23: osimertinib | E23: NSCLC commercial benchmark | F23: 2025 | G23: 2025 | H23: reported | I23: 7254 | K23: =I23 | M23: 2026E annualizes H1 2026. Thereafter an illustrative slowing-growth curve is followed by modeled erosion beginning at the earliest disclosed 2032 exclusivity date. | N23: https://www.sec.gov/Archives/edgar/data/901832/000110465926019130/azn-20251231x20f.htm | https://www.rns-pdf.londonstockexchange.com/rns/9440N_1-2026-7-26.pdf | O23: 7254
A24: TAGRISSO | B24: AstraZeneca | C24: Tagrisso | D24: osimertinib | E24: NSCLC commercial benchmark | F24: 2026E | G24: 2026 | H24: projected | J24: 0.040805073 | K24: =K23*(1+J24) | M24: 2026E annualizes H1 2026. Thereafter an illustrative slowing-growth curve is followed by modeled erosion beginning at the earliest disclosed 2032 exclusivity date. | N24: https://www.sec.gov/Archives/edgar/data/901832/000110465926019130/azn-20251231x20f.htm | https://www.rns-pdf.londonstockexchange.com/rns/9440N_1-2026-7-26.pdf | O24: 7550
A25: TAGRISSO | B25: AstraZeneca | C25: Tagrisso | D25: osimertinib | E25: NSCLC commercial benchmark | F25: 2027 | G25: 2027 | H25: projected | J25: 0.070066225 | K25: =K24*(1+J25) | M25: 2026E annualizes H1 2026. Thereafter an illustrative slowing-growth curve is followed by modeled erosion beginning at the earliest disclosed 2032 exclusivity date. | N25: https://www.sec.gov/Archives/edgar/data/901832/000110465926019130/azn-20251231x20f.htm | https://www.rns-pdf.londonstockexchange.com/rns/9440N_1-2026-7-26.pdf | O25: 8079
A26: TAGRISSO | B26: AstraZeneca | C26: Tagrisso | D26: osimertinib | E26: NSCLC commercial benchmark | F26: 2028 | G26: 2028 | H26: projected | J26: 0.060032182 | K26: =K25*(1+J26) | M26: 2026E annualizes H1 2026. Thereafter an illustrative slowing-growth curve is followed by modeled erosion beginning at the earliest disclosed 2032 exclusivity date. | N26: https://www.sec.gov/Archives/edgar/data/901832/000110465926019130/azn-20251231x20f.htm | https://www.rns-pdf.londonstockexchange.com/rns/9440N_1-2026-7-26.pdf | O26: 8564
A27: TAGRISSO | B27: AstraZeneca | C27: Tagrisso | D27: osimertinib | E27: NSCLC commercial benchmark | F27: 2029 | G27: 2029 | H27: projected | J27: 0.049976646 | K27: =K26*(1+J27) | M27: 2026E annualizes H1 2026. Thereafter an illustrative slowing-growth curve is followed by modeled erosion beginning at the earliest disclosed 2032 exclusivity date. | N27: https://www.sec.gov/Archives/edgar/data/901832/000110465926019130/azn-20251231x20f.htm | https://www.rns-pdf.londonstockexchange.com/rns/9440N_1-2026-7-26.pdf | O27: 8992
A28: TAGRISSO | B28: AstraZeneca | C28: Tagrisso | D28: osimertinib | E28: NSCLC commercial benchmark | F28: 2030 | G28: 2030 | H28: projected | J28: 0.040035587 | K28: =K27*(1+J28) | M28: 2026E annualizes H1 2026. Thereafter an illustrative slowing-growth curve is followed by modeled erosion beginning at the earliest disclosed 2032 exclusivity date. | N28: https://www.sec.gov/Archives/edgar/data/901832/000110465926019130/azn-20251231x20f.htm | https://www.rns-pdf.londonstockexchange.com/rns/9440N_1-2026-7-26.pdf | O28: 9352
A29: TAGRISSO | B29: AstraZeneca | C29: Tagrisso | D29: osimertinib | E29: NSCLC commercial benchmark | F29: 2031 | G29: 2031 | H29: projected | J29: 0.019995723 | K29: =K28*(1+J29) | M29: 2026E annualizes H1 2026. Thereafter an illustrative slowing-growth curve is followed by modeled erosion beginning at the earliest disclosed 2032 exclusivity date. | N29: https://www.sec.gov/Archives/edgar/data/901832/000110465926019130/azn-20251231x20f.htm | https://www.rns-pdf.londonstockexchange.com/rns/9440N_1-2026-7-26.pdf | O29: 9539
A30: TAGRISSO | B30: AstraZeneca | C30: Tagrisso | D30: osimertinib | E30: NSCLC commercial benchmark | F30: 2032 | G30: 2032 | H30: projected | J30: -0.20002097 | K30: =K29*(1+J30) | L30: Earliest disclosed LOE | M30: 2026E annualizes H1 2026. Thereafter an illustrative slowing-growth curve is followed by modeled erosion beginning at the earliest disclosed 2032 exclusivity date. | N30: https://www.sec.gov/Archives/edgar/data/901832/000110465926019130/azn-20251231x20f.htm | https://www.rns-pdf.londonstockexchange.com/rns/9440N_1-2026-7-26.pdf | O30: 7631
A31: TAGRISSO | B31: AstraZeneca | C31: Tagrisso | D31: osimertinib | E31: NSCLC commercial benchmark | F31: 2033 | G31: 2033 | H31: projected | J31: -0.39994758 | K31: =K30*(1+J31) | M31: 2026E annualizes H1 2026. Thereafter an illustrative slowing-growth curve is followed by modeled erosion beginning at the earliest disclosed 2032 exclusivity date. | N31: https://www.sec.gov/Archives/edgar/data/901832/000110465926019130/azn-20251231x20f.htm | https://www.rns-pdf.londonstockexchange.com/rns/9440N_1-2026-7-26.pdf | O31: 4579
A33: IMFINZI | B33: AstraZeneca | C33: Imfinzi | D33: durvalumab | E33: Marketed combination backbone | F33: 2023 | G33: 2023 | H33: reported | I33: 4019 | K33: =I33 | M33: 2026E annualizes H1 2026. The scenario assumes continued indication growth through 2029, then erosion as disclosed EU/China and US exclusivity dates arrive. | N33: https://www.sec.gov/Archives/edgar/data/901832/000110465926019130/azn-20251231x20f.htm | https://www.rns-pdf.londonstockexchange.com/rns/9440N_1-2026-7-26.pdf | O33: 4019
A34: IMFINZI | B34: AstraZeneca | C34: Imfinzi | D34: durvalumab | E34: Marketed combination backbone | F34: 2024 | G34: 2024 | H34: reported | I34: 4717 | K34: =I34 | M34: 2026E annualizes H1 2026. The scenario assumes continued indication growth through 2029, then erosion as disclosed EU/China and US exclusivity dates arrive. | N34: https://www.sec.gov/Archives/edgar/data/901832/000110465926019130/azn-20251231x20f.htm | https://www.rns-pdf.londonstockexchange.com/rns/9440N_1-2026-7-26.pdf | O34: 4717
A35: IMFINZI | B35: AstraZeneca | C35: Imfinzi | D35: durvalumab | E35: Marketed combination backbone | F35: 2025 | G35: 2025 | H35: reported | I35: 6063 | K35: =I35 | M35: 2026E annualizes H1 2026. The scenario assumes continued indication growth through 2029, then erosion as disclosed EU/China and US exclusivity dates arrive. | N35: https://www.sec.gov/Archives/edgar/data/901832/000110465926019130/azn-20251231x20f.htm | https://www.rns-pdf.londonstockexchange.com/rns/9440N_1-2026-7-26.pdf | O35: 6063
A36: IMFINZI | B36: AstraZeneca | C36: Imfinzi | D36: durvalumab | E36: Marketed combination backbone | F36: 2026E | G36: 2026 | H36: projected | J36: 0.1703777 | K36: =K35*(1+J36) | M36: 2026E annualizes H1 2026. The scenario assumes continued indication growth through 2029, then erosion as disclosed EU/China and US exclusivity dates arrive. | N36: https://www.sec.gov/Archives/edgar/data/901832/000110465926019130/azn-20251231x20f.htm | https://www.rns-pdf.londonstockexchange.com/rns/9440N_1-2026-7-26.pdf | O36: 7096
A37: IMFINZI | B37: AstraZeneca | C37: Imfinzi | D37: durvalumab | E37: Marketed combination backbone | F37: 2027 | G37: 2027 | H37: projected | J37: 0.14994363 | K37: =K36*(1+J37) | M37: 2026E annualizes H1 2026. The scenario assumes continued indication growth through 2029, then erosion as disclosed EU/China and US exclusivity dates arrive. | N37: https://www.sec.gov/Archives/edgar/data/901832/000110465926019130/azn-20251231x20f.htm | https://www.rns-pdf.londonstockexchange.com/rns/9440N_1-2026-7-26.pdf | O37: 8160
A38: IMFINZI | B38: AstraZeneca | C38: Imfinzi | D38: durvalumab | E38: Marketed combination backbone | F38: 2028 | G38: 2028 | H38: projected | J38: 0.125 | K38: =K37*(1+J38) | M38: 2026E annualizes H1 2026. The scenario assumes continued indication growth through 2029, then erosion as disclosed EU/China and US exclusivity dates arrive. | N38: https://www.sec.gov/Archives/edgar/data/901832/000110465926019130/azn-20251231x20f.htm | https://www.rns-pdf.londonstockexchange.com/rns/9440N_1-2026-7-26.pdf | O38: 9180
A39: IMFINZI | B39: AstraZeneca | C39: Imfinzi | D39: durvalumab | E39: Marketed combination backbone | F39: 2029 | G39: 2029 | H39: projected | J39: 0.1 | K39: =K38*(1+J39) | M39: 2026E annualizes H1 2026. The scenario assumes continued indication growth through 2029, then erosion as disclosed EU/China and US exclusivity dates arrive. | N39: https://www.sec.gov/Archives/edgar/data/901832/000110465926019130/azn-20251231x20f.htm | https://www.rns-pdf.londonstockexchange.com/rns/9440N_1-2026-7-26.pdf | O39: 10098
A40: IMFINZI | B40: AstraZeneca | C40: Imfinzi | D40: durvalumab | E40: Marketed combination backbone | F40: 2030 | G40: 2030 | H40: projected | J40: -0.10001981 | K40: =K39*(1+J40) | L40: EU/China LOE | M40: 2026E annualizes H1 2026. The scenario assumes continued indication growth through 2029, then erosion as disclosed EU/China and US exclusivity dates arrive. | N40: https://www.sec.gov/Archives/edgar/data/901832/000110465926019130/azn-20251231x20f.htm | https://www.rns-pdf.londonstockexchange.com/rns/9440N_1-2026-7-26.pdf | O40: 9088
A41: IMFINZI | B41: AstraZeneca | C41: Imfinzi | D41: durvalumab | E41: Marketed combination backbone | F41: 2031 | G41: 2031 | H41: projected | J41: -0.25 | K41: =K40*(1+J41) | L41: US LOE | M41: 2026E annualizes H1 2026. The scenario assumes continued indication growth through 2029, then erosion as disclosed EU/China and US exclusivity dates arrive. | N41: https://www.sec.gov/Archives/edgar/data/901832/000110465926019130/azn-20251231x20f.htm | https://www.rns-pdf.londonstockexchange.com/rns/9440N_1-2026-7-26.pdf | O41: 6816
A42: IMFINZI | B42: AstraZeneca | C42: Imfinzi | D42: durvalumab | E42: Marketed combination backbone | F42: 2032 | G42: 2032 | H42: projected | J42: -0.19997066 | K42: =K41*(1+J42) | M42: 2026E annualizes H1 2026. The scenario assumes continued indication growth through 2029, then erosion as disclosed EU/China and US exclusivity dates arrive. | N42: https://www.sec.gov/Archives/edgar/data/901832/000110465926019130/azn-20251231x20f.htm | https://www.rns-pdf.londonstockexchange.com/rns/9440N_1-2026-7-26.pdf | O42: 5453
A44: FARXIGA | B44: AstraZeneca | C44: Farxiga / Forxiga | D44: dapagliflozin | E44: Marketed component in investigational combinations | F44: 2023 | G44: 2023 | H44: reported | I44: 5963 | K44: =I44 | M44: 2026E annualizes H1 2026. The decline curve explicitly reflects the US loss of exclusivity reported in 2026 and the disclosed 2027 EU date. | N44: https://www.sec.gov/Archives/edgar/data/901832/000110465926019130/azn-20251231x20f.htm | https://www.rns-pdf.londonstockexchange.com/rns/9440N_1-2026-7-26.pdf | O44: 5963
A45: FARXIGA | B45: AstraZeneca | C45: Farxiga / Forxiga | D45: dapagliflozin | E45: Marketed component in investigational combinations | F45: 2024 | G45: 2024 | H45: reported | I45: 7656 | K45: =I45 | M45: 2026E annualizes H1 2026. The decline curve explicitly reflects the US loss of exclusivity reported in 2026 and the disclosed 2027 EU date. | N45: https://www.sec.gov/Archives/edgar/data/901832/000110465926019130/azn-20251231x20f.htm | https://www.rns-pdf.londonstockexchange.com/rns/9440N_1-2026-7-26.pdf | O45: 7656
A46: FARXIGA | B46: AstraZeneca | C46: Farxiga / Forxiga | D46: dapagliflozin | E46: Marketed component in investigational combinations | F46: 2025 | G46: 2025 | H46: reported | I46: 8492 | K46: =I46 | M46: 2026E annualizes H1 2026. The decline curve explicitly reflects the US loss of exclusivity reported in 2026 and the disclosed 2027 EU date. | N46: https://www.sec.gov/Archives/edgar/data/901832/000110465926019130/azn-20251231x20f.htm | https://www.rns-pdf.londonstockexchange.com/rns/9440N_1-2026-7-26.pdf | O46: 8492
A47: FARXIGA | B47: AstraZeneca | C47: Farxiga / Forxiga | D47: dapagliflozin | E47: Marketed component in investigational combinations | F47: 2026E | G47: 2026 | H47: projected | J47: -0.058407913 | K47: =K46*(1+J47) | L47: US LOE / erosion begins | M47: 2026E annualizes H1 2026. The decline curve explicitly reflects the US loss of exclusivity reported in 2026 and the disclosed 2027 EU date. | N47: https://www.sec.gov/Archives/edgar/data/901832/000110465926019130/azn-20251231x20f.htm | https://www.rns-pdf.londonstockexchange.com/rns/9440N_1-2026-7-26.pdf | O47: 7996
A48: FARXIGA | B48: AstraZeneca | C48: Farxiga / Forxiga | D48: dapagliflozin | E48: Marketed component in investigational combinations | F48: 2027 | G48: 2027 | H48: projected | J48: -0.10005003 | K48: =K47*(1+J48) | L48: EU LOE | M48: 2026E annualizes H1 2026. The decline curve explicitly reflects the US loss of exclusivity reported in 2026 and the disclosed 2027 EU date. | N48: https://www.sec.gov/Archives/edgar/data/901832/000110465926019130/azn-20251231x20f.htm | https://www.rns-pdf.londonstockexchange.com/rns/9440N_1-2026-7-26.pdf | O48: 7196
A49: FARXIGA | B49: AstraZeneca | C49: Farxiga / Forxiga | D49: dapagliflozin | E49: Marketed component in investigational combinations | F49: 2028 | G49: 2028 | H49: projected | J49: -0.10005559 | K49: =K48*(1+J49) | M49: 2026E annualizes H1 2026. The decline curve explicitly reflects the US loss of exclusivity reported in 2026 and the disclosed 2027 EU date. | N49: https://www.sec.gov/Archives/edgar/data/901832/000110465926019130/azn-20251231x20f.htm | https://www.rns-pdf.londonstockexchange.com/rns/9440N_1-2026-7-26.pdf | O49: 6476
A50: FARXIGA | B50: AstraZeneca | C50: Farxiga / Forxiga | D50: dapagliflozin | E50: Marketed component in investigational combinations | F50: 2029 | G50: 2029 | H50: projected | J50: -0.090024707 | K50: =K49*(1+J50) | M50: 2026E annualizes H1 2026. The decline curve explicitly reflects the US loss of exclusivity reported in 2026 and the disclosed 2027 EU date. | N50: https://www.sec.gov/Archives/edgar/data/901832/000110465926019130/azn-20251231x20f.htm | https://www.rns-pdf.londonstockexchange.com/rns/9440N_1-2026-7-26.pdf | O50: 5893
A51: FARXIGA | B51: AstraZeneca | C51: Farxiga / Forxiga | D51: dapagliflozin | E51: Marketed component in investigational combinations | F51: 2030 | G51: 2030 | H51: projected | J51: -0.069913457 | K51: =K50*(1+J51) | M51: 2026E annualizes H1 2026. The decline curve explicitly reflects the US loss of exclusivity reported in 2026 and the disclosed 2027 EU date. | N51: https://www.sec.gov/Archives/edgar/data/901832/000110465926019130/azn-20251231x20f.htm | https://www.rns-pdf.londonstockexchange.com/rns/9440N_1-2026-7-26.pdf | O51: 5481
A52: FARXIGA | B52: AstraZeneca | C52: Farxiga / Forxiga | D52: dapagliflozin | E52: Marketed component in investigational combinations | F52: 2031 | G52: 2031 | H52: projected | J52: -0.049990878 | K52: =K51*(1+J52) | M52: 2026E annualizes H1 2026. The decline curve explicitly reflects the US loss of exclusivity reported in 2026 and the disclosed 2027 EU date. | N52: https://www.sec.gov/Archives/edgar/data/901832/000110465926019130/azn-20251231x20f.htm | https://www.rns-pdf.londonstockexchange.com/rns/9440N_1-2026-7-26.pdf | O52: 5207
A54: OPDIVO_FRANCHISE | B54: Bristol Myers Squibb | C54: Opdivo franchise | D54: nivolumab; includes Opdivo Qvantig from 2025 | E54: Marketed component / IO franchise | F54: 2023 | G54: 2023 | H54: reported | I54: 9009 | K54: =I54 | M54: 2026E annualizes H1 2026 Opdivo plus Opdivo Qvantig. The scenario then applies material erosion at the disclosed US, EU and Japan exclusivity dates. | N54: https://www.sec.gov/Archives/edgar/data/14272/000001427226000004/bmy-20251231.htm | https://www.bms.com/assets/bms/us/en-us/pdf/investor-info/doc_financials/quarterly_reports/2026/ghBMY-Q2-2026-Earnings-Press-Release.pdf | O54: 9009
A55: OPDIVO_FRANCHISE | B55: Bristol Myers Squibb | C55: Opdivo franchise | D55: nivolumab; includes Opdivo Qvantig from 2025 | E55: Marketed component / IO franchise | F55: 2024 | G55: 2024 | H55: reported | I55: 9304 | K55: =I55 | M55: 2026E annualizes H1 2026 Opdivo plus Opdivo Qvantig. The scenario then applies material erosion at the disclosed US, EU and Japan exclusivity dates. | N55: https://www.sec.gov/Archives/edgar/data/14272/000001427226000004/bmy-20251231.htm | https://www.bms.com/assets/bms/us/en-us/pdf/investor-info/doc_financials/quarterly_reports/2026/ghBMY-Q2-2026-Earnings-Press-Release.pdf | O55: 9304
A56: OPDIVO_FRANCHISE | B56: Bristol Myers Squibb | C56: Opdivo franchise | D56: nivolumab; includes Opdivo Qvantig from 2025 | E56: Marketed component / IO franchise | F56: 2025 | G56: 2025 | H56: reported | I56: 10287 | K56: =I56 | M56: 2026E annualizes H1 2026 Opdivo plus Opdivo Qvantig. The scenario then applies material erosion at the disclosed US, EU and Japan exclusivity dates. | N56: https://www.sec.gov/Archives/edgar/data/14272/000001427226000004/bmy-20251231.htm | https://www.bms.com/assets/bms/us/en-us/pdf/investor-info/doc_financials/quarterly_reports/2026/ghBMY-Q2-2026-Earnings-Press-Release.pdf | O56: 10287
A57: OPDIVO_FRANCHISE | B57: Bristol Myers Squibb | C57: Opdivo franchise | D57: nivolumab; includes Opdivo Qvantig from 2025 | E57: Marketed component / IO franchise | F57: 2026E | G57: 2026 | H57: projected | J57: -0.017206183 | K57: =K56*(1+J57) | M57: 2026E annualizes H1 2026 Opdivo plus Opdivo Qvantig. The scenario then applies material erosion at the disclosed US, EU and Japan exclusivity dates. | N57: https://www.sec.gov/Archives/edgar/data/14272/000001427226000004/bmy-20251231.htm | https://www.bms.com/assets/bms/us/en-us/pdf/investor-info/doc_financials/quarterly_reports/2026/ghBMY-Q2-2026-Earnings-Press-Release.pdf | O57: 10110
A58: OPDIVO_FRANCHISE | B58: Bristol Myers Squibb | C58: Opdivo franchise | D58: nivolumab; includes Opdivo Qvantig from 2025 | E58: Marketed component / IO franchise | F58: 2027 | G58: 2027 | H58: projected | J58: -0.019980218 | K58: =K57*(1+J58) | M58: 2026E annualizes H1 2026 Opdivo plus Opdivo Qvantig. The scenario then applies material erosion at the disclosed US, EU and Japan exclusivity dates. | N58: https://www.sec.gov/Archives/edgar/data/14272/000001427226000004/bmy-20251231.htm | https://www.bms.com/assets/bms/us/en-us/pdf/investor-info/doc_financials/quarterly_reports/2026/ghBMY-Q2-2026-Earnings-Press-Release.pdf | O58: 9908
A59: OPDIVO_FRANCHISE | B59: Bristol Myers Squibb | C59: Opdivo franchise | D59: nivolumab; includes Opdivo Qvantig from 2025 | E59: Marketed component / IO franchise | F59: 2028 | G59: 2028 | H59: projected | J59: -0.25 | K59: =K58*(1+J59) | L59: US LOE | M59: 2026E annualizes H1 2026 Opdivo plus Opdivo Qvantig. The scenario then applies material erosion at the disclosed US, EU and Japan exclusivity dates. | N59: https://www.sec.gov/Archives/edgar/data/14272/000001427226000004/bmy-20251231.htm | https://www.bms.com/assets/bms/us/en-us/pdf/investor-info/doc_financials/quarterly_reports/2026/ghBMY-Q2-2026-Earnings-Press-Release.pdf | O59: 7431
A60: OPDIVO_FRANCHISE | B60: Bristol Myers Squibb | C60: Opdivo franchise | D60: nivolumab; includes Opdivo Qvantig from 2025 | E60: Marketed component / IO franchise | F60: 2029 | G60: 2029 | H60: projected | J60: -0.19997309 | K60: =K59*(1+J60) | M60: 2026E annualizes H1 2026 Opdivo plus Opdivo Qvantig. The scenario then applies material erosion at the disclosed US, EU and Japan exclusivity dates. | N60: https://www.sec.gov/Archives/edgar/data/14272/000001427226000004/bmy-20251231.htm | https://www.bms.com/assets/bms/us/en-us/pdf/investor-info/doc_financials/quarterly_reports/2026/ghBMY-Q2-2026-Earnings-Press-Release.pdf | O60: 5945
A61: OPDIVO_FRANCHISE | B61: Bristol Myers Squibb | C61: Opdivo franchise | D61: nivolumab; includes Opdivo Qvantig from 2025 | E61: Marketed component / IO franchise | F61: 2030 | G61: 2030 | H61: projected | J61: -0.24995795 | K61: =K60*(1+J61) | L61: EU LOE | M61: 2026E annualizes H1 2026 Opdivo plus Opdivo Qvantig. The scenario then applies material erosion at the disclosed US, EU and Japan exclusivity dates. | N61: https://www.sec.gov/Archives/edgar/data/14272/000001427226000004/bmy-20251231.htm | https://www.bms.com/assets/bms/us/en-us/pdf/investor-info/doc_financials/quarterly_reports/2026/ghBMY-Q2-2026-Earnings-Press-Release.pdf | O61: 4459
A62: OPDIVO_FRANCHISE | B62: Bristol Myers Squibb | C62: Opdivo franchise | D62: nivolumab; includes Opdivo Qvantig from 2025 | E62: Marketed component / IO franchise | F62: 2031 | G62: 2031 | H62: projected | J62: -0.20004485 | K62: =K61*(1+J62) | L62: Japan LOE | M62: 2026E annualizes H1 2026 Opdivo plus Opdivo Qvantig. The scenario then applies material erosion at the disclosed US, EU and Japan exclusivity dates. | N62: https://www.sec.gov/Archives/edgar/data/14272/000001427226000004/bmy-20251231.htm | https://www.bms.com/assets/bms/us/en-us/pdf/investor-info/doc_financials/quarterly_reports/2026/ghBMY-Q2-2026-Earnings-Press-Release.pdf | O62: 3567
A63: OPDIVO_FRANCHISE | B63: Bristol Myers Squibb | C63: Opdivo franchise | D63: nivolumab; includes Opdivo Qvantig from 2025 | E63: Marketed component / IO franchise | F63: 2032 | G63: 2032 | H63: projected | J63: -0.1000841 | K63: =K62*(1+J63) | M63: 2026E annualizes H1 2026 Opdivo plus Opdivo Qvantig. The scenario then applies material erosion at the disclosed US, EU and Japan exclusivity dates. | N63: https://www.sec.gov/Archives/edgar/data/14272/000001427226000004/bmy-20251231.htm | https://www.bms.com/assets/bms/us/en-us/pdf/investor-info/doc_financials/quarterly_reports/2026/ghBMY-Q2-2026-Earnings-Press-Release.pdf | O63: 3210
A65: OPDUALAG | B65: Bristol Myers Squibb | C65: Opdualag | D65: nivolumab + relatlimab-rmbw | E65: Related marketed fixed-dose combination | F65: 2023 | G65: 2023 | H65: reported | I65: 627 | K65: =I65 | M65: 2026E annualizes H1 2026. A base-case cliff begins around the currently listed 2033-2034 dates; pending patent-term/SPC extensions could delay the decline. | N65: https://www.sec.gov/Archives/edgar/data/14272/000001427226000004/bmy-20251231.htm | https://www.bms.com/assets/bms/us/en-us/pdf/investor-info/doc_financials/quarterly_reports/2026/ghBMY-Q2-2026-Earnings-Press-Release.pdf | O65: 627
A66: OPDUALAG | B66: Bristol Myers Squibb | C66: Opdualag | D66: nivolumab + relatlimab-rmbw | E66: Related marketed fixed-dose combination | F66: 2024 | G66: 2024 | H66: reported | I66: 928 | K66: =I66 | M66: 2026E annualizes H1 2026. A base-case cliff begins around the currently listed 2033-2034 dates; pending patent-term/SPC extensions could delay the decline. | N66: https://www.sec.gov/Archives/edgar/data/14272/000001427226000004/bmy-20251231.htm | https://www.bms.com/assets/bms/us/en-us/pdf/investor-info/doc_financials/quarterly_reports/2026/ghBMY-Q2-2026-Earnings-Press-Release.pdf | O66: 928
A67: OPDUALAG | B67: Bristol Myers Squibb | C67: Opdualag | D67: nivolumab + relatlimab-rmbw | E67: Related marketed fixed-dose combination | F67: 2025 | G67: 2025 | H67: reported | I67: 1185 | K67: =I67 | M67: 2026E annualizes H1 2026. A base-case cliff begins around the currently listed 2033-2034 dates; pending patent-term/SPC extensions could delay the decline. | N67: https://www.sec.gov/Archives/edgar/data/14272/000001427226000004/bmy-20251231.htm | https://www.bms.com/assets/bms/us/en-us/pdf/investor-info/doc_financials/quarterly_reports/2026/ghBMY-Q2-2026-Earnings-Press-Release.pdf | O67: 1185
A68: OPDUALAG | B68: Bristol Myers Squibb | C68: Opdualag | D68: nivolumab + relatlimab-rmbw | E68: Related marketed fixed-dose combination | F68: 2026E | G68: 2026 | H68: projected | J68: 0.086919831 | K68: =K67*(1+J68) | M68: 2026E annualizes H1 2026. A base-case cliff begins around the currently listed 2033-2034 dates; pending patent-term/SPC extensions could delay the decline. | N68: https://www.sec.gov/Archives/edgar/data/14272/000001427226000004/bmy-20251231.htm | https://www.bms.com/assets/bms/us/en-us/pdf/investor-info/doc_financials/quarterly_reports/2026/ghBMY-Q2-2026-Earnings-Press-Release.pdf | O68: 1288
A69: OPDUALAG | B69: Bristol Myers Squibb | C69: Opdualag | D69: nivolumab + relatlimab-rmbw | E69: Related marketed fixed-dose combination | F69: 2027 | G69: 2027 | H69: projected | J69: 0.17857143 | K69: =K68*(1+J69) | M69: 2026E annualizes H1 2026. A base-case cliff begins around the currently listed 2033-2034 dates; pending patent-term/SPC extensions could delay the decline. | N69: https://www.sec.gov/Archives/edgar/data/14272/000001427226000004/bmy-20251231.htm | https://www.bms.com/assets/bms/us/en-us/pdf/investor-info/doc_financials/quarterly_reports/2026/ghBMY-Q2-2026-Earnings-Press-Release.pdf | O69: 1518
A70: OPDUALAG | B70: Bristol Myers Squibb | C70: Opdualag | D70: nivolumab + relatlimab-rmbw | E70: Related marketed fixed-dose combination | F70: 2028 | G70: 2028 | H70: projected | J70: 0.16996047 | K70: =K69*(1+J70) | M70: 2026E annualizes H1 2026. A base-case cliff begins around the currently listed 2033-2034 dates; pending patent-term/SPC extensions could delay the decline. | N70: https://www.sec.gov/Archives/edgar/data/14272/000001427226000004/bmy-20251231.htm | https://www.bms.com/assets/bms/us/en-us/pdf/investor-info/doc_financials/quarterly_reports/2026/ghBMY-Q2-2026-Earnings-Press-Release.pdf | O70: 1776
A71: OPDUALAG | B71: Bristol Myers Squibb | C71: Opdualag | D71: nivolumab + relatlimab-rmbw | E71: Related marketed fixed-dose combination | F71: 2029 | G71: 2029 | H71: projected | J71: 0.13513514 | K71: =K70*(1+J71) | M71: 2026E annualizes H1 2026. A base-case cliff begins around the currently listed 2033-2034 dates; pending patent-term/SPC extensions could delay the decline. | N71: https://www.sec.gov/Archives/edgar/data/14272/000001427226000004/bmy-20251231.htm | https://www.bms.com/assets/bms/us/en-us/pdf/investor-info/doc_financials/quarterly_reports/2026/ghBMY-Q2-2026-Earnings-Press-Release.pdf | O71: 2016
A72: OPDUALAG | B72: Bristol Myers Squibb | C72: Opdualag | D72: nivolumab + relatlimab-rmbw | E72: Related marketed fixed-dose combination | F72: 2030 | G72: 2030 | H72: projected | J72: 0.10019841 | K72: =K71*(1+J72) | M72: 2026E annualizes H1 2026. A base-case cliff begins around the currently listed 2033-2034 dates; pending patent-term/SPC extensions could delay the decline. | N72: https://www.sec.gov/Archives/edgar/data/14272/000001427226000004/bmy-20251231.htm | https://www.bms.com/assets/bms/us/en-us/pdf/investor-info/doc_financials/quarterly_reports/2026/ghBMY-Q2-2026-Earnings-Press-Release.pdf | O72: 2218
A73: OPDUALAG | B73: Bristol Myers Squibb | C73: Opdualag | D73: nivolumab + relatlimab-rmbw | E73: Related marketed fixed-dose combination | F73: 2031 | G73: 2031 | H73: projected | J73: 0.069882777 | K73: =K72*(1+J73) | M73: 2026E annualizes H1 2026. A base-case cliff begins around the currently listed 2033-2034 dates; pending patent-term/SPC extensions could delay the decline. | N73: https://www.sec.gov/Archives/edgar/data/14272/000001427226000004/bmy-20251231.htm | https://www.bms.com/assets/bms/us/en-us/pdf/investor-info/doc_financials/quarterly_reports/2026/ghBMY-Q2-2026-Earnings-Press-Release.pdf | O73: 2373
A74: OPDUALAG | B74: Bristol Myers Squibb | C74: Opdualag | D74: nivolumab + relatlimab-rmbw | E74: Related marketed fixed-dose combination | F74: 2032 | G74: 2032 | H74: projected | J74: 0.040876528 | K74: =K73*(1+J74) | M74: 2026E annualizes H1 2026. A base-case cliff begins around the currently listed 2033-2034 dates; pending patent-term/SPC extensions could delay the decline. | N74: https://www.sec.gov/Archives/edgar/data/14272/000001427226000004/bmy-20251231.htm | https://www.bms.com/assets/bms/us/en-us/pdf/investor-info/doc_financials/quarterly_reports/2026/ghBMY-Q2-2026-Earnings-Press-Release.pdf | O74: 2470
A75: OPDUALAG | B75: Bristol Myers Squibb | C75: Opdualag | D75: nivolumab + relatlimab-rmbw | E75: Related marketed fixed-dose combination | F75: 2033 | G75: 2033 | H75: projected | J75: -0.049797571 | K75: =K74*(1+J75) | L75: EU base date | M75: 2026E annualizes H1 2026. A base-case cliff begins around the currently listed 2033-2034 dates; pending patent-term/SPC extensions could delay the decline. | N75: https://www.sec.gov/Archives/edgar/data/14272/000001427226000004/bmy-20251231.htm | https://www.bms.com/assets/bms/us/en-us/pdf/investor-info/doc_financials/quarterly_reports/2026/ghBMY-Q2-2026-Earnings-Press-Release.pdf | O75: 2347
A76: OPDUALAG | B76: Bristol Myers Squibb | C76: Opdualag | D76: nivolumab + relatlimab-rmbw | E76: Related marketed fixed-dose combination | F76: 2034 | G76: 2034 | H76: projected | J76: -0.19982957 | K76: =K75*(1+J76) | L76: US base date | M76: 2026E annualizes H1 2026. A base-case cliff begins around the currently listed 2033-2034 dates; pending patent-term/SPC extensions could delay the decline. | N76: https://www.sec.gov/Archives/edgar/data/14272/000001427226000004/bmy-20251231.htm | https://www.bms.com/assets/bms/us/en-us/pdf/investor-info/doc_financials/quarterly_reports/2026/ghBMY-Q2-2026-Earnings-Press-Release.pdf | O76: 1878
A77: OPDUALAG | B77: Bristol Myers Squibb | C77: Opdualag | D77: nivolumab + relatlimab-rmbw | E77: Related marketed fixed-dose combination | F77: 2035 | G77: 2035 | H77: projected | J77: -0.20021299 | K77: =K76*(1+J77) | M77: 2026E annualizes H1 2026. A base-case cliff begins around the currently listed 2033-2034 dates; pending patent-term/SPC extensions could delay the decline. | N77: https://www.sec.gov/Archives/edgar/data/14272/000001427226000004/bmy-20251231.htm | https://www.bms.com/assets/bms/us/en-us/pdf/investor-info/doc_financials/quarterly_reports/2026/ghBMY-Q2-2026-Earnings-Press-Release.pdf | O77: 1502
A78: OPDUALAG | B78: Bristol Myers Squibb | C78: Opdualag | D78: nivolumab + relatlimab-rmbw | E78: Related marketed fixed-dose combination | F78: 2036 | G78: 2036 | H78: projected | J78: -0.40013316 | K78: =K77*(1+J78) | L78: Potential US extension | M78: 2026E annualizes H1 2026. A base-case cliff begins around the currently listed 2033-2034 dates; pending patent-term/SPC extensions could delay the decline. | N78: https://www.sec.gov/Archives/edgar/data/14272/000001427226000004/bmy-20251231.htm | https://www.bms.com/assets/bms/us/en-us/pdf/investor-info/doc_financials/quarterly_reports/2026/ghBMY-Q2-2026-Earnings-Press-Release.pdf | O78: 901
A80: BREYANZI | B80: Bristol Myers Squibb | C80: Breyanzi | D80: lisocabtagene maraleucel | E80: B-cell lymphoma cell-therapy benchmark | F80: 2023 | G80: 2023 | H80: reported | I80: 364 | K80: =I80 | M80: 2026E annualizes H1 2026. The scenario assumes continued uptake followed by erosion at the currently disclosed minimum exclusivity date. | N80: https://www.sec.gov/Archives/edgar/data/14272/000001427226000004/bmy-20251231.htm | https://www.bms.com/assets/bms/us/en-us/pdf/investor-info/doc_financials/quarterly_reports/2026/ghBMY-Q2-2026-Earnings-Press-Release.pdf | O80: 364
A81: BREYANZI | B81: Bristol Myers Squibb | C81: Breyanzi | D81: lisocabtagene maraleucel | E81: B-cell lymphoma cell-therapy benchmark | F81: 2024 | G81: 2024 | H81: reported | I81: 747 | K81: =I81 | M81: 2026E annualizes H1 2026. The scenario assumes continued uptake followed by erosion at the currently disclosed minimum exclusivity date. | N81: https://www.sec.gov/Archives/edgar/data/14272/000001427226000004/bmy-20251231.htm | https://www.bms.com/assets/bms/us/en-us/pdf/investor-info/doc_financials/quarterly_reports/2026/ghBMY-Q2-2026-Earnings-Press-Release.pdf | O81: 747
A82: BREYANZI | B82: Bristol Myers Squibb | C82: Breyanzi | D82: lisocabtagene maraleucel | E82: B-cell lymphoma cell-therapy benchmark | F82: 2025 | G82: 2025 | H82: reported | I82: 1358 | K82: =I82 | M82: 2026E annualizes H1 2026. The scenario assumes continued uptake followed by erosion at the currently disclosed minimum exclusivity date. | N82: https://www.sec.gov/Archives/edgar/data/14272/000001427226000004/bmy-20251231.htm | https://www.bms.com/assets/bms/us/en-us/pdf/investor-info/doc_financials/quarterly_reports/2026/ghBMY-Q2-2026-Earnings-Press-Release.pdf | O82: 1358
A83: BREYANZI | B83: Bristol Myers Squibb | C83: Breyanzi | D83: lisocabtagene maraleucel | E83: B-cell lymphoma cell-therapy benchmark | F83: 2026E | G83: 2026 | H83: projected | J83: 0.31958763 | K83: =K82*(1+J83) | M83: 2026E annualizes H1 2026. The scenario assumes continued uptake followed by erosion at the currently disclosed minimum exclusivity date. | N83: https://www.sec.gov/Archives/edgar/data/14272/000001427226000004/bmy-20251231.htm | https://www.bms.com/assets/bms/us/en-us/pdf/investor-info/doc_financials/quarterly_reports/2026/ghBMY-Q2-2026-Earnings-Press-Release.pdf | O83: 1792
A84: BREYANZI | B84: Bristol Myers Squibb | C84: Breyanzi | D84: lisocabtagene maraleucel | E84: B-cell lymphoma cell-therapy benchmark | F84: 2027 | G84: 2027 | H84: projected | J84: 0.19977679 | K84: =K83*(1+J84) | M84: 2026E annualizes H1 2026. The scenario assumes continued uptake followed by erosion at the currently disclosed minimum exclusivity date. | N84: https://www.sec.gov/Archives/edgar/data/14272/000001427226000004/bmy-20251231.htm | https://www.bms.com/assets/bms/us/en-us/pdf/investor-info/doc_financials/quarterly_reports/2026/ghBMY-Q2-2026-Earnings-Press-Release.pdf | O84: 2150
A85: BREYANZI | B85: Bristol Myers Squibb | C85: Breyanzi | D85: lisocabtagene maraleucel | E85: B-cell lymphoma cell-therapy benchmark | F85: 2028 | G85: 2028 | H85: projected | J85: 0.14 | K85: =K84*(1+J85) | M85: 2026E annualizes H1 2026. The scenario assumes continued uptake followed by erosion at the currently disclosed minimum exclusivity date. | N85: https://www.sec.gov/Archives/edgar/data/14272/000001427226000004/bmy-20251231.htm | https://www.bms.com/assets/bms/us/en-us/pdf/investor-info/doc_financials/quarterly_reports/2026/ghBMY-Q2-2026-Earnings-Press-Release.pdf | O85: 2451
A86: BREYANZI | B86: Bristol Myers Squibb | C86: Breyanzi | D86: lisocabtagene maraleucel | E86: B-cell lymphoma cell-therapy benchmark | F86: 2029 | G86: 2029 | H86: projected | J86: 0.07996736 | K86: =K85*(1+J86) | M86: 2026E annualizes H1 2026. The scenario assumes continued uptake followed by erosion at the currently disclosed minimum exclusivity date. | N86: https://www.sec.gov/Archives/edgar/data/14272/000001427226000004/bmy-20251231.htm | https://www.bms.com/assets/bms/us/en-us/pdf/investor-info/doc_financials/quarterly_reports/2026/ghBMY-Q2-2026-Earnings-Press-Release.pdf | O86: 2647
A87: BREYANZI | B87: Bristol Myers Squibb | C87: Breyanzi | D87: lisocabtagene maraleucel | E87: B-cell lymphoma cell-therapy benchmark | F87: 2030 | G87: 2030 | H87: projected | J87: 0.060068002 | K87: =K86*(1+J87) | M87: 2026E annualizes H1 2026. The scenario assumes continued uptake followed by erosion at the currently disclosed minimum exclusivity date. | N87: https://www.sec.gov/Archives/edgar/data/14272/000001427226000004/bmy-20251231.htm | https://www.bms.com/assets/bms/us/en-us/pdf/investor-info/doc_financials/quarterly_reports/2026/ghBMY-Q2-2026-Earnings-Press-Release.pdf | O87: 2806
A88: BREYANZI | B88: Bristol Myers Squibb | C88: Breyanzi | D88: lisocabtagene maraleucel | E88: B-cell lymphoma cell-therapy benchmark | F88: 2031 | G88: 2031 | H88: projected | J88: 0.039914469 | K88: =K87*(1+J88) | M88: 2026E annualizes H1 2026. The scenario assumes continued uptake followed by erosion at the currently disclosed minimum exclusivity date. | N88: https://www.sec.gov/Archives/edgar/data/14272/000001427226000004/bmy-20251231.htm | https://www.bms.com/assets/bms/us/en-us/pdf/investor-info/doc_financials/quarterly_reports/2026/ghBMY-Q2-2026-Earnings-Press-Release.pdf | O88: 2918
A89: BREYANZI | B89: Bristol Myers Squibb | C89: Breyanzi | D89: lisocabtagene maraleucel | E89: B-cell lymphoma cell-therapy benchmark | F89: 2032 | G89: 2032 | H89: projected | J89: 0.030157642 | K89: =K88*(1+J89) | M89: 2026E annualizes H1 2026. The scenario assumes continued uptake followed by erosion at the currently disclosed minimum exclusivity date. | N89: https://www.sec.gov/Archives/edgar/data/14272/000001427226000004/bmy-20251231.htm | https://www.bms.com/assets/bms/us/en-us/pdf/investor-info/doc_financials/quarterly_reports/2026/ghBMY-Q2-2026-Earnings-Press-Release.pdf | O89: 3006
A90: BREYANZI | B90: Bristol Myers Squibb | C90: Breyanzi | D90: lisocabtagene maraleucel | E90: B-cell lymphoma cell-therapy benchmark | F90: 2033 | G90: 2033 | H90: projected | J90: -0.10013307 | K90: =K89*(1+J90) | L90: Current minimum LOE | M90: 2026E annualizes H1 2026. The scenario assumes continued uptake followed by erosion at the currently disclosed minimum exclusivity date. | N90: https://www.sec.gov/Archives/edgar/data/14272/000001427226000004/bmy-20251231.htm | https://www.bms.com/assets/bms/us/en-us/pdf/investor-info/doc_financials/quarterly_reports/2026/ghBMY-Q2-2026-Earnings-Press-Release.pdf | O90: 2705
A91: BREYANZI | B91: Bristol Myers Squibb | C91: Breyanzi | D91: lisocabtagene maraleucel | E91: B-cell lymphoma cell-therapy benchmark | F91: 2034 | G91: 2034 | H91: projected | J91: -0.2 | K91: =K90*(1+J91) | L91: Potential US extension | M91: 2026E annualizes H1 2026. The scenario assumes continued uptake followed by erosion at the currently disclosed minimum exclusivity date. | N91: https://www.sec.gov/Archives/edgar/data/14272/000001427226000004/bmy-20251231.htm | https://www.bms.com/assets/bms/us/en-us/pdf/investor-info/doc_financials/quarterly_reports/2026/ghBMY-Q2-2026-Earnings-Press-Release.pdf | O91: 2164
A93: CAMZYOS | B93: Bristol Myers Squibb | C93: Camzyos | D93: mavacamten | E93: Cardiac-myosin commercial benchmark | F93: 2023 | G93: 2023 | H93: reported | I93: 231 | K93: =I93 | M93: 2026E annualizes H1 2026. The scenario uses a maturing growth curve and applies erosion at the disclosed US patent expiry. | N93: https://www.sec.gov/Archives/edgar/data/14272/000001427226000004/bmy-20251231.htm | https://www.bms.com/assets/bms/us/en-us/pdf/investor-info/doc_financials/quarterly_reports/2026/ghBMY-Q2-2026-Earnings-Press-Release.pdf | O93: 231
A94: CAMZYOS | B94: Bristol Myers Squibb | C94: Camzyos | D94: mavacamten | E94: Cardiac-myosin commercial benchmark | F94: 2024 | G94: 2024 | H94: reported | I94: 602 | K94: =I94 | M94: 2026E annualizes H1 2026. The scenario uses a maturing growth curve and applies erosion at the disclosed US patent expiry. | N94: https://www.sec.gov/Archives/edgar/data/14272/000001427226000004/bmy-20251231.htm | https://www.bms.com/assets/bms/us/en-us/pdf/investor-info/doc_financials/quarterly_reports/2026/ghBMY-Q2-2026-Earnings-Press-Release.pdf | O94: 602
A95: CAMZYOS | B95: Bristol Myers Squibb | C95: Camzyos | D95: mavacamten | E95: Cardiac-myosin commercial benchmark | F95: 2025 | G95: 2025 | H95: reported | I95: 1068 | K95: =I95 | M95: 2026E annualizes H1 2026. The scenario uses a maturing growth curve and applies erosion at the disclosed US patent expiry. | N95: https://www.sec.gov/Archives/edgar/data/14272/000001427226000004/bmy-20251231.htm | https://www.bms.com/assets/bms/us/en-us/pdf/investor-info/doc_financials/quarterly_reports/2026/ghBMY-Q2-2026-Earnings-Press-Release.pdf | O95: 1068
A96: CAMZYOS | B96: Bristol Myers Squibb | C96: Camzyos | D96: mavacamten | E96: Cardiac-myosin commercial benchmark | F96: 2026E | G96: 2026 | H96: projected | J96: 0.36516854 | K96: =K95*(1+J96) | M96: 2026E annualizes H1 2026. The scenario uses a maturing growth curve and applies erosion at the disclosed US patent expiry. | N96: https://www.sec.gov/Archives/edgar/data/14272/000001427226000004/bmy-20251231.htm | https://www.bms.com/assets/bms/us/en-us/pdf/investor-info/doc_financials/quarterly_reports/2026/ghBMY-Q2-2026-Earnings-Press-Release.pdf | O96: 1458
A97: CAMZYOS | B97: Bristol Myers Squibb | C97: Camzyos | D97: mavacamten | E97: Cardiac-myosin commercial benchmark | F97: 2027 | G97: 2027 | H97: projected | J97: 0.2441701 | K97: =K96*(1+J97) | M97: 2026E annualizes H1 2026. The scenario uses a maturing growth curve and applies erosion at the disclosed US patent expiry. | N97: https://www.sec.gov/Archives/edgar/data/14272/000001427226000004/bmy-20251231.htm | https://www.bms.com/assets/bms/us/en-us/pdf/investor-info/doc_financials/quarterly_reports/2026/ghBMY-Q2-2026-Earnings-Press-Release.pdf | O97: 1814
A98: CAMZYOS | B98: Bristol Myers Squibb | C98: Camzyos | D98: mavacamten | E98: Cardiac-myosin commercial benchmark | F98: 2028 | G98: 2028 | H98: projected | J98: 0.18026461 | K98: =K97*(1+J98) | M98: 2026E annualizes H1 2026. The scenario uses a maturing growth curve and applies erosion at the disclosed US patent expiry. | N98: https://www.sec.gov/Archives/edgar/data/14272/000001427226000004/bmy-20251231.htm | https://www.bms.com/assets/bms/us/en-us/pdf/investor-info/doc_financials/quarterly_reports/2026/ghBMY-Q2-2026-Earnings-Press-Release.pdf | O98: 2141
A99: CAMZYOS | B99: Bristol Myers Squibb | C99: Camzyos | D99: mavacamten | E99: Cardiac-myosin commercial benchmark | F99: 2029 | G99: 2029 | H99: projected | J99: 0.12003737 | K99: =K98*(1+J99) | M99: 2026E annualizes H1 2026. The scenario uses a maturing growth curve and applies erosion at the disclosed US patent expiry. | N99: https://www.sec.gov/Archives/edgar/data/14272/000001427226000004/bmy-20251231.htm | https://www.bms.com/assets/bms/us/en-us/pdf/investor-info/doc_financials/quarterly_reports/2026/ghBMY-Q2-2026-Earnings-Press-Release.pdf | O99: 2398
A100: CAMZYOS | B100: Bristol Myers Squibb | C100: Camzyos | D100: mavacamten | E100: Cardiac-myosin commercial benchmark | F100: 2030 | G100: 2030 | H100: projected | J100: 0.080066722 | K100: =K99*(1+J100) | M100: 2026E annualizes H1 2026. The scenario uses a maturing growth curve and applies erosion at the disclosed US patent expiry. | N100: https://www.sec.gov/Archives/edgar/data/14272/000001427226000004/bmy-20251231.htm | https://www.bms.com/assets/bms/us/en-us/pdf/investor-info/doc_financials/quarterly_reports/2026/ghBMY-Q2-2026-Earnings-Press-Release.pdf | O100: 2590
A101: CAMZYOS | B101: Bristol Myers Squibb | C101: Camzyos | D101: mavacamten | E101: Cardiac-myosin commercial benchmark | F101: 2031 | G101: 2031 | H101: projected | J101: 0.05984556 | K101: =K100*(1+J101) | M101: 2026E annualizes H1 2026. The scenario uses a maturing growth curve and applies erosion at the disclosed US patent expiry. | N101: https://www.sec.gov/Archives/edgar/data/14272/000001427226000004/bmy-20251231.htm | https://www.bms.com/assets/bms/us/en-us/pdf/investor-info/doc_financials/quarterly_reports/2026/ghBMY-Q2-2026-Earnings-Press-Release.pdf | O101: 2745
A102: CAMZYOS | B102: Bristol Myers Squibb | C102: Camzyos | D102: mavacamten | E102: Cardiac-myosin commercial benchmark | F102: 2032 | G102: 2032 | H102: projected | J102: 0.04007286 | K102: =K101*(1+J102) | M102: 2026E annualizes H1 2026. The scenario uses a maturing growth curve and applies erosion at the disclosed US patent expiry. | N102: https://www.sec.gov/Archives/edgar/data/14272/000001427226000004/bmy-20251231.htm | https://www.bms.com/assets/bms/us/en-us/pdf/investor-info/doc_financials/quarterly_reports/2026/ghBMY-Q2-2026-Earnings-Press-Release.pdf | O102: 2855
A103: CAMZYOS | B103: Bristol Myers Squibb | C103: Camzyos | D103: mavacamten | E103: Cardiac-myosin commercial benchmark | F103: 2033 | G103: 2033 | H103: projected | J103: 0.030122592 | K103: =K102*(1+J103) | M103: 2026E annualizes H1 2026. The scenario uses a maturing growth curve and applies erosion at the disclosed US patent expiry. | N103: https://www.sec.gov/Archives/edgar/data/14272/000001427226000004/bmy-20251231.htm | https://www.bms.com/assets/bms/us/en-us/pdf/investor-info/doc_financials/quarterly_reports/2026/ghBMY-Q2-2026-Earnings-Press-Release.pdf | O103: 2941
A104: CAMZYOS | B104: Bristol Myers Squibb | C104: Camzyos | D104: mavacamten | E104: Cardiac-myosin commercial benchmark | F104: 2034 | G104: 2034 | H104: projected | J104: 0.029921795 | K104: =K103*(1+J104) | M104: 2026E annualizes H1 2026. The scenario uses a maturing growth curve and applies erosion at the disclosed US patent expiry. | N104: https://www.sec.gov/Archives/edgar/data/14272/000001427226000004/bmy-20251231.htm | https://www.bms.com/assets/bms/us/en-us/pdf/investor-info/doc_financials/quarterly_reports/2026/ghBMY-Q2-2026-Earnings-Press-Release.pdf | O104: 3029
A105: CAMZYOS | B105: Bristol Myers Squibb | C105: Camzyos | D105: mavacamten | E105: Cardiac-myosin commercial benchmark | F105: 2035 | G105: 2035 | H105: projected | J105: 0.02013866 | K105: =K104*(1+J105) | M105: 2026E annualizes H1 2026. The scenario uses a maturing growth curve and applies erosion at the disclosed US patent expiry. | N105: https://www.sec.gov/Archives/edgar/data/14272/000001427226000004/bmy-20251231.htm | https://www.bms.com/assets/bms/us/en-us/pdf/investor-info/doc_financials/quarterly_reports/2026/ghBMY-Q2-2026-Earnings-Press-Release.pdf | O105: 3090
A106: CAMZYOS | B106: Bristol Myers Squibb | C106: Camzyos | D106: mavacamten | E106: Cardiac-myosin commercial benchmark | F106: 2036 | G106: 2036 | H106: projected | J106: -0.2 | K106: =K105*(1+J106) | L106: US LOE | M106: 2026E annualizes H1 2026. The scenario uses a maturing growth curve and applies erosion at the disclosed US patent expiry. | N106: https://www.sec.gov/Archives/edgar/data/14272/000001427226000004/bmy-20251231.htm | https://www.bms.com/assets/bms/us/en-us/pdf/investor-info/doc_financials/quarterly_reports/2026/ghBMY-Q2-2026-Earnings-Press-Release.pdf | O106: 2472
A107: CAMZYOS | B107: Bristol Myers Squibb | C107: Camzyos | D107: mavacamten | E107: Cardiac-myosin commercial benchmark | F107: 2037 | G107: 2037 | H107: projected | J107: -0.40008091 | K107: =K106*(1+J107) | M107: 2026E annualizes H1 2026. The scenario uses a maturing growth curve and applies erosion at the disclosed US patent expiry. | N107: https://www.sec.gov/Archives/edgar/data/14272/000001427226000004/bmy-20251231.htm | https://www.bms.com/assets/bms/us/en-us/pdf/investor-info/doc_financials/quarterly_reports/2026/ghBMY-Q2-2026-Earnings-Press-Release.pdf | O107: 1483
A109: REVLIMID | B109: Bristol Myers Squibb | C109: Revlimid | D109: lenalidomide | E109: Multiple-myeloma franchise benchmark | F109: 2023 | G109: 2023 | H109: reported | I109: 6097 | K109: =I109 | M109: 2026E annualizes H1 2026. The decline reflects unrestricted US generic entry from 31 January 2026 and existing generic competition outside the US. | N109: https://www.sec.gov/Archives/edgar/data/14272/000001427226000004/bmy-20251231.htm | https://www.bms.com/assets/bms/us/en-us/pdf/investor-info/doc_financials/quarterly_reports/2026/ghBMY-Q2-2026-Earnings-Press-Release.pdf | O109: 6097
A110: REVLIMID | B110: Bristol Myers Squibb | C110: Revlimid | D110: lenalidomide | E110: Multiple-myeloma franchise benchmark | F110: 2024 | G110: 2024 | H110: reported | I110: 5773 | K110: =I110 | M110: 2026E annualizes H1 2026. The decline reflects unrestricted US generic entry from 31 January 2026 and existing generic competition outside the US. | N110: https://www.sec.gov/Archives/edgar/data/14272/000001427226000004/bmy-20251231.htm | https://www.bms.com/assets/bms/us/en-us/pdf/investor-info/doc_financials/quarterly_reports/2026/ghBMY-Q2-2026-Earnings-Press-Release.pdf | O110: 5773
...
